Workbook

Sheet DASHBOARD
C1: NexusRH CI — Cahier de Recettes Officiel OpenLab Consulting · v1.0
C3: Mis à jour le 25/10/2026 · Couverture cible : 100% des fonctionnalités · statut vide = non exécuté
A5: RÉSUMÉ PAR MODULE
A6: Module | B6: Total | C6: ✅ Passé | D6: ❌ Échoué | E6: ⚠️ Bloqué | F6: ▶️ En cours | G6: ⬜ Non exécuté | H6: % Réussite | I6: Statut
A7: Authentification | B7: =COUNTA('AUTH'!A:A)-2 | C7: =COUNTIF('AUTH'!I:I,"✅ Passé") | D7: =COUNTIF('AUTH'!I:I,"❌ Échoué") | E7: =COUNTIF('AUTH'!I:I,"⚠️ Bloqué") | F7: =COUNTIF('AUTH'!I:I,"▶️ En cours") | G7: =B7-SUM(C7:F7) | H7: =IF(B7=0,0,C7/B7) | I7: =IF(H7=1,"🟢 Complet",IF(H7>0.7,"🟡 Avancé",IF(H7>0,"🟠 En cours","⬜ À faire")))
A8: Portail Super Admin | B8: =COUNTA('PLT'!A:A)-2 | C8: =COUNTIF('PLT'!I:I,"✅ Passé") | D8: =COUNTIF('PLT'!I:I,"❌ Échoué") | E8: =COUNTIF('PLT'!I:I,"⚠️ Bloqué") | F8: =COUNTIF('PLT'!I:I,"▶️ En cours") | G8: =B8-SUM(C8:F8) | H8: =IF(B8=0,0,C8/B8) | I8: =IF(H8=1,"🟢 Complet",IF(H8>0.7,"🟡 Avancé",IF(H8>0,"🟠 En cours","⬜ À faire")))
A9: Employés & contrats | B9: =COUNTA('EMP'!A:A)-2 | C9: =COUNTIF('EMP'!I:I,"✅ Passé") | D9: =COUNTIF('EMP'!I:I,"❌ Échoué") | E9: =COUNTIF('EMP'!I:I,"⚠️ Bloqué") | F9: =COUNTIF('EMP'!I:I,"▶️ En cours") | G9: =B9-SUM(C9:F9) | H9: =IF(B9=0,0,C9/B9) | I9: =IF(H9=1,"🟢 Complet",IF(H9>0.7,"🟡 Avancé",IF(H9>0,"🟠 En cours","⬜ À faire")))
A10: Paie CI (CNPS+ITS) | B10: =COUNTA('PAY'!A:A)-2 | C10: =COUNTIF('PAY'!I:I,"✅ Passé") | D10: =COUNTIF('PAY'!I:I,"❌ Échoué") | E10: =COUNTIF('PAY'!I:I,"⚠️ Bloqué") | F10: =COUNTIF('PAY'!I:I,"▶️ En cours") | G10: =B10-SUM(C10:F10) | H10: =IF(B10=0,0,C10/B10) | I10: =IF(H10=1,"🟢 Complet",IF(H10>0.7,"🟡 Avancé",IF(H10>0,"🟠 En cours","⬜ À faire")))
A11: Absences & congés | B11: =COUNTA('ABS'!A:A)-2 | C11: =COUNTIF('ABS'!I:I,"✅ Passé") | D11: =COUNTIF('ABS'!I:I,"❌ Échoué") | E11: =COUNTIF('ABS'!I:I,"⚠️ Bloqué") | F11: =COUNTIF('ABS'!I:I,"▶️ En cours") | G11: =B11-SUM(C11:F11) | H11: =IF(B11=0,0,C11/B11) | I11: =IF(H11=1,"🟢 Complet",IF(H11>0.7,"🟡 Avancé",IF(H11>0,"🟠 En cours","⬜ À faire")))
A12: Recrutement | B12: =COUNTA('REC'!A:A)-2 | C12: =COUNTIF('REC'!I:I,"✅ Passé") | D12: =COUNTIF('REC'!I:I,"❌ Échoué") | E12: =COUNTIF('REC'!I:I,"⚠️ Bloqué") | F12: =COUNTIF('REC'!I:I,"▶️ En cours") | G12: =B12-SUM(C12:F12) | H12: =IF(B12=0,0,C12/B12) | I12: =IF(H12=1,"🟢 Complet",IF(H12>0.7,"🟡 Avancé",IF(H12>0,"🟠 En cours","⬜ À faire")))
A13: Sourcing IA | B13: =COUNTA('SRC'!A:A)-2 | C13: =COUNTIF('SRC'!I:I,"✅ Passé") | D13: =COUNTIF('SRC'!I:I,"❌ Échoué") | E13: =COUNTIF('SRC'!I:I,"⚠️ Bloqué") | F13: =COUNTIF('SRC'!I:I,"▶️ En cours") | G13: =B13-SUM(C13:F13) | H13: =IF(B13=0,0,C13/B13) | I13: =IF(H13=1,"🟢 Complet",IF(H13>0.7,"🟡 Avancé",IF(H13>0,"🟠 En cours","⬜ À faire")))
A14: Multi-pays & filiales | B14: =COUNTA('MPF'!A:A)-2 | C14: =COUNTIF('MPF'!I:I,"✅ Passé") | D14: =COUNTIF('MPF'!I:I,"❌ Échoué") | E14: =COUNTIF('MPF'!I:I,"⚠️ Bloqué") | F14: =COUNTIF('MPF'!I:I,"▶️ En cours") | G14: =B14-SUM(C14:F14) | H14: =IF(B14=0,0,C14/B14) | I14: =IF(H14=1,"🟢 Complet",IF(H14>0.7,"🟡 Avancé",IF(H14>0,"🟠 En cours","⬜ À faire")))
A15: Formation / FDFP | B15: =COUNTA('FRM'!A:A)-2 | C15: =COUNTIF('FRM'!I:I,"✅ Passé") | D15: =COUNTIF('FRM'!I:I,"❌ Échoué") | E15: =COUNTIF('FRM'!I:I,"⚠️ Bloqué") | F15: =COUNTIF('FRM'!I:I,"▶️ En cours") | G15: =B15-SUM(C15:F15) | H15: =IF(B15=0,0,C15/B15) | I15: =IF(H15=1,"🟢 Complet",IF(H15>0.7,"🟡 Avancé",IF(H15>0,"🟠 En cours","⬜ À faire")))
A16: Notes de Frais | B16: =COUNTA('FRA'!A:A)-2 | C16: =COUNTIF('FRA'!I:I,"✅ Passé") | D16: =COUNTIF('FRA'!I:I,"❌ Échoué") | E16: =COUNTIF('FRA'!I:I,"⚠️ Bloqué") | F16: =COUNTIF('FRA'!I:I,"▶️ En cours") | G16: =B16-SUM(C16:F16) | H16: =IF(B16=0,0,C16/B16) | I16: =IF(H16=1,"🟢 Complet",IF(H16>0.7,"🟡 Avancé",IF(H16>0,"🟠 En cours","⬜ À faire")))
A17: Carrières | B17: =COUNTA('CAR'!A:A)-2 | C17: =COUNTIF('CAR'!I:I,"✅ Passé") | D17: =COUNTIF('CAR'!I:I,"❌ Échoué") | E17: =COUNTIF('CAR'!I:I,"⚠️ Bloqué") | F17: =COUNTIF('CAR'!I:I,"▶️ En cours") | G17: =B17-SUM(C17:F17) | H17: =IF(B17=0,0,C17/B17) | I17: =IF(H17=1,"🟢 Complet",IF(H17>0.7,"🟡 Avancé",IF(H17>0,"🟠 En cours","⬜ À faire")))
A18: CNPS & DISA | B18: =COUNTA('CNP'!A:A)-2 | C18: =COUNTIF('CNP'!I:I,"✅ Passé") | D18: =COUNTIF('CNP'!I:I,"❌ Échoué") | E18: =COUNTIF('CNP'!I:I,"⚠️ Bloqué") | F18: =COUNTIF('CNP'!I:I,"▶️ En cours") | G18: =B18-SUM(C18:F18) | H18: =IF(B18=0,0,C18/B18) | I18: =IF(H18=1,"🟢 Complet",IF(H18>0.7,"🟡 Avancé",IF(H18>0,"🟠 En cours","⬜ À faire")))
A19: Mobile Money & virements | B19: =COUNTA('MM'!A:A)-2 | C19: =COUNTIF('MM'!I:I,"✅ Passé") | D19: =COUNTIF('MM'!I:I,"❌ Échoué") | E19: =COUNTIF('MM'!I:I,"⚠️ Bloqué") | F19: =COUNTIF('MM'!I:I,"▶️ En cours") | G19: =B19-SUM(C19:F19) | H19: =IF(B19=0,0,C19/B19) | I19: =IF(H19=1,"🟢 Complet",IF(H19>0.7,"🟡 Avancé",IF(H19>0,"🟠 En cours","⬜ À faire")))
A20: Assistant IA | B20: =COUNTA('AI'!A:A)-2 | C20: =COUNTIF('AI'!I:I,"✅ Passé") | D20: =COUNTIF('AI'!I:I,"❌ Échoué") | E20: =COUNTIF('AI'!I:I,"⚠️ Bloqué") | F20: =COUNTIF('AI'!I:I,"▶️ En cours") | G20: =B20-SUM(C20:F20) | H20: =IF(B20=0,0,C20/B20) | I20: =IF(H20=1,"🟢 Complet",IF(H20>0.7,"🟡 Avancé",IF(H20>0,"🟠 En cours","⬜ À faire")))
A21: Reporting & Vue DG | B21: =COUNTA('REP'!A:A)-2 | C21: =COUNTIF('REP'!I:I,"✅ Passé") | D21: =COUNTIF('REP'!I:I,"❌ Échoué") | E21: =COUNTIF('REP'!I:I,"⚠️ Bloqué") | F21: =COUNTIF('REP'!I:I,"▶️ En cours") | G21: =B21-SUM(C21:F21) | H21: =IF(B21=0,0,C21/B21) | I21: =IF(H21=1,"🟢 Complet",IF(H21>0.7,"🟡 Avancé",IF(H21>0,"🟠 En cours","⬜ À faire")))
A22: Paramètres | B22: =COUNTA('SET'!A:A)-2 | C22: =COUNTIF('SET'!I:I,"✅ Passé") | D22: =COUNTIF('SET'!I:I,"❌ Échoué") | E22: =COUNTIF('SET'!I:I,"⚠️ Bloqué") | F22: =COUNTIF('SET'!I:I,"▶️ En cours") | G22: =B22-SUM(C22:F22) | H22: =IF(B22=0,0,C22/B22) | I22: =IF(H22=1,"🟢 Complet",IF(H22>0.7,"🟡 Avancé",IF(H22>0,"🟠 En cours","⬜ À faire")))
A23: RBAC | B23: =COUNTA('RBA'!A:A)-2 | C23: =COUNTIF('RBA'!I:I,"✅ Passé") | D23: =COUNTIF('RBA'!I:I,"❌ Échoué") | E23: =COUNTIF('RBA'!I:I,"⚠️ Bloqué") | F23: =COUNTIF('RBA'!I:I,"▶️ En cours") | G23: =B23-SUM(C23:F23) | H23: =IF(B23=0,0,C23/B23) | I23: =IF(H23=1,"🟢 Complet",IF(H23>0.7,"🟡 Avancé",IF(H23>0,"🟠 En cours","⬜ À faire")))
A24: Espace Employé | B24: =COUNTA('ESP'!A:A)-2 | C24: =COUNTIF('ESP'!I:I,"✅ Passé") | D24: =COUNTIF('ESP'!I:I,"❌ Échoué") | E24: =COUNTIF('ESP'!I:I,"⚠️ Bloqué") | F24: =COUNTIF('ESP'!I:I,"▶️ En cours") | G24: =B24-SUM(C24:F24) | H24: =IF(B24=0,0,C24/B24) | I24: =IF(H24=1,"🟢 Complet",IF(H24>0.7,"🟡 Avancé",IF(H24>0,"🟠 En cours","⬜ À faire")))
A25: Workflows & validations | B25: =COUNTA('WF'!A:A)-2 | C25: =COUNTIF('WF'!I:I,"✅ Passé") | D25: =COUNTIF('WF'!I:I,"❌ Échoué") | E25: =COUNTIF('WF'!I:I,"⚠️ Bloqué") | F25: =COUNTIF('WF'!I:I,"▶️ En cours") | G25: =B25-SUM(C25:F25) | H25: =IF(B25=0,0,C25/B25) | I25: =IF(H25=1,"🟢 Complet",IF(H25>0.7,"🟡 Avancé",IF(H25>0,"🟠 En cours","⬜ À faire")))
A26: Temps & pointage | B26: =COUNTA('TPS'!A:A)-2 | C26: =COUNTIF('TPS'!I:I,"✅ Passé") | D26: =COUNTIF('TPS'!I:I,"❌ Échoué") | E26: =COUNTIF('TPS'!I:I,"⚠️ Bloqué") | F26: =COUNTIF('TPS'!I:I,"▶️ En cours") | G26: =B26-SUM(C26:F26) | H26: =IF(B26=0,0,C26/B26) | I26: =IF(H26=1,"🟢 Complet",IF(H26>0.7,"🟡 Avancé",IF(H26>0,"🟠 En cours","⬜ À faire")))
A27: Talents & organisation | B27: =COUNTA('TAL'!A:A)-2 | C27: =COUNTIF('TAL'!I:I,"✅ Passé") | D27: =COUNTIF('TAL'!I:I,"❌ Échoué") | E27: =COUNTIF('TAL'!I:I,"⚠️ Bloqué") | F27: =COUNTIF('TAL'!I:I,"▶️ En cours") | G27: =B27-SUM(C27:F27) | H27: =IF(B27=0,0,C27/B27) | I27: =IF(H27=1,"🟢 Complet",IF(H27>0.7,"🟡 Avancé",IF(H27>0,"🟠 En cours","⬜ À faire")))
A28: Onboarding / Offboarding | B28: =COUNTA('OFF'!A:A)-2 | C28: =COUNTIF('OFF'!I:I,"✅ Passé") | D28: =COUNTIF('OFF'!I:I,"❌ Échoué") | E28: =COUNTIF('OFF'!I:I,"⚠️ Bloqué") | F28: =COUNTIF('OFF'!I:I,"▶️ En cours") | G28: =B28-SUM(C28:F28) | H28: =IF(B28=0,0,C28/B28) | I28: =IF(H28=1,"🟢 Complet",IF(H28>0.7,"🟡 Avancé",IF(H28>0,"🟠 En cours","⬜ À faire")))
A29: Intégrations & sécurité | B29: =COUNTA('INT'!A:A)-2 | C29: =COUNTIF('INT'!I:I,"✅ Passé") | D29: =COUNTIF('INT'!I:I,"❌ Échoué") | E29: =COUNTIF('INT'!I:I,"⚠️ Bloqué") | F29: =COUNTIF('INT'!I:I,"▶️ En cours") | G29: =B29-SUM(C29:F29) | H29: =IF(B29=0,0,C29/B29) | I29: =IF(H29=1,"🟢 Complet",IF(H29>0.7,"🟡 Avancé",IF(H29>0,"🟠 En cours","⬜ À faire")))
A30: Configuration tenant | B30: =COUNTA('CFG'!A:A)-2 | C30: =COUNTIF('CFG'!I:I,"✅ Passé") | D30: =COUNTIF('CFG'!I:I,"❌ Échoué") | E30: =COUNTIF('CFG'!I:I,"⚠️ Bloqué") | F30: =COUNTIF('CFG'!I:I,"▶️ En cours") | G30: =B30-SUM(C30:F30) | H30: =IF(B30=0,0,C30/B30) | I30: =IF(H30=1,"🟢 Complet",IF(H30>0.7,"🟡 Avancé",IF(H30>0,"🟠 En cours","⬜ À faire")))
A31: Cabinet de recrutement | B31: =COUNTA('CAB'!A:A)-2 | C31: =COUNTIF('CAB'!I:I,"✅ Passé") | D31: =COUNTIF('CAB'!I:I,"❌ Échoué") | E31: =COUNTIF('CAB'!I:I,"⚠️ Bloqué") | F31: =COUNTIF('CAB'!I:I,"▶️ En cours") | G31: =B31-SUM(C31:F31) | H31: =IF(B31=0,0,C31/B31) | I31: =IF(H31=1,"🟢 Complet",IF(H31>0.7,"🟡 Avancé",IF(H31>0,"🟠 En cours","⬜ À faire")))
A32: End-to-End | B32: =COUNTA('E2E'!A:A)-2 | C32: =COUNTIF('E2E'!I:I,"✅ Passé") | D32: =COUNTIF('E2E'!I:I,"❌ Échoué") | E32: =COUNTIF('E2E'!I:I,"⚠️ Bloqué") | F32: =COUNTIF('E2E'!I:I,"▶️ En cours") | G32: =B32-SUM(C32:F32) | H32: =IF(B32=0,0,C32/B32) | I32: =IF(H32=1,"🟢 Complet",IF(H32>0.7,"🟡 Avancé",IF(H32>0,"🟠 En cours","⬜ À faire")))
A33: TOTAL GLOBAL | B33: =SUM(B7:B32) | C33: =SUM(C7:C32) | D33: =SUM(D7:D32) | E33: =SUM(E7:E32) | F33: =SUM(F7:F32) | G33: =SUM(G7:G32) | H33: =IF(B33=0,0,C33/B33)
A34: « ⬜ Non exécuté » = Total − (Passé + Échoué + Bloqué + En cours) : inclut les scénarios au statut vide.
A36: INDICATEURS CLÉS EN TEMPS RÉEL
A37: Total scénarios | B37: ✅ Passés | C37: ❌ Échoués | D37: ⚠️ Bloqués | E37: ▶️ En cours | F37: ⬜ Non exécutés | G37: % Réussite | H37: Couverture
A38: =B33 | B38: =C33 | C38: =D33 | D38: =E33 | E38: =F33 | F38: =G33 | G38: =H33 | H38: =IF(B33=0,"0%",TEXT(1-G33/B33,"0%"))

Sheet GUIDE
A1: MODE D'EMPLOI — NexusRH CI Cahier de Recettes
A3: STATUTS DE TEST
A4: Statut | B4: Signification | C4: Couleur
A5: ✅ Passé | B5: Test exécuté et résultat conforme | C5: Vert
A6: ❌ Échoué | B6: Résultat non conforme — bug identifié | C6: Rouge
A7: ⚠️ Bloqué | B7: Test non exécutable (dépendance manquante) | C7: Jaune
A8: ▶️ En cours | B8: Test en cours d'exécution | C8: Bleu
A9: ⬜ Non exécuté | B9: Test planifié, pas encore démarré | C9: Gris
A11: PRIORITÉS
A12: P1 — Critique | B12: Fonctionnalité bloquante, doit passer avant release | C12: Rouge foncé
A13: P2 — Haute | B13: Fonctionnalité importante, impact élevé si KO | C13: Amber
A14: P3 — Moyenne | B14: Fonctionnalité utile, contournement possible | C14: Bleu
A15: P4 — Basse | B15: Amélioration ou cas limite | C15: Vert
A17: REQUALIFICATION EN TICKET
A18: Colonne 'Ticket / Requalification' | B18: Saisir le numéro de ticket (ex: NRH-123)
A19: Commentaire / Amélioration | B19: Détailler le comportement observé et suggestion
A21: WORKFLOW DE TEST
A22: 1. Sélectionner le module (onglet) | B22: Chaque onglet = un module fonctionnel
A23: 2. Exécuter chaque scénario | B23: Suivre les étapes détaillées
A24: 3. Mettre à jour le Statut (colonne I) | B24: Dropdown avec les 5 statuts
A25: 4. Saisir Résultat obtenu (colonne H) | B25: Comportement réel observé
A26: 5. Créer un ticket si Échoué/Bloqué | B26: Saisir référence dans colonne M
A27: 6. Le DASHBOARD se met à jour automatiquement | B27: Formules COUNTIF dynamiques
A29: COMPTES DE TEST
A30: superadmin@nexusrh-ci.com / SuperAdmin1234! | B30: Super Admin Plateforme → /platform/dashboard
A31: admin@sotra.ci / Admin1234! | B31: Admin SOTRA → /dashboard (thème orange)
A32: rh@sotra.ci / Admin1234! | B32: RH Manager SOTRA → /dashboard
A33: manager@sotra.ci / Admin1234! | B33: Manager SOTRA → /dashboard équipe
A34: employe@sotra.ci / Admin1234! | B34: Employé SOTRA → /mon-espace
A35: admin@cabinet-expertise.ci / Admin1234! | B35: Admin Cabinet Expertise CI → /dashboard
A36: employe2@cabinet-expertise.ci / Admin1234! | B36: Employé Cabinet → /mon-espace
A37: coulwao@gmail.com / Openlab2025! | B37: Admin OpenLab Consulting → /dashboard
A39: URL PRODUCTION
A40: https://nexusrh.openlabconsulting.com | B40: Application web NexusRH CI
A41: https://nexusrh.openlabconsulting.com/api/docs | B41: Swagger API (debug)
A43: COMPTES DE TEST COMPLÉMENTAIRES (SOTRA)
A44: chef.perso@sotra.ci | B44: Chargé RH (hr_officer) « Chef Personnel » — mot de passe démo identique à rh@sotra.ci
A45: dg@sotra.ci | B45: Directeur Général (rôle dg, Vue 360° — module dg_view à activer)
A46: Compte raf_site / readonly | B46: À créer dans Paramètres → Utilisateurs si nécessaire (scénarios RBA / PAY multi-filiales)
A48: CAMPAGNE 10/2026 — NOUVEAUX ONGLETS
A49: WF | B49: Workflows & validations
A50: TPS | B50: Temps & pointage (badgeuse)
A51: TAL | B51: Talents & organisation
A52: OFF | B52: Intégration (onboarding) & sorties (offboarding)
A53: INT | B53: Intégrations, signature & sécurité
A54: CFG | B54: Configuration tenant (modules, pays, champs, langue)
A55: CAB | B55: Cabinet de recrutement (agency)
A56: Nouveaux scénarios | B56: Ajoutés en fin de chaque onglet existant, Sprint « Recette 10/2026 », statut vide = non exécuté
A57: PAY-007 à PAY-015 | B57: Ancien barème ITS (abattement 15 %, crédits d'impôt) — remplacé par la réforme ITS 2024 : voir les scénarios [ITS 2024] de PAY

Sheet AUTH
A1: AUTHENTIFICATION & SÉCURITÉ · 29 scénarios
A2: ID Test | B2: Priorité | C2: Titre du scénario | D2: Description / Contexte | E2: Prérequis / Données | F2: Étapes détaillées | G2: Résultat attendu | H2: Résultat obtenu | I2: Statut | J2: Testeur | K2: Date test | L2: Durée (min) | M2: Ticket / Requalification | N2: Commentaire / Amélioration | O2: Sprint | P2: Env.
A3: AUTH-001 | B3: P1 — Critique | C3: Login super_admin valide | D3: Connexion avec superadmin@nexusrh-ci.com / SuperAdmin1234! | E3: API déployée, DB seedée | F3: 1. Ouvrir nexusrh.openlabconsulting.com 2. Saisir email + mdp 3. Cliquer Connexion | G3: Token JWT reçu, redirection vers /platform/dashboard, sidebar plateforme affichée | H3: HTTP 200, JWT role=super_admin / schema=platform, redirectTo=/platform/dashboard ; sidebar plateforme (PlatformLayout sous PlatformGuard). Verifie en live prod. | I3: ✅ Passé | J3: Agents IA (live prod + code) | K3: 23/06/2026 | O3: Sprint 1 | P3: Production
A4: AUTH-002 | B4: P1 — Critique | C4: Login admin tenant valide | D4: Connexion admin@sotra.ci / Admin1234! | E4: Tenant SOTRA seedé | F4: 1. Saisir admin@sotra.ci 2. Saisir Admin1234! 3. Cliquer Connexion | G4: Redirection /dashboard, thème orange SOTRA appliqué, sidebar RH complète | H4: HTTP 200, JWT role=admin / schema=tenant_sotra ; tenantConfig orange primaryColor #E85D04 applique au login (authStore), redirect /dashboard + sidebar RH complete. NB: changement de mot de passe force au 1er login (post-reset demo). | I4: ✅ Passé | J4: Agents IA (live prod + code) | K4: 23/06/2026 | O4: Sprint 1 | P4: Production
A5: AUTH-003 | B5: P1 — Critique | C5: Login mot de passe incorrect → message d'erreur visible | D5: Vérifier que le message 401 remonte au formulaire (plus de rechargement silencieux) | E5: Correctif intercepteur 401 déployé | F5: 1. Saisir un email valide 2. Saisir un mauvais mot de passe 3. Soumettre | G5: Message 'Email ou mot de passe incorrect' affiché dans le formulaire, pas de rechargement de page | H5: 401 'Email ou mot de passe incorrect' ; intercepteur axios exclut /auth/* donc message affiche dans le formulaire sans rechargement (message UI generique anti-enumeration OWASP A07). | I5: ✅ Passé | J5: Agents IA (live prod + code) | K5: 23/06/2026 | O5: Sprint 1 | P5: Production
A6: AUTH-004 | B6: P2 — Haute | C6: Login email inexistant | D6: Email qui n'existe dans aucun tenant | F6: 1. Saisir email@inconnu.com 2. Mdp quelconque 3. Soumettre | G6: Message d'erreur 401 affiché sans plantage | H6: Email inexistant donne 401 message generique identique au mauvais mot de passe (anti-enumeration ; bcrypt dummy temps constant) ; corps malforme donne 400 propre, aucun 500. | I6: ✅ Passé | J6: Agents IA (live prod + code) | K6: 23/06/2026 | O6: Sprint 1 | P6: Production
A7: AUTH-005 | B7: P1 — Critique | C7: Redirection rôle employee → /mon-espace | D7: employe@sotra.ci doit atterrir sur son espace | E7: Seed SOTRA OK | F7: 1. Connecter employe@sotra.ci 2. Observar la redirection | G7: Redirection automatique vers /mon-espace, sidebar réduite (5 items seulement) | H7: HTTP 200, JWT role=employee / schema=tenant_sotra ; redirect /mon-espace + sidebar self-service reduite dediee (10 items, tous /mon-espace) ; RoleGuard bloque /employees, /payroll, /reporting. | I7: ✅ Passé | J7: Agents IA (live prod + code) | K7: 23/06/2026 | O7: Sprint 1 | P7: Production
A8: AUTH-006 | B8: P1 — Critique | C8: Redirection rôle manager → /dashboard | D8: manager@sotra.ci → /dashboard version manager | F8: 1. Connecter manager@sotra.ci 2. Observer dashboard | G8: Dashboard manager affiché (équipe, demandes à valider), pas les KPIs admin | H8: HTTP 200, JWT role=manager/tenant_sotra ; redirect /dashboard qui rend la variante ManagerDashboard (mon equipe + demandes a valider), sans KPIs admin (requete /payroll desactivee). | I8: ✅ Passé | J8: Agents IA (live prod + code) | K8: 23/06/2026 | O8: Sprint 1 | P8: Production
A9: AUTH-007 | B9: P1 — Critique | C9: Redirection super_admin → /platform/dashboard | D9: Aucun accès aux données RH | F9: 1. Connecter superadmin@nexusrh-ci.com 2. Tenter /dashboard | G9: Redirigé vers /platform/dashboard, sidebar plateforme uniquement | H9: CORRIGE: la route /dashboard n'avait aucune garde -> super_admin pouvait y acceder (coquille vide, aucune fuite car API 403). Ajout RhDashboardGuard (super_admin -> /platform/dashboard, employee -> /mon-espace). Verifie code + typecheck. | I9: ✅ Passé | J9: Agents IA + correctif | K9: 23/06/2026 | O9: Sprint 1 | P9: Production
A10: AUTH-008 | B10: P2 — Haute | C10: Refresh automatique token JWT expiré | D10: Le refresh token permet de renouveler le JWT sans déconnexion | E10: Token expiré simulé | F10: 1. Connecter 2. Attendre expiration JWT ou modifier exp dans DevTools 3. Effectuer une requête API | G10: Token rafraîchi silencieusement, requête relancée, utilisateur non déconnecté | H10: CORRIGE + CONFIRME LIVE: flux refresh token rotatif (login -> refreshToken 64 hex ; POST /auth/refresh-token -> nouveau JWT valide + nouveau refreshToken, ancien revoque=401). REGRESSION detectee a AUTH-015 et corrigee: ne plus emettre de refresh token si pwdResetRequired/mfaPending (sinon contournement du garde) + re-verif expiration au refresh. | I10: ✅ Passé | J10: Agents IA + correctif | K10: 23/06/2026 | O10: Sprint 1 | P10: Production
A11: AUTH-009 | B11: P2 — Haute | C11: Déconnexion propre | D11: Store Zustand vidé, redirection /login | E11: Session active | F11: 1. Cliquer sur Déconnexion 2. Vérifier localStorage/sessionStorage | G11: Token supprimé, store authStore vidé, redirection /login, route protégée inaccessible | H11: Deconnexion vide entierement authStore (token/user/tenantConfig/refreshToken), supprime la cle localStorage nexusrhci-auth, purge le cache React Query, guards reactifs -> /login. | I11: ✅ Passé | J11: Agents IA (live prod + code) | K11: 23/06/2026 | O11: Sprint 1 | P11: Production
A12: AUTH-010 | B12: P1 — Critique | C12: Route protégée sans token → /login | D12: Un utilisateur non connecté tente d'accéder /dashboard | F12: 1. Sans session, accéder directement à /dashboard | G12: Redirection automatique vers /login | H12: Sans token, AuthGuard redirige /dashboard (et toute route protegee) vers /login via Navigate replace ; aucune route protegee accessible sans session ; pas de page blanche. | I12: ✅ Passé | J12: Agents IA (live prod + code) | K12: 23/06/2026 | O12: Sprint 1 | P12: Production
A13: AUTH-011 | B13: P2 — Haute | C13: must_change_password = false après seed | D13: Les comptes seedés n'exigent pas de changement de mdp | E13: Seed v2 avec last_login_at déployé | F13: 1. Connecter n'importe quel compte seedé | G13: Connexion directe au dashboard, pas de popup changement de mot de passe | H13: COMPORTEMENT ATTENDU (decision recette): le controle HIBP force le changement quand le mdp est compromis (Admin1234! dans HIBP) -> bonne pratique securite. La logique last_login_at est correcte. Scenario a reformuler (le critere 'must_change_password=false' suppose un mdp non compromis). | I13: ✅ Passé | J13: Agents IA (live prod + code) | K13: 23/06/2026 | O13: Sprint 1 | P13: Production
A14: AUTH-012 | B14: P3 — Moyenne | C14: Activation MFA (QR code TOTP) | D14: L'utilisateur active la double authentification | F14: 1. Mon profil → Sécurité → Activer MFA 2. Scanner QR code avec app TOTP 3. Valider avec code | G14: MFA activé, codes de secours affichés, connexion suivante demande OTP | H14: Code MFA TOTP conforme: secret + QR (data URL) + 10 backup codes hashes bcrypt12 ; mfa_enabled active seulement apres validation d'un code ; login d'un compte mfa_enabled renvoie un challenge 202. Parcours scan-QR / saisie-OTP a valider manuellement en UI. | I14: ⚠️ Bloqué | J14: Agents IA (live prod + code) | K14: 23/06/2026 | O14: Sprint 1 | P14: Production
A15: AUTH-013 | B15: P2 — Haute | C15: MFA code OTP valide | D15: Connexion avec MFA activé | E15: MFA activé sur le compte | F15: 1. Connecter 2. Saisir code TOTP valide | G15: Accès accordé, token JWT émis | H15: Flux TOTP->JWT conforme: login mfa_enabled -> 202 challenge (sans JWT), /auth/mfa/login-verify valide via otplib (fenetre +-1 step) + anti-rejeu Redis (consumeTotpStep) + backup codes consommes 1x, puis emet le JWT final. Non testable live (aucun compte MFA seede). | I15: ⚠️ Bloqué | J15: Agents IA (live prod + code) | K15: 23/06/2026 | O15: Sprint 1 | P15: Production
A16: AUTH-014 | B16: P2 — Haute | C16: MFA code OTP invalide → rejet | E16: MFA activé | F16: 1. Connecter 2. Saisir code TOTP périmé ou incorrect | G16: Erreur 401, message explicite, pas de token émis | H16: Code TOTP invalide -> 401 'Code MFA invalide', AUCUN token emis (garde avant jwt.sign) ; anti-rejeu (step deja consomme refuse) ; rate-limit 10/15min ; challenge expire -> 401 ; body malforme -> 400 (Zod strict), aucun 500. | I16: ✅ Passé | J16: Agents IA (live prod + code) | K16: 23/06/2026 | O16: Sprint 1 | P16: Production
A17: AUTH-015 | B17: P1 — Critique | C17: Isolation multi-tenant | D17: Token SOTRA ne donne pas accès aux données Cabinet Expertise CI | E17: 2 tenants seedés | F17: 1. Connecter admin@sotra.ci 2. Inspecter les requêtes API 3. Tenter d'appeler /api/employees avec schéma cabinet | G17: 403 Forbidden ou données vides, jamais de fuite cross-tenant | H17: Isolation parfaite: le schema tenant est derive UNIQUEMENT du JWT signe (request.user.schemaName), tentative d'override par header X-Schema/?schema ignoree (renvoie toujours SOTRA) ; donnees SOTRA vs Cabinet disjointes (/auth/me tenantId differents) ; zero fuite cross-tenant. | I17: ✅ Passé | J17: Agents IA (live prod + code) | K17: 23/06/2026 | O17: Sprint 1 | P17: Production
A18: AUTH-016 | B18: P1 — Critique | C18: [NON-REGRESSION] Seed DO UPDATE password_hash | D18: Régression résolue 2026-05-15 : seed ON CONFLICT DO NOTHING ne rafraîchissait pas les hashes SOTRA/Cabinet (login 401 sur tous les comptes) | E18: Re-seed exécuté en prod | F18: 1. kubectl apply seed-job-prod.yaml ou pnpm run db:seed 2. Tenter login admin@sotra.ci / Admin1234! | G18: Login OK 200 — le seed met à jour password_hash si l'utilisateur existe déjà | H18: Login admin@sotra.ci 200 apres re-seed du deploiement ; le seed fait ON CONFLICT (email) DO UPDATE SET password_hash pour les users tenant (rafraichit le hash, anti-regression DO NOTHING). super_admin reste DO NOTHING = choix delibere documente. | I18: ✅ Passé | J18: Agents IA (live prod + code) | K18: 23/06/2026 | O18: Sprint 1 | P18: Production
A19: AUTH-017 | B19: P1 — Critique | C19: [NON-REGRESSION] Script reset-admin-passwords.sql | D19: Récupération prod sans rebuild — applique 8 UPDATE bcrypt 12 rounds | E19: Accès kubectl prod | F19: 1. kubectl exec -i postgres-0 -- psql -U nexusrh -d nexusrh < scripts/reset-admin-passwords.sql 2. Vérifier les is_active=true 3. Login admin@sotra.ci | G19: 8 lignes UPDATE OK, login fonctionnel sur les 8 comptes documentés | H19: CORRIGE: le script scripts/reset-admin-passwords.sql ne mettait pas password_changed_at=now() -> ne levait pas l'expiration mdp (le .ts canonique le faisait). Ajoute password_changed_at=now() aux 8 UPDATE. 8 UPDATE (= attendu) + is_active=true + login admin@sotra.ci 200. | I19: ✅ Passé | J19: Agents IA + correctif | K19: 23/06/2026 | O19: Sprint 1 | P19: Production
A20: AUTH-018 | B20: P2 — Haute | C20: [NON-REGRESSION] Script reset-admin-passwords.ts standalone | D20: pnpm run admin:reset-passwords:dry-run puis admin:reset-passwords | E20: DB locale ou prod accessible | F20: 1. pnpm --filter @nexusrhci/api run admin:reset-passwords:dry-run 2. Vérifier la liste des comptes ciblés 3. Lancer admin:reset-passwords | G20: Mode dry-run liste les 8 cibles. Lancement réel : ✓ pour chaque compte. Bcrypt 12 rounds, OWASP A02 respecté | H20: Dry-run liste 17 cibles sans ecrire ; bcrypt 12 rounds (OWASP A02) ; SET is_active=true + password_changed_at=now() ; comptes reels (super_admin, OpenLab) proteges sauf RESET_REAL_ACCOUNTS=true ; double garde FORCE_RESET_PROD requise en prod. | I20: ✅ Passé | J20: Agents IA (live prod + code) | K20: 23/06/2026 | O20: Sprint 1 | P20: Production
A21: AUTH-019 | B21: P1 — Critique | C21: Mot de passe oublié — demande de lien | D21: Flux « Mot de passe oublié » depuis /login (POST /auth/forgot-password). | E21: Compte employe@sotra.ci actif, SMTP tenant ou plateforme opérationnel | F21: 1. /login → « Mot de passe oublié ? » 2. Saisir employe@sotra.ci → Envoyer 3. Répéter avec un email inexistant (inconnu@sotra.ci) | G21: Même message neutre dans les 2 cas (pas d'énumération) ; email reçu pour le compte existant avec lien /reset-password à jeton à durée limitée | O21: Recette 10/2026 | P21: Production
A22: AUTH-020 | B22: P1 — Critique | C22: Réinitialisation du mot de passe via le lien | D22: POST /auth/reset-password avec jeton reçu par email. | E22: Lien de réinitialisation reçu (scénario précédent) | F22: 1. Ouvrir le lien /reset-password?token=… 2. Saisir un mot de passe conforme à la politique 3. Se connecter avec le nouveau mot de passe 4. Réutiliser le même lien une 2e fois | G22: Mot de passe changé, login OK ; le jeton est à usage unique (2e usage refusé avec message clair) ; jeton expiré refusé | O22: Recette 10/2026 | P22: Production
A23: AUTH-021 | B23: P1 — Critique | C23: Verrouillage du compte après N échecs | D23: Verrouillage paramétrable (account-lockout) câblé au login. | E23: Seuil configuré dans Plateforme → Paramètres (ex. 5 tentatives) | F23: 1. Se tromper 5 fois de mot de passe sur chef.perso@sotra.ci 2. Tenter avec le bon mot de passe 3. Attendre la durée de verrouillage puis réessayer | G23: Après le seuil : message « compte temporairement verrouillé » même avec le bon mot de passe ; déverrouillage automatique après la durée ; tentative auditée | O23: Recette 10/2026 | P23: Production
A24: AUTH-022 | B24: P1 — Critique | C24: Politique mot de passe — expiration (30 j) | D24: passwordMaxAgeDays de la politique de sécurité plateforme. | E24: Compte de test dont le mot de passe a plus de 30 jours (ou durée abaissée à 1 j par le super_admin) | F24: 1. Se connecter avec le compte expiré 2. Suivre l'écran de changement obligatoire 3. Saisir un nouveau mot de passe | G24: Connexion bloquée tant que le mot de passe n'est pas changé ; après changement, accès normal ; 0 = jamais d'expiration | O24: Recette 10/2026 | P24: Production
A25: AUTH-023 | B25: P2 — Haute | C25: Politique mot de passe — anti-réutilisation (historique) | D25: Historique des N derniers mots de passe (défaut 5). | E25: Compte employe@sotra.ci | F25: 1. Mon profil → Changer le mot de passe 2. Saisir comme nouveau mot de passe l'un des 5 précédents | G25: Refus explicite « mot de passe déjà utilisé récemment » ; un mot de passe jamais utilisé est accepté | O25: Recette 10/2026 | P25: Production
A26: AUTH-024 | B26: P2 — Haute | C26: Politique mot de passe — mot de passe compromis (HaveIBeenPwned) | D26: Vérification k-anonymat, non bloquante si pas d'accès internet. | E26: Vérification de fuite activée (défaut) | F26: 1. Changer son mot de passe en « Password123! » 2. Changer ensuite pour un mot de passe robuste unique | G26: 1er refusé (mot de passe présent dans des fuites) ; 2e accepté ; le mot de passe en clair n'est jamais transmis (seul le préfixe SHA-1) | O26: Recette 10/2026 | P26: Production
A27: AUTH-025 | B27: P1 — Critique | C27: MFA obligatoire — enrôlement forcé au 1er login | D27: MFA rendu obligatoire par le super_admin (super_admin / employés tenant) → /mfa-setup. | E27: Politique « MFA obligatoire tenant » activée ; compte sans MFA | F27: 1. Se connecter avec rh@sotra.ci 2. Constater la redirection /mfa-setup 3. Scanner le QR code, saisir le code TOTP | G27: Accès à l'application impossible avant enrôlement ; après validation du code, accès normal ; login suivant demande le code | O27: Recette 10/2026 | P27: Production
A28: AUTH-026 | B28: P2 — Haute | C28: MFA — anti-rejeu du code TOTP | D28: Un code TOTP déjà utilisé ne peut pas être réutilisé. | E28: Compte avec MFA actif | F28: 1. Se connecter avec un code TOTP valide 2. Se déconnecter puis se reconnecter immédiatement avec le MÊME code | G28: 2e utilisation du même code refusée (401 « Code MFA invalide ») | O28: Recette 10/2026 | P28: Production
A29: AUTH-027 | B29: P2 — Haute | C29: Réinitialisation MFA d'un utilisateur par l'admin | D29: POST /settings/users/:id/reset-mfa. | E29: admin@sotra.ci ; utilisateur avec MFA actif ayant perdu son téléphone | F29: 1. Paramètres → Utilisateurs → utilisateur → Réinitialiser MFA 2. L'utilisateur se reconnecte | G29: MFA désactivé pour cet utilisateur, nouvel enrôlement demandé si MFA obligatoire ; action auditée | O29: Recette 10/2026 | P29: Production
A30: AUTH-028 | B30: P1 — Critique | C30: Déconnexion — révocation du jeton (jti) | D30: Le refresh/access token révoqué à la déconnexion ne doit plus fonctionner. | E30: Session rh@sotra.ci ouverte, jeton copié (outil dev) | F30: 1. Copier l'access token 2. Se déconnecter 3. Rejouer un appel API (GET /employees) avec l'ancien jeton et un refresh avec l'ancien refresh token | G30: 401 dans les deux cas : jeton révoqué côté serveur | O30: Recette 10/2026 | P30: Production
A31: AUTH-029 | B31: P2 — Haute | C31: Mise hors ligne tenant — message au login | D31: Tenant mis hors ligne par le super_admin avec message personnalisé. | E31: Tenant de test mis hors ligne (voir PLT) | F31: 1. Se connecter avec un compte du tenant hors ligne, mauvais mot de passe 2. Puis bon mot de passe | G31: Mauvais mdp → message d'échec générique (pas de fuite) ; bon mdp → message hors ligne personnalisé, aucun accès ; API renvoie 403 même avec un jeton existant | O31: Recette 10/2026 | P31: Production

Sheet PLT
A1: PORTAIL SUPER ADMIN · 39 scénarios
A2: ID Test | B2: Priorité | C2: Titre du scénario | D2: Description / Contexte | E2: Prérequis / Données | F2: Étapes détaillées | G2: Résultat attendu | H2: Résultat obtenu | I2: Statut | J2: Testeur | K2: Date test | L2: Durée (min) | M2: Ticket / Requalification | N2: Commentaire / Amélioration | O2: Sprint | P2: Env.
A3: PLT-001 | B3: P1 — Critique | C3: KPIs plateforme corrects | D3: Dashboard /platform/dashboard affiche tenants actifs, trials, MRR | E3: 2+ tenants seedés | F3: 1. Connecter superadmin 2. Observer KPI cards | G3: Valeurs cohérentes avec la base (ex: 3 tenants actifs = 3 affiché) | H3: KPIs dashboard plateforme {actifs, trial, suspendus, total} parfaitement coherents avec la liste reelle des tenants recomptee par statut. Issus d'une vraie requete count(*) FILTER (status=...) sur platform.tenants, aucune valeur en dur. | I3: ✅ Passé | J3: Agents IA + live (super_admin) | K3: 23/06/2026 | O3: Sprint 1 | P3: Production
A4: PLT-002 | B4: P1 — Critique | C4: Création tenant — wizard 3 étapes | D4: Créer un nouveau tenant via le formulaire | E4: Super admin connecté | F4: 1. /platform/tenants/new 2. Étape 1: nom, slug, plan, secteur, ville 3. Étape 2: admin email/prénom/nom 4. Étape 3: couleurs | G4: Tenant créé, schema PostgreSQL provisionné, email admin envoyé, tempPassword affiché | H4: POST /platform/tenants -> 201, data {id, slug, schemaName=tenant_<slug>, planType} + tempPassword (12c) + adminEmail ; schema PG provisionne (toutes les tables creees, GET /tenants/{id}=200) ; max_users/max_employees selon plan ; email admin non bloquant (.catch). | I4: ✅ Passé | J4: Agents IA + live (super_admin) | K4: 23/06/2026 | O4: Sprint 1 | P4: Production
A5: PLT-003 | B5: P2 — Haute | C5: Slug auto-généré depuis le nom | D5: Le slug se pré-remplit en minuscules-sans-espaces | F5: 1. Saisir nom entreprise 'Tech Corp' 2. Observer le champ slug | G5: Slug = 'tech-corp' (minuscules, tirets, sans caractères spéciaux) | H5: CORRIGE: le wizard n'auto-generait PAS le slug depuis le nom (2 champs independants, aucune slugification). Ajout slugify('Tech Corp')->'tech-corp' (minuscules/accents retires/espaces->tirets) sur saisie du nom, slug restant editable + nettoye a la frappe (PlatformTenantNew.tsx). | I5: ✅ Passé | J5: Agents IA + correctif | K5: 23/06/2026 | O5: Sprint 1 | P5: Production
A6: PLT-004 | B6: P2 — Haute | C6: Slug déjà existant → erreur | E6: Tenant 'sotra' existant | F6: 1. Créer un tenant avec slug 'sotra' | G6: Erreur explicite 'Slug déjà utilisé', formulaire non soumis | H6: POST /platform/tenants slug='sotra' (deja pris) -> HTTP 409 'Le slug "sotra" est deja utilise', aucun tenant cree/duplique. TenantSlugConflictError mappee en 409. | I6: ✅ Passé | J6: Agents IA + live (super_admin) | K6: 23/06/2026 | O6: Sprint 1 | P6: Production
A7: PLT-005 | B7: P2 — Haute | C7: Seed données démo (seedDemoData) | D7: Cocher l'option inject démo lors création | F7: 1. Wizard création 2. Cocher 'Injecter données de démonstration' 3. Créer | G7: 8 employés, 3 mois de bulletins créés dans le nouveau tenant, non bloquant | H7: CORRIGE: seedDemoData:true ne produisait AUCUNE donnee (0 employe). Cause: seed-demo.ts desync du schema (gross_salary->base_salary, pay_period_id->period_id, total_employee_contributions->total_cnps_sal, income_tax->its, pay_periods label/year->month). INSERT realignes sur le seed principal + VALIDES en direct (rollback). Provisioning lui-meme complet (toutes tables). Non bloquant OK. | I7: ✅ Passé | J7: Agents IA + correctif | K7: 23/06/2026 | O7: Sprint 1 | P7: Production
A8: PLT-006 | B8: P1 — Critique | C8: tempPassword retourné dans réponse | D8: En cas d'échec email, le mdp reste accessible | F8: 1. Créer un tenant 2. Observer la réponse écran de confirmation | G8: Mot de passe temporaire affiché dans l'encart de succès | H8: Apres creation tenant, l'encart de succes affiche adminEmail + tempPassword (bloc code copiable) ; l'API renvoie tempPassword dans le JSON 201. Confirme en live (PLT-002/005). | I8: ✅ Passé | J8: Agents IA + live (super_admin) | K8: 23/06/2026 | O8: Sprint 1 | P8: Production
A9: PLT-007 | B9: P1 — Critique | C9: Liste tenants paginée | D9: Tableau /platform/tenants | E9: 3+ tenants | F9: 1. Accéder /platform/tenants | G9: Tableau avec nom, plan, ville, statut, nb users, nb employés, actions | H9: CORRIGE: GET /platform/tenants enrichit chaque tenant avec user_count + employee_count REELS (comptes dans son schema) ; colonnes 'Utilisateurs' et 'Employes' (reel/quota) ajoutees a la liste. + pagination existante. | I9: ✅ Passé | J9: Agents IA + correctif | K9: 23/06/2026 | O9: Sprint 1 | P9: Production
A10: PLT-008 | B10: P2 — Haute | C10: Filtrage tenants par statut | D10: Filtre active/trial/suspended | F10: 1. Utiliser le filtre statut | G10: Tableau filtré correctement | H10: CORRIGE: ajout d'un selecteur de statut (Tous/Actifs/Trial/Suspendus) cote UI qui alimente la requete ?status= (le backend filtrait deja, parametre/anti-injection). Le tableau se filtre desormais. | I10: ✅ Passé | J10: Agents IA + correctif | K10: 23/06/2026 | O10: Sprint 1 | P10: Production
A11: PLT-009 | B11: P1 — Critique | C11: Détail tenant — 4 onglets | D11: Apparence, Plan, Modules, Données | F11: 1. Cliquer sur un tenant dans la liste | G11: 4 onglets affichés et fonctionnels | H11: CORRIGE: page detail refondue en 4 ONGLETS (Apparence, Plan, Modules, Donnees). Nouvel onglet Donnees = stats (users/employes/bulletins) + export RGPD (JSON) + suppression definitive (DELETE avec confirmation du slug + DROP schema). 3 endpoints backend ajoutes. | I11: ✅ Passé | J11: Agents IA + correctif | K11: 23/06/2026 | O11: Sprint 1 | P11: Production
A12: PLT-010 | B12: P2 — Haute | C12: Modification apparence — couleur primaire | D12: Changer couleur et observer preview live | F12: 1. Onglet Apparence 2. Changer couleur primaire 3. Observer prévisualisation 4. Sauvegarder | G12: Couleur mise à jour, preview reflète le changement immédiatement | H12: CORRIGE (2 volets): (1) FIX WAF CRITIQUE - CRS 911100 bloquait PATCH/PUT/DELETE -> debloque, PATCH /tenants/:id primary_color persiste (200). (2) onglet Apparence du detail rendu EDITABLE : color pickers primaire/secondaire + previsualisation live + sauvegarde (PATCH). Avant: lecture seule. | I12: ✅ Passé | J12: Agents IA + correctif | K12: 23/06/2026 | O12: Sprint 1 | P12: Production
A13: PLT-011 | B13: P2 — Haute | C13: Modification plan tenant | D13: Changer de trial → business | F13: 1. Onglet Plan 2. Sélectionner Business 3. Sauvegarder | G13: Plan mis à jour dans platform.tenants, maxUsers/maxEmployees ajustés selon PLAN_DEFAULTS | H13: CORRIGE: changer le plan n'ajustait pas les quotas + plan non editable. Le PATCH /tenants/:id reajuste max_users/max_employees selon PLAN_DEFAULTS quand plan_type change ; selecteur de plan ajoute a l'onglet Plan. (Live avant: business gardait 30/30 -> desormais 100/150.) | I13: ✅ Passé | J13: Agents IA + correctif | K13: 23/06/2026 | O13: Sprint 1 | P13: Production
A14: PLT-012 | B14: P2 — Haute | C14: Suspension tenant | D14: Tenant passé en statut suspended | F14: 1. Onglet Plan → Suspendre | G14: Status = suspended, login des users du tenant retourne erreur | H14: Suspension tenant OK (live): POST /suspend -> status=suspended ; login d'un user du tenant renvoie {error:message,offline:true} (bloque). Dialogue de message hors-ligne cote UI. | I14: ✅ Passé | J14: Agents IA + live (super_admin) | K14: 23/06/2026 | O14: Sprint 1 | P14: Production
A15: PLT-013 | B15: P2 — Haute | C15: Réactivation tenant | E15: Tenant suspendu | F15: 1. Onglet Plan → Réactiver | G15: Status = active, users peuvent se reconnecter | H15: Reactivation OK (live): POST /reactivate -> status=active, offline_message=NULL, cache invalide ; le login du user du tenant refonctionne (200). | I15: ✅ Passé | J15: Agents IA + live (super_admin) | K15: 23/06/2026 | O15: Sprint 1 | P15: Production
A16: PLT-014 | B16: P2 — Haute | C16: Consulter utilisateurs tenant | D16: Lecture seule des users d'un tenant | F16: 1. /platform/tenants/:id/users | G16: Liste avec email, rôle, statut, date création — pas de création depuis ici | H16: CORRIGE: aucune consultation des utilisateurs du tenant (endpoint + page absents). Ajout GET /platform/tenants/:id/users (email, role, statut, date - lecture seule) + liste dans l'onglet Donnees (sans creation depuis cette vue). | I16: ✅ Passé | J16: Agents IA + correctif | K16: 23/06/2026 | O16: Sprint 1 | P16: Production
A17: PLT-015 | B17: P2 — Haute | C17: Suspension utilisateur tenant | F17: 1. Trouver un utilisateur 2. Cliquer Suspendre | G17: is_active = false, cet user ne peut plus se connecter | H17: CORRIGE: impossible de suspendre un utilisateur individuel (seul le tenant entier). Ajout PATCH /platform/tenants/:id/users/:userId {isActive} (UPDATE users.is_active dans le schema tenant) + boutons Suspendre/Reactiver ; le blocage login is_active=false existait deja cote auth. | I17: ✅ Passé | J17: Agents IA + correctif | K17: 23/06/2026 | O17: Sprint 1 | P17: Production
A18: PLT-016 | B18: P2 — Haute | C18: Reset admin tenant | D18: Regénérer un mdp temporaire pour l'admin | F18: 1. POST /platform/tenants/:id/reset-admin | G18: Nouveau tempPassword retourné + email envoyé | H18: Live: POST /platform/tenants/:id/reset-admin -> adminEmail + tempPassword (12c) ; bcrypt 12, is_active=true, email non bloquant. Bouton dans l'onglet Plan + affichage tempPassword. | I18: ✅ Passé | J18: Agents IA + live (super_admin) | K18: 23/06/2026 | O18: Sprint 1 | P18: Production
A19: PLT-017 | B19: P3 — Moyenne | C19: Diagnostic admin-status | D19: GET /platform/tenants/:id/admin-status | F19: 1. Appeler l'endpoint via Swagger | G19: JSON avec schemaExists, adminUser.isActive, hasPasswordHash, issue | H19: Live: GET /platform/tenants/:id/admin-status -> {schemaExists:true, tenantName, adminUser:{is_active, has_hash, mfa_enabled}, issue:null}. Diagnostic complet conforme. | I19: ✅ Passé | J19: Agents IA + live (super_admin) | K19: 23/06/2026 | O19: Sprint 1 | P19: Production
A20: PLT-018 | B20: P1 — Critique | C20: Logs activité cross-tenant | D20: /platform/logs | F20: 1. Accéder /platform/logs | G20: Logs triés par date, avec tenant, user, action, IP | H20: CORRIGE: l'audit plateforme etait SILENCIEUSEMENT PERDU (auditLogPlatform ecrivait dans platform.audit_log, table jamais creee, .catch() avalait l'echec) + page /platform/logs inexistante. Ajout table platform.audit_log (migrations, OWASP A09) + GET /logs (jointure entity_id, pagination hasMore) + page PlatformLogs (date/tenant/action/entite/user/IP) + route + sidebar + i18n. | I20: ✅ Passé | J20: Agents IA + correctif | K20: 23/06/2026 | O20: Sprint 1 | P20: Production
A21: PLT-019 | B21: P3 — Moyenne | C21: Alerte trials expirant < 7 jours | D21: Dashboard plateforme signale les essais proches de l'expiration | E21: Tenant trial.endsAt dans < 7j | F21: 1. Observer le panneau alertes du dashboard | G21: Badge rouge avec le nom du tenant et date d'expiration | H21: CORRIGE: aucune alerte de trials expirant. GET /platform/dashboard renvoie desormais expiringTrials (status=trial, trial_ends_at < 7j) ; panneau d'alerte rouge (nom tenant + date expiration) ajoute au dashboard super_admin. | I21: ✅ Passé | J21: Agents IA + correctif | K21: 23/06/2026 | O21: Sprint 1 | P21: Production
A22: PLT-020 | B22: P2 — Haute | C22: Thématisation dynamique au login | D22: Au login, les couleurs tenant s'appliquent | F22: 1. Accéder page login SOTRA 2. Saisir admin@sotra.ci | G22: Bouton login orange (#E85D04), logo SOTRA visible avant même de se connecter | H22: CORRIGE (approche ?tenant=slug, choix recette): endpoint PUBLIC GET /public/brand/by-slug/:slug (couleur+logo+nom, tenant suspendu exclu) ; la page login lit le slug depuis ?tenant= (ou sous-domaine) et applique le theme AVANT login (applyTenantTheme exporte) + affiche le logo/nom du tenant. Bouton a la vraie couleur du tenant (plus par coincidence). | I22: ✅ Passé | J22: Agents IA + correctif | K22: 23/06/2026 | O22: Sprint 1 | P22: Production
A23: PLT-021 | B23: P3 — Moyenne | C23: Graphique croissance tenants 12 mois | D23: LineChart sur le dashboard plateforme | F23: 1. Observer le graphique dashboard plateforme | G23: Courbe affichée avec données des 12 derniers mois | H23: CORRIGE: aucun graphique de croissance (backend ni frontend). GET /platform/dashboard renvoie desormais growth (12 mois glissants, count par mois via generate_series + group by created_at) ; LineChart Recharts ajoute au dashboard plateforme. | I23: ✅ Passé | J23: Agents IA + correctif | K23: 23/06/2026 | O23: Sprint 1 | P23: Production
A24: PLT-022 | B24: P2 — Haute | C24: MRR estimé FCFA | D24: KPI card affiche le revenu mensuel récurrent estimé | F24: 1. Observer KPI dashboard plateforme | G24: Valeur en FCFA calculée selon plan × tarif indicatif | H24: CORRIGE: KPI MRR absent. GET /platform/dashboard calcule estimatedMrr (FCFA) selon tarifs indicatifs par plan (starter 65k, business 10k/employe) sur les tenants ACTIFS uniquement (trial/enterprise/public=0) ; KPI card 'MRR estime' formatee FCFA ajoutee. | I24: ✅ Passé | J24: Agents IA + correctif | K24: 23/06/2026 | O24: Sprint 1 | P24: Production
A25: PLT-023 | B25: P2 — Haute | C25: Feature flags par tenant | D25: Activer/désactiver modules individuellement | F25: 1. Onglet Modules d'un tenant 2. Désactiver 'IA Assistant' 3. Connecter admin du tenant | G25: Module IA n'apparaît pas dans la sidebar du tenant | H25: Backend CONFORME (live): PUT /modules persiste enabled_modules, login renvoie tenantConfig.enabledModules (ai true->false apres desactivation), enforcement API hook /ai -> 403 moduleDisabled. CORRIGE cote UI: le widget IA flottant (AiChat) etait rendu inconditionnellement -> desormais gate par isModuleEnabled(tenantConfig,'ai') dans MainLayout. Cle module = 'ai'. | I25: ✅ Passé | J25: Agents IA + correctif | K25: 23/06/2026 | O25: Sprint 1 | P25: Production
A26: PLT-024 | B26: P1 — Critique | C26: Modules activables par tenant — désactivation | D26: PUT /platform/tenants/:id/modules ; enforcement API (403 moduleDisabled) + sidebar masquée. | E26: superadmin connecté ; tenant SOTRA | F26: 1. Plateforme → Tenants → SOTRA → Modules → désactiver « Recrutement » 2. Se connecter admin@sotra.ci 3. Appeler GET /recruitment/jobs | G26: Entrée Recrutement absente de la sidebar ; API 403 { moduleDisabled: true } ; réactivation rétablit l'accès | O26: Recette 10/2026 | P26: Production
A27: PLT-025 | B27: P2 — Haute | C27: Modules opt-in — Vue DG 360°, Pointage, Simulations d'entretien | D27: dg_view, attendance, interview_sim désactivés par défaut. | E27: Nouveau tenant de test | F27: 1. Créer un tenant 2. Vérifier l'onglet Modules 3. Activer dg_view puis se connecter dg@ | G27: Les 3 modules sont OFF par défaut, tous les autres ON ; l'activation rend les pages accessibles | O27: Recette 10/2026 | P27: Production
A28: PLT-026 | B28: P2 — Haute | C28: Activation de modules en masse (bulk) | D28: POST /platform/tenants/modules-bulk. | E28: Plusieurs tenants | F28: 1. Sélectionner 2 tenants 2. Activer « Signature électronique » en masse | G28: Les 2 tenants reçoivent la surcharge ; clé de module inconnue refusée (400) | O28: Recette 10/2026 | P28: Production
A29: PLT-027 | B29: P1 — Critique | C29: Mise hors ligne d'un tenant avec message | D29: Suspension avec offline_message (variable système offline_message_default). | E29: Tenant de test | F29: 1. Tenant → Suspendre → saisir message « Maintenance contractuelle » 2. Vérifier login d'un utilisateur du tenant 3. Réactiver | G29: Message affiché aux utilisateurs bloqués ; filiales du tenant également bloquées ; si message obligatoire et vide → refus ; actions auditées | O29: Recette 10/2026 | P29: Production
A30: PLT-028 | B30: P2 — Haute | C30: Paramètres plateforme — politique de sécurité | D30: GET/PATCH /platform/settings (singleton). | E30: superadmin | F30: 1. Plateforme → Paramètres 2. Modifier MFA obligatoire, durée de vie mdp, historique, verrouillage, message hors ligne par défaut 3. Enregistrer puis recharger | G30: Valeurs persistées sur une seule ligne (pas de doublon) ; appliquées aux logins suivants | O30: Recette 10/2026 | P30: Production
A31: PLT-029 | B31: P2 — Haute | C31: Packs législatifs — consultation et modification | D31: GET/PATCH /platform/legislation-packs/:country. | E31: superadmin | F31: 1. Plateforme → Législation → pack CI 2. Consulter SMIG, préavis, barème ITS, taux CNPS 3. Modifier une valeur de test puis annuler | G31: Pack affiché complet ; modification validée et versionnée ; tenants CI recalculés avec la nouvelle valeur | O31: Recette 10/2026 | P31: Production
A32: PLT-030 | B32: P2 — Haute | C32: Propositions législatives — approbation / rejet | D32: legislation-proposals : approve/reject. | E32: Une proposition en attente | F32: 1. Plateforme → Législation → Propositions 2. Approuver une proposition, en rejeter une autre avec motif | G32: Statuts mis à jour, pack modifié uniquement après approbation, audit présent | O32: Recette 10/2026 | P32: Production
A33: PLT-031 | B33: P2 — Haute | C33: Veille légale IA — analyse de texte | D33: POST /platform/legal-watch/analyze (diff IA, confiance 0-100). | E33: superadmin ; IA disponible | F33: 1. Plateforme → Veille légale → coller un nouveau texte d'article 2. Lancer l'analyse 3. Coller un texte > 30 000 caractères | G33: Résumé des changements, confiance, raisonnement ; proposition créée ; texte trop long refusé (400) | O33: Recette 10/2026 | P33: Production
A34: PLT-032 | B34: P3 — Moyenne | C34: Constantes légales par pays et version | D34: GET/PATCH /platform/legal-constants/:country/:version. | E34: superadmin | F34: 1. Plateforme → Législation → Constantes 2. Modifier une constante d'une version future | G34: Constante enregistrée pour la version ciblée, version courante inchangée | O34: Recette 10/2026 | P34: Production
A35: PLT-033 | B35: P2 — Haute | C35: Configuration du sourcing IA (modèles, plateformes, réglages) | D35: Tables platform.sourcing_* — 100 % paramétrable. | E35: superadmin | F35: 1. Plateforme → Paramètres → Sourcing 2. Ajouter un modèle, désactiver une plateforme, modifier les réglages 3. Lancer un sourcing côté tenant | G35: Le sourcing utilise exactement la configuration (aucune valeur en dur) ; plateforme désactivée absente | O35: Recette 10/2026 | P35: Production
A36: PLT-034 | B36: P2 — Haute | C36: Export des données d'un tenant | D36: GET /platform/tenants/:id/export. | E36: superadmin | F36: 1. Tenant → Exporter les données | G36: Archive/JSON téléchargé contenant uniquement les données du tenant ciblé ; action auditée | O36: Recette 10/2026 | P36: Production
A37: PLT-035 | B37: P2 — Haute | C37: Suppression d'un tenant | D37: DELETE /platform/tenants/:id. | E37: Tenant de test créé pour l'occasion | F37: 1. Tenant de test → Supprimer → confirmer en saisissant le slug | G37: Tenant supprimé, schéma retiré, plus aucun login possible ; SOTRA intact | O37: Recette 10/2026 | P37: Production
... A41: PLT-039 | B41: P2 — Haute | C41: Consommation IA par tenant | D41: GET /platform/ai-usage (complément AI-104). | E41: superadmin ; tenants avec usage IA | F41: 1. Plateforme → Consommation IA 2. Filtrer par tenant et par mois | G41: Tokens et coût estimé par tenant/mois, aucune donnée de contenu des conversations exposée | O41: Recette 10/2026 | P41: Production

Sheet EMP
A1: GESTION DES EMPLOYÉS · 32 scénarios
A2: ID Test | B2: Priorité | C2: Titre du scénario | D2: Description / Contexte | E2: Prérequis / Données | F2: Étapes détaillées | G2: Résultat attendu | H2: Résultat obtenu | I2: Statut | J2: Testeur | K2: Date test | L2: Durée (min) | M2: Ticket / Requalification | N2: Commentaire / Amélioration | O2: Sprint | P2: Env.
A3: EMP-001 | B3: P1 — Critique | C3: Création employé — champs obligatoires | D3: Prénom, nom, email, département, poste, salaire brut FCFA | E3: Admin connecté, département créé | F3: 1. /employees/new 2. Remplir tous les champs requis 3. Sauvegarder | G3: Employé créé, visible dans la liste, aucune décimale dans le salaire | H3: Live: POST /employees valide -> 201 {data:{id, first_name, base_salary...}} ; employe visible en liste ; base_salary stocke en numeric(12,0) = entier (zero decimale). Champs requis: firstName, lastName, baseSalary (>=75000 SMIG CI). | I3: ✅ Passé | J3: Agents IA + live | K3: 23/06/2026 | O3: Sprint 1 | P3: Production
A4: EMP-002 | B4: P1 — Critique | C4: Email employé unique dans le tenant | F4: 1. Créer 2 employés avec le même email | G4: Erreur 409, message 'Email déjà utilisé dans ce tenant' | H4: Doublon email -> 409 (contrainte UNIQUE(email) intra-schema, catch 23505). Message: 'Un employe avec cet email existe deja.' (libelle canonique, coherent avec EMP-102 non-regression). | I4: ✅ Passé | J4: Agents IA + live | K4: 23/06/2026 | O4: Sprint 1 | P4: Production
A5: EMP-003 | B5: P2 — Haute | C5: Validation NNI — format ivoirien | D5: Format CI + 9 chiffres | F5: 1. Saisir NNI 'CI123456789' 2. Saisir NNI invalide 'AB12' | G5: NNI valide accepté, NNI invalide rejeté avec message d'erreur | H5: CORRIGE: le NNI n'avait aucune validation de format (seulement max(50)). Ajout regex /^CId{9,13}$/ : 'CI123456789' accepte, 'AB12' rejete avec message clair. NNI chiffre AES (RGPD). (Avant: 'AB12' echouait par accident en 22001 longueur ciphertext, message trompeur.) | I5: ✅ Passé | J5: Agents IA + correctif | K5: 23/06/2026 | O5: Sprint 1 | P5: Production
A6: EMP-004 | B6: P2 — Haute | C6: Validation CNPS — format CI | D6: Format CI + 8 chiffres + lettre | F6: 1. Saisir CI12345678A (valide) 2. Saisir 12345 (invalide) | G6: Valide accepté, invalide rejeté | H6: CORRIGE: le numero CNPS n'avait aucune validation. Ajout regex /^CId{8}[A-Z]$/ : 'CI12345678A' accepte, '12345' rejete avec message. | I6: ✅ Passé | J6: Agents IA + correctif | K6: 23/06/2026 | O6: Sprint 1 | P6: Production
A7: EMP-005 | B7: P2 — Haute | C7: Validation téléphone Mobile Money CI | D7: +225 07/05 + 8 chiffres | F7: 1. Saisir +225 07 12 34 56 78 (valide) 2. Saisir +33 6 12 (invalide) | G7: Format CI accepté, autre rejeté | H7: CORRIGE: le telephone Mobile Money n'etait pas valide a la saisie. Ajout validation indicatif AFRICAIN (CEDEAO+CEMAC+RDC : CI/BF/ML/NE/SN/TD/CG/RDC/CM...) car les employes peuvent venir de toute la zone ; +225/+226/+223/+235/+242 acceptes, +33/+1 rejetes ; espaces tolerees. | I7: ✅ Passé | J7: Agents IA + correctif | K7: 23/06/2026 | O7: Sprint 1 | P7: Production
A8: EMP-006 | B8: P1 — Critique | C8: Liste employés — pagination | D8: Affichage par page avec navigation | E8: 80+ employés SOTRA | F8: 1. Accéder /employees | G8: Pagination fonctionnelle, 20-50 par page, nombre total affiché | H8: CORRIGE: la liste renvoyait TOUS les employes (total=taille page). GET /employees pagine desormais (page/limit + COUNT reel) ; barre de pagination UI (prec/suiv + plage X-Y / total). Le total affiche est le vrai nombre du tenant (80+). | I8: ✅ Passé | J8: Agents IA + correctif | K8: 23/06/2026 | O8: Sprint 1 | P8: Production
A9: EMP-007 | B9: P1 — Critique | C9: Recherche employé par nom | D9: Champ de recherche filtrant en temps réel | F9: 1. Taper 'Kouassi' dans la recherche | G9: Liste filtrée aux employés correspondants | H9: Recherche par nom OK (live: 'Camara' -> 1 resultat). Backend ILIKE parametre (anti-injection) sur prenom/nom/cnps. Reserve mineure: pas de debounce (1 requete par frappe), non bloquant. | I9: ✅ Passé | J9: Agents IA + live | K9: 23/06/2026 | O9: Sprint 1 | P9: Production
A10: EMP-008 | B10: P2 — Haute | C10: Filtrage par département | D10: Sélecteur département | F10: 1. Sélectionner département 'Exploitation' 2. Observer la liste | G10: Seuls les employés du département Exploitation affichés | H10: CORRIGE: le filtre departement existait cote API (live OK: meme dept) mais aucun selecteur UI. Ajout d'un <select> departement (alimente par /employees/departments) cable a la requete, reset page au changement. | I10: ✅ Passé | J10: Agents IA + correctif | K10: 23/06/2026 | O10: Sprint 1 | P10: Production
A11: EMP-009 | B11: P1 — Critique | C11: Fiche employé — consultation | D11: Tous les champs visibles | F11: 1. Cliquer sur un employé dans la liste | G11: Fiche complète: identité, poste, salaire FCFA, NNI, CNPS, Mobile Money, ancienneté calculée | H11: CORRIGE: fiche complete (identite, poste, salaire FCFA, NNI dechiffre par role RH, CNPS, Mobile Money) mais ANCIENNETE non calculee. GET /employees/:id renvoie seniority_months + seniority_label (calcul depuis hire_date), affichee dans la fiche. (NB: nni null sur donnees seedees = seed-demo n'encrypte pas le nni - mineur.) | I11: ✅ Passé | J11: Agents IA + correctif | K11: 23/06/2026 | O11: Sprint 1 | P11: Production
A12: EMP-010 | B12: P1 — Critique | C12: Modification employé | D12: Mise à jour des données | F12: 1. Ouvrir fiche 2. Modifier salaire 3. Sauvegarder | G12: Données mises à jour, historique hr_events enregistré | H12: CORRIGE: modifier le salaire (live: PATCH 200, salaire mis a jour) ne creait AUCUN hr_events. PATCH /employees/:id capture l'ancien salaire et insere un hr_events (augmentation/salary_change avec ancien/nouveau montant, non bloquant). Historique RH desormais alimente. | I12: ✅ Passé | J12: Agents IA + correctif | K12: 23/06/2026 | O12: Sprint 1 | P12: Production
A13: EMP-011 | B13: P2 — Haute | C13: Désactivation employé | D13: is_active = false, employé absent des listings actifs | F13: 1. Fiche employé → Désactiver | G13: Employé marqué inactif, n'apparaît plus dans liste active | H13: Live: PATCH /employees/:id isActive=false -> l'employe disparait de la liste active (GET ?isActive=true ne le contient plus). Le compte user lie est aussi desactive (cf. DELETE/archive employe). | I13: ✅ Passé | J13: Agents IA + live | K13: 23/06/2026 | O13: Sprint 1 | P13: Production
A14: EMP-012 | B14: P2 — Haute | C14: Calcul ancienneté affiché | D14: Années et mois depuis hire_date | F14: 1. Ouvrir fiche employé embauché il y a 3 ans 2 mois | G14: Affiche '3 ans 2 mois' correctement | H14: Live: employe embauche le 2023-04-23 (il y a 3 ans 2 mois) -> GET /employees/:id renvoie seniority_months=38, seniority_label='3 an(s) 2 mois' ; affiche correctement dans la fiche. (Corrige via EMP-009.) | I14: ✅ Passé | J14: Agents IA + live | K14: 23/06/2026 | O14: Sprint 1 | P14: Production
A15: EMP-013 | B15: P3 — Moyenne | C15: Import CSV employés | D15: Upload d'un fichier CSV pour création en masse | E15: Fichier CSV valide préparé | F15: 1. /employees/import 2. Uploader CSV 3. Valider | G15: Employés créés en masse, rapport d'import (succès/erreurs) | H15: CORRIGE (decouvrabilite): l'import CSV de masse EXISTE et fonctionne (Parametres > Reprise de donnees, POST /settings/import/employees : creation en masse + rapport succes/erreurs par ligne, chiffrement IBAN, RBAC). Ajout d'un bouton 'Importer' sur la page Employes qui ouvre l'onglet d'import (/settings?tab=data-import). | I15: ✅ Passé | J15: Agents IA + correctif | K15: 23/06/2026 | O15: Sprint 1 | P15: Production
A16: EMP-014 | B16: P3 — Moyenne | C16: Export liste employés | D16: Téléchargement CSV/Excel | F16: 1. Bouton Export dans la liste 2. Choisir format | G16: Fichier téléchargé avec tous les champs, encodage UTF-8, FCFA entiers | H16: CORRIGE: aucun export de la liste. Ajout GET /employees/export.csv (BOM UTF-8 pour Excel FR, anti-injection CSV via encodeField, salaires FCFA ENTIERS via Math.round, NNI/IBAN EXCLUS pour RGPD) + bouton 'Exporter' (telechargement blob). RBAC admin/hr_manager/hr_officer. | I16: ✅ Passé | J16: Agents IA + correctif | K16: 23/06/2026 | O16: Sprint 1 | P16: Production
A17: EMP-015 | B17: P3 — Moyenne | C17: Upload photo profil | D17: Image recadrée et sauvegardée | F17: 1. Fiche employé → Photo 2. Uploader une image 3. Recadrer 4. Sauvegarder | G17: Photo visible dans la fiche et dans le header | H17: CORRIGE: aucune photo de profil (champ existait mais ni endpoint, ni UI, ni affichage). Ajout POST /employees/:id/photo (multipart, allowlist PNG/JPEG/WEBP/GIF, max 2Mo, RBAC RH+self, SVG exclu anti-XSS) + l'avatar de la fiche affiche la VRAIE photo (fallback initiales) avec bouton d'upload (icone appareil photo). Recadrage avance non inclus (P3). | I17: ✅ Passé | J17: Agents IA + correctif | K17: 23/06/2026 | O17: Sprint 1 | P17: Production
A18: EMP-016 | B18: P1 — Critique | C18: Manager ne voit que son équipe | D18: Filtrage automatique par department_id du manager | E18: manager@sotra.ci lié à département Exploitation | F18: 1. Connecter manager@sotra.ci 2. Accéder /employees | G18: Seuls les employés de son département listés | H18: Manager filtre fail-closed: ne voit que son EQUIPE DIRECTE (e.manager_id = id de l'employe lie au manager via email du JWT). Si pas de dossier lie -> liste vide/403 (pas tout le tenant). COUNT partage le meme WHERE. Fiche /:id refuse aussi hors-equipe (403). NNI/IBAN masques au manager. | I18: ✅ Passé | J18: Agents IA (code) | K18: 23/06/2026 | O18: Sprint 1 | P18: Production
A19: EMP-017 | B19: P1 — Critique | C19: Employee ne peut pas accéder /employees | D19: Redirection /mon-espace | F19: 1. Connecter employe@sotra.ci 2. Tenter /employees | G19: Redirection automatique vers /mon-espace | H19: Employee bloque de /employees: RoleGuard (allowedRoles sans 'employee') -> /dashboard -> RhDashboardGuard -> /mon-espace (chaine deterministe, sans boucle). Backend defense-in-depth: GET /employees authorize sans 'employee' -> 403. | I19: ✅ Passé | J19: Agents IA (code) | K19: 23/06/2026 | O19: Sprint 1 | P19: Production
A20: EMP-018 | B20: P2 — Haute | C20: Mobile Money affiché sur fiche | D20: Provider + numéro formaté | F20: 1. Ouvrir fiche d'un employé avec Wave enregistré | G20: Affiche 'Wave — +225 07 XX XX XX XX' | H20: Mobile Money affiche sur la fiche: PROVIDER_LABEL (wave->Wave, mtn_momo->MTN MoMo, orange_money->Orange Money) + numero mobile_money_phone. Backend GET /:id renvoie les 2 champs (SELECT e.*). | I20: ✅ Passé | J20: Agents IA (code) | K20: 23/06/2026 | O20: Sprint 1 | P20: Production
A21: EMP-101 | B21: P1 — Critique | C21: Création employé avec NNI et IBAN | D21: Plus de 500 à l'enregistrement (chiffrement configuré) | E21: ENCRYPTION_KEY présente, admin/RH connecté | F21: 1. /employees/new 2. Renseigner NNI et IBAN 3. Enregistrer | G21: Employé créé, NNI/IBAN chiffrés, aucune « Erreur interne » | H21: CORRIGE: creer un employe avec NNI -> 400 (PG 22001 valeur trop longue) car la colonne nni varchar(50) ne pouvait pas contenir le NNI CHIFFRE AES (~100+ chars), alors qu'iban varchar(255) passait. Elargi nni a varchar(255) (provisioning + schema + migration lazy ALTER COLUMN TYPE, sans reecriture). NNI/IBAN chiffres, aucune 500. | I21: ✅ Passé | J21: Agents IA + correctif | K21: 23/06/2026 | O21: Corrections 23/06 | P21: Production
A22: EMP-102 | B22: P1 — Critique | C22: Email employé dupliqué → message personnalisé | D22: Erreur métier claire, pas de 500 brute | E22: Un employé avec cet email existe déjà | F22: 1. Créer un employé avec un email déjà utilisé | G22: 409 « Un employé avec cet email existe déjà. » | H22: Doublon email -> 409 'Un employe avec cet email existe deja.' Message ramene au libelle canonique attendu par ce scenario de non-regression (revert de l'alignement EMP-002, les 2 sont desormais coherents). | I22: ✅ Passé | J22: Agents IA + correctif | K22: 23/06/2026 | O22: Corrections 23/06 | P22: Production
A23: EMP-103 | B23: P1 — Critique | C23: Rupture de contrat | D23: Le bouton « Rompre le contrat » fonctionne | E23: Contrat actif sur un employé | F23: 1. Fiche contrat → Rompre 2. Date + motif 3. Confirmer | G23: Contrat terminé, employé désactivé, événement RH créé, aucune 500 | H23: Rupture contrat OK (code): POST /contracts/:id/terminate -> contrat status=terminated + end_date, employe is_active=false, hr_events cree (colonne 'date', PAS event_date - non-regression du bug historique), gestion d'erreur personnalisee (pas de 500 brute). Reserve mineure: les 3 ecritures non transactionnelles. | I23: ✅ Passé | J23: Agents IA (code) | K23: 23/06/2026 | O23: Corrections 23/06 | P23: Production
A24: EMP-104 | B24: P1 — Critique | C24: Contrats OHADA — création CDD / CDI | D24: Page Contrats OHADA (POST /contracts). | E24: rh@sotra.ci (hr_manager, « Responsable Paie ») | F24: 1. Contrats OHADA → Nouveau contrat 2. Employé, type CDD, dates, salaire 3. Enregistrer | G24: Contrat créé, visible dans la fiche employé et la liste ; CDD sans date de fin refusé | O24: Recette 10/2026 | P24: Production
A25: EMP-105 | B25: P2 — Haute | C25: Contrats — renouvellement d'un CDD | D25: POST /contracts/:id/renew. | E25: CDD actif | F25: 1. Contrat → Renouveler → nouvelle date de fin | G25: Nouveau contrat lié, ancien clôturé ; règle de renouvellement CDD CI respectée (message si dépassement) | O25: Recette 10/2026 | P25: Production
A26: EMP-106 | B26: P2 — Haute | C26: Contrats — consultation « Mon contrat » par l'employé | D26: GET /contracts/my-contract. | E26: employe@sotra.ci (Kouassi Coulibaly) | F26: 1. Mon espace → Profil → Mon contrat | G26: Seul son contrat est visible ; GET /contracts → 403 | O26: Recette 10/2026 | P26: Production
A27: EMP-107 | B27: P2 — Haute | C27: Contrats — suppression d'un brouillon | D27: DELETE /contracts/:id (réservé RH). | E27: Contrat brouillon | F27: 1. Supprimer le contrat 2. Tenter avec manager@ | G27: Supprimé par la RH ; manager → 403 | O27: Recette 10/2026 | P27: Production
A28: EMP-108 | B28: P1 — Critique | C28: Champs personnalisés sur la fiche employé | D28: Valeurs custom_fields validées contre la définition du tenant. | E28: Champs « Groupe sanguin » (liste) et « N° badge » (texte, sensible) définis dans Paramètres | F28: 1. Fiche employé → Modifier → renseigner les champs 2. Saisir une valeur hors liste via l'API 3. Ouvrir la fiche avec manager@ | G28: Valeurs enregistrées et affichées ; valeur invalide → 400 ; champ sensible masqué au manager, visible RH et salarié | O28: Recette 10/2026 | P28: Production
A29: EMP-109 | B29: P1 — Critique | C29: Archivage employé — cascade sans processus orphelin | D29: employee-archive : compte désactivé, contrats terminés, sanctions annulées, signatures annulées. | E29: Employé de test avec contrat actif, sanction en cours, demande de signature en attente | F29: 1. Fiche → Supprimer / Archiver → vérification préalable (check-delete) 2. Confirmer 3. Contrôler contrats, discipline, signature, login | G29: Pré-contrôle liste les impacts ; après archivage : login impossible, contrat 'terminated', sanction 'cancelled', signature 'cancelled' ; ré-archivage sans effet | O29: Recette 10/2026 | P29: Production
A30: EMP-110 | B30: P2 — Haute | C30: Hiérarchie — choix du manager sans cycle | D30: GET /employees/manager-options ; refus d'un cycle hiérarchique. | E30: A manager de B | F30: 1. Fiche de A → Manager = B 2. Enregistrer | G30: Refus explicite « cycle hiérarchique » ; la liste ne propose pas le salarié lui-même | O30: Recette 10/2026 | P30: Production
A31: EMP-111 | B31: P2 — Haute | C31: Mode de paiement — virement bancaire (RIB) | D31: paymentMethod mobile_money / bank_transfer sur la fiche. | E31: Employé de test | F31: 1. Modifier → Mode de paiement = Virement → saisir banque, IBAN/RIB 2. Enregistrer 3. RIB invalide | G31: RIB enregistré (chiffré, masqué hors RH) ; RIB invalide refusé avec message clair | O31: Recette 10/2026 | P31: Production
A32: EMP-112 | B32: P2 — Haute | C32: Photo de profil — isolation | D32: GET /employees/:id/photo protégé. | E32: Photo chargée sur un employé SOTRA | F32: 1. Copier l'URL photo 2. L'ouvrir avec un compte d'un autre tenant | G32: 403/404 cross-tenant ; un employé ne voit pas la photo d'un autre salarié hors annuaire autorisé | O32: Recette 10/2026 | P32: Production
A33: EMP-113 | B33: P2 — Haute | C33: Profil d'entretien (interview-focus) d'un employé | D33: PUT /employees/:id/interview-focus — calibre les simulations internes. | E33: rh@sotra.ci (hr_manager, « Responsable Paie ») | F33: 1. Fiche employé → Profil technique → compétences clés, niveau 2. Enregistrer | G33: Profil enregistré et normalisé ; valeurs invalides refusées | O33: Recette 10/2026 | P33: Production
A34: EMP-114 | B34: P2 — Haute | C34: Rattachement manager et périmètre (job_level) | D34: job_level pilote les offres internes visibles. | E34: Employé avec job_level NULL | F34: 1. Renseigner job_level sur la fiche 2. Connecter l'employé → Mes offres internes | G34: Sans job_level aucune offre ciblée ; après saisie, les offres ciblant ce niveau apparaissent | O34: Recette 10/2026 | P34: Production

Sheet PAY
A1: MOTEUR DE PAIE CI (CNPS + ITS) · 62 scénarios
A2: ID Test | B2: Priorité | C2: Titre du scénario | D2: Description / Contexte | E2: Prérequis / Données | F2: Étapes détaillées | G2: Résultat attendu | H2: Résultat obtenu | I2: Statut | J2: Testeur | K2: Date test | L2: Durée (min) | M2: Ticket / Requalification | N2: Commentaire / Amélioration | O2: Sprint | P2: Env.
A3: PAY-001 | B3: P1 — Critique | C3: CNPS Retraite salarié 6.3% — plafond 1 647 315 FCFA | D3: Vérifier le calcul exact pour un salaire de 200 000 FCFA | E3: Moteur CI déployé | F3: 1. Créer bulletin pour salaire 200 000 FCFA 2. Vérifier rubrique CNPS retraite sal | G3: 200 000 × 6.3% = 12 600 FCFA (< plafond → pas d'écrêtement) | H3: Live (POST /payroll/simulate, salaire 200000): retraite sal (rubrique 2000) = 200000 x 6.3% = 12600 FCFA (< plafond 1647315, pas d'ecretement). Taux 0.063 + plafond depuis le pack legislatif CIV-2024. Couvert par test unitaire + golden. | I3: ✅ Passé | J3: Agents IA + live (simulate) | K3: 23/06/2026 | O3: Sprint 1 | P3: Production
A4: PAY-002 | B4: P1 — Critique | C4: CNPS Retraite salarié — plafond appliqué | D4: Salaire > 1 647 315 FCFA | F4: 1. Créer bulletin pour salaire 2 000 000 FCFA | G4: CNPS retraite sal = 1 647 315 × 6.3% = 103 781 FCFA (pas 2 000 000 × 6.3%) | H4: Live (salaire 2000000): retraite sal = base ECRETEE a 1647315 x 6.3% = 103780 FCFA (PAS 2000000 x 6.3%). Le PLAFOND est correctement applique (min avant taux). Ecart de 1 FCFA vs cahier (103781): le moteur fait Math.floor (troncature) - DECISION RECETTE: garder Math.floor (convention documentee, plafond conforme). | I4: ✅ Passé | J4: Agents IA + live (simulate) | K4: 23/06/2026 | O4: Sprint 1 | P4: Production
A5: PAY-003 | B5: P1 — Critique | C5: CNPS AT commerce 2% — plafond 70 000 FCFA | D5: Tenant secteur Commerce | E5: Tenant services (atRate=2%) | F5: 1. Générer bulletin pour salaire 200 000 FCFA 2. Vérifier rubrique AT | G5: AT = min(200 000, 70 000) × 2% = 1 400 FCFA | H5: Live (services atRate=2%, salaire 200000): AT (rubrique 3300, part patronale) = min(200000,70000) x 2% = 1400 FCFA. Plafond AT/PF=70000 distinct du plafond retraite (double plafond respecte). Golden fixture 01 verrouille 200000@2%->1400. | I5: ✅ Passé | J5: Agents IA + live (simulate) | K5: 23/06/2026 | O5: Sprint 1 | P5: Production
A6: PAY-004 | B6: P1 — Critique | C6: CNPS AT BTP 3% — plafond 70 000 FCFA | D6: Tenant secteur Transport (SOTRA atRate=3%) | E6: Tenant SOTRA connecté | F6: 1. Générer bulletin SOTRA, salaire 180 000 FCFA | G6: AT = min(180 000, 70 000) × 3% = 2 100 FCFA | H6: Live (atRate=3% BTP/transport=SOTRA, salaire 180000): AT = min(180000,70000) x 3% = 2100 FCFA. Le taux AT vient du tenant (at_rate parametrable 2-5% par secteur/filiale), PAS en dur. Conforme. | I6: ✅ Passé | J6: Agents IA + live (simulate) | K6: 23/06/2026 | O6: Sprint 1 | P6: Production
A7: PAY-005 | B7: P1 — Critique | C7: CNPS Prestations Familiales 5% | D7: Part patronale seulement, plafond 70 000 | F7: 1. Vérifier rubrique PF sur bulletin | G7: PF = min(BRUT, 70 000) × 5%, salarié ne paie rien sur cette branche | H7: Live (salaire 200000): PF (rubrique 3100) = min(200000,70000) x 5% = 3500 FCFA, base=70000, type=employer_contribution (100% patronale). Part salariee PF = 0 (totalCnpsSal = retraite seule). Conforme. | I7: ✅ Passé | J7: Agents IA + live (simulate) | K7: 23/06/2026 | O7: Sprint 1 | P7: Production
A8: PAY-006 | B8: P1 — Critique | C8: CNPS Maternité 0.75% — patronal | F8: 1. Vérifier rubrique maternité | G8: Maternité = min(BRUT, 70 000) × 0.75% | H8: Live (@200000): maternite (rubrique 3200, patronale) = min(200000,70000) x 0.75% = 525 FCFA, base=70000. Conforme. | I8: ✅ Passé | J8: Agents IA + live (simulate) | K8: 23/06/2026 | O8: Sprint 1 | P8: Production
A9: PAY-007 | B9: P1 — Critique | C9: ITS barème 0% — salaire net imposable ≤ 75 000 FCFA | D9: Salaire SMIG = 60 000 FCFA | F9: 1. Créer bulletin SMIG = 60 000 FCFA 2. Calculer net imposable = 60 000 × 0.85 - CNPS | G9: ITS = 0 FCFA | H9: Live (SMIG 60000): net imposable = floor(60000x0.85)-CNPS = 47220 (<= 75000) -> ITS = 0 FCFA. Conforme. | I9: ✅ Passé | J9: Agents IA + live (simulate) | K9: 23/06/2026 | O9: Sprint 1 | P9: Production
A10: PAY-008 | B10: P1 — Critique | C10: ITS barème 1.5% — tranche 75 001 à 240 000 FCFA | D10: Salaire net imposable dans cette tranche | F10: 1. Salaire brut 120 000 FCFA 2. Net imposable = 120 000×0.85 - CNPS ≈ 94 440 | G10: ITS = (94 440 - 75 000) × 1.5% ≈ 292 FCFA | H10: Live (brut 120000): imposable = floor(120000x0.85) - CNPS 7560 = 94440 -> ITS = (94440-75000) x 1.5% = 291 FCFA (floor). Conforme au barème tranche 1,5%. | I10: ✅ Passé | J10: Agents IA + live (simulate) | K10: 23/06/2026 | O10: Sprint 1 | P10: Production
A11: PAY-009 | B11: P1 — Critique | C11: ITS barème 5% — tranche 240 001 à 800 000 FCFA | F11: 1. Salaire brut 400 000 FCFA | G11: ITS calculé selon barème progressif, taux 5% sur la tranche | H11: Live (brut 400000): imposable = 314800 -> ITS progressif = 6214 FCFA (tranche 1,5% sur 75001-240000 + tranche 5% sur 240001-314800). Bareme progressif applique (pas un taux unique). 1 FCFA d'ecart vs calcul single-floor = floor par tranche (convention conservee). | I11: ✅ Passé | J11: Agents IA + live (simulate) | K11: 23/06/2026 | O11: Sprint 1 | P11: Production
A12: PAY-010 | B12: P1 — Critique | C12: ITS barème 10% — tranche 800 001 à 2 000 000 FCFA | F12: 1. Salaire brut 1 200 000 FCFA | G12: ITS avec taux 10% sur la tranche concernée | H12: Live (brut 1200000): imposable = 944400 -> ITS progressif = 44914 FCFA (tranches 1,5% + 5% + 10% sur 800001-944400). Tranche 10% atteinte, bareme progressif correct. | I12: ✅ Passé | J12: Agents IA + live (simulate) | K12: 23/06/2026 | O12: Sprint 1 | P12: Production
A13: PAY-011 | B13: P1 — Critique | C13: ITS barème 15% — tranche > 2 000 000 FCFA | F13: 1. Salaire brut 3 000 000 FCFA | G13: ITS avec taux 15% sur la tranche > 2M | H13: Live (brut 3000000 single): imposable~2446220 -> ITS=217407 FCFA, tranche 15% atteinte (>2M). Bareme progressif complet (1,5+5+10+15%). Conforme. | I13: ✅ Passé | J13: Agents IA + live (simulate) | K13: 23/06/2026 | O13: Sprint 1 | P13: Production
A14: PAY-012 | B14: P1 — Critique | C14: Abattement ITS 15% appliqué avant barème | D14: Net imposable = BRUT × 0.85 | F14: 1. Salaire 200 000 FCFA 2. Vérifier base de calcul ITS | G14: Base ITS = 200 000 × 0.85 - CNPS sal, PAS directement 200 000 | H14: Live (brut 200000): la rubrique ITS a base=157400 = floor(200000x0.85) - CNPS 12600. L'abattement 15% est applique sur le BRUT AVANT le bareme (pas sur 200000 direct), puis CNPS deduite. Confirme code (payroll-engine-ci abattementImpotSalaire=0.15). Conforme. | I14: ✅ Passé | J14: Agents IA + live (simulate) | K14: 23/06/2026 | O14: Sprint 1 | P14: Production
A15: PAY-013 | B15: P2 — Haute | C15: Crédit d'impôt marié sans enfant — 5 500 FCFA/mois | F15: 1. Employé marié, 0 enfant 2. Vérifier crédit ITS | G15: ITS final = max(0, ITS brut - 5 500) | H15: Live (brut 1200000, marie 0 enfant): ITS brut 44914 - credit 5500 = 39414 FCFA. max(0, its-credit) applique. Conforme. | I15: ✅ Passé | J15: Agents IA + live (simulate) | K15: 23/06/2026 | O15: Sprint 1 | P15: Production
A16: PAY-014 | B16: P2 — Haute | C16: Crédit d'impôt 1 enfant — 3 000 FCFA supplémentaires | F16: 1. Employé marié, 1 enfant 2. Crédit = 5 500 + 3 000 = 8 500 FCFA | G16: ITS final déduit du crédit cumulé | H16: Live (brut 1200000, marie 1 enfant): credit = 5500 + 3000 = 8500 -> ITS = 44914 - 8500 = 36414 FCFA. Credit cumulatif marie+enfant correct. | I16: ✅ Passé | J16: Agents IA + live (simulate) | K16: 23/06/2026 | O16: Sprint 1 | P16: Production
A17: PAY-015 | B17: P2 — Haute | C17: Crédit d'impôt 3+ enfants — 9 000 FCFA supplémentaires | F17: 1. Employé marié, 3 enfants 2. Crédit = 5 500 + 9 000 = 14 500 FCFA | G17: ITS final correct | H17: Live (brut 1200000, marie 3 enfants): credit = 5500 + 9000 = 14500 -> ITS = 44914 - 14500 = 30414 FCFA. Bareme enfants [3000,6000,9000] correct. | I17: ✅ Passé | J17: Agents IA + live (simulate) | K17: 23/06/2026 | O17: Sprint 1 | P17: Production
A18: PAY-016 | B18: P1 — Critique | C18: Net payable ≥ SMIG 60 000 FCFA | D18: Vérification du plancher légal CI | F18: 1. Créer bulletin pour salaire bas (60 000 FCFA) 2. Vérifier net payable | G18: Net payable ≥ 60 000 FCFA, jamais en dessous du SMIG pour temps plein | H18: SCENARIO INCORRECT (moteur correct): net@60000 = 56220 < 60000. Le SMIG est un minimum de salaire BRUT (pas du net - le net est toujours < brut apres CNPS 6.3%). Le moteur traite le SMIG comme controle (smigCompliant) + validation embauche (baseSalary<SMIG->422), PAS de plancher net (correct legalement). De plus SMIG revalorise a 75000 (cahier dit 60000, perime). A reformuler: 'BRUT >= SMIG'. | I18: ⚠️ Bloqué | J18: Agents IA + live (simulate) | K18: 23/06/2026 | O18: Sprint 1 | P18: Production
A19: PAY-017 | B19: P2 — Haute | C19: Prorata jours travaillés | D19: BRUT_PRORATA = BRUT × (jours_travaillés / jours_ouvrables) | F19: 1. Employé ayant travaillé 13j sur 26j ouvrables 2. Vérifier BRUT_PRORATA | G19: Salaire brut = 50% du brut mensuel contractuel | H19: Live: prorata 13j/26j de 200000 -> brut (rubrique 1000) = 100000 = 50% du brut mensuel. brutProrata = floor(baseSalary x jours/jours_ouvrables). Conforme. | I19: ✅ Passé | J19: Agents IA + live (simulate) | K19: 23/06/2026 | O19: Sprint 1 | P19: Production
A20: PAY-018 | B20: P2 — Haute | C20: Prime de transport intégrée (variable elements) | F20: 1. Ajouter prime transport 30 000 FCFA dans variable elements | G20: Bulletin inclut prime, brut augmenté, CNPS recalculé | H20: Live: variable element {PRIME_TRANSPORT:30000} -> rubrique 1300 = 30000, brut 200000 -> 230000 (+net). Prime integree. NUANCE correcte: la prime transport n'augmente PAS les bases CNPS/ITS (exoneree/non cotisable en CI, conforme spec). Saisie via POST /settings/variable-elements (lie a une periode). | I20: ✅ Passé | J20: Agents IA + live (simulate) | K20: 23/06/2026 | O20: Sprint 1 | P20: Production
A21: PAY-019 | B21: P1 — Critique | C21: Création période de paie | E21: Admin connecté | F21: 1. Paie → Nouvelle période → Mai 2025 2. Créer | G21: Période créée avec statut 'open' | H21: CORRIGE: pas d'endpoint mono-tenant creant une periode au statut 'open' (la creation etait couplee a la generation dans /close qui passe direct en pending_validation). Ajout POST /payroll/periods/:month -> cree la periode statut 'open' (409 si existe) + bouton 'Creer la periode' sur PayrollPage. Generation ensuite via /close. | I21: ✅ Passé | J21: Agents IA + correctif | K21: 23/06/2026 | O21: Sprint 1 | P21: Production
A22: PAY-020 | B22: P1 — Critique | C22: Génération bulletins pour tous les employés actifs | E22: Période ouverte | F22: 1. Période → Générer bulletins 2. Confirmer | G22: Un bulletin par employé actif, calculs CNPS+ITS correct, pas de décimales | H22: Code+flux (POST /payroll/periods/:month/close): 1 pay_slip par employe ACTIF (WHERE is_active=true AND deleted_at IS NULL), calculs CNPS+ITS via calculatePayrollCI, montants ENTIERS (Math.floor + colonnes numeric(N,0) zero decimale). Workflow 2-yeux ensuite (pending_validation -> validate -> closed). | I22: ✅ Passé | J22: Agents IA + live (simulate) | K22: 23/06/2026 | O22: Sprint 1 | P22: Production
A23: PAY-021 | B23: P1 — Critique | C23: Clôture période de paie | E23: Bulletins générés | F23: 1. Période → Clôturer | G23: Statut = 'closed', bulletins figés, plus de modification possible | H23: Code+flux : la cloture passe par workflow 2-yeux open->pending_validation (close)->approve par un AUTRE admin/hr_mgr->'closed'. Re-cloture bloquee (422 deja cloturee / 409 en validation). Bulletins figes (ON CONFLICT DO NOTHING, aucune route de modif post-cloture). Conforme. | I23: ✅ Passé | J23: Agents IA + rendu PDF | K23: 24/06/2026 | O23: Sprint 1 | P23: Production
A24: PAY-022 | B24: P1 — Critique | C24: Téléchargement bulletin PDF — employee | D24: employe@sotra.ci télécharge son bulletin | E24: Bulletins générés | F24: 1. /mon-espace/bulletins 2. Cliquer Télécharger sur un bulletin | G24: PDF téléchargé avec logo SOTRA, mentions CNPS, ITS, NNI, net FCFA, pas de décimales | H24: CORRIGE+verifie : GET /payroll/my-payslips/:id/pdf (employee, RBAC anti-IDOR via employeeId du token) — le BLOQUANT 404 d'un audit anterieur etait obsolete. PDF enrichi : logo tenant (raster), n° CNPS employeur, lignes CNPS/ITS detaillees, NNI, net FCFA ENTIER, cumuls annuels. Rendu verifie visuellement (bulletins d'exemple docs/bulletins-exemples). | I24: ✅ Passé | J24: Agents IA + correctif | K24: 24/06/2026 | O24: Sprint 1 | P24: Production
A25: PAY-023 | B25: P2 — Haute | C25: Badge 'Nouveau' bulletin non consulté | E25: Bulletin non encore ouvert par l'employé | F25: 1. Connecter employe 2. Observer /mon-espace/bulletins | G25: Badge 'Nouveau' visible sur les bulletins dont viewed_by_employee_at IS NULL | H25: Code : colonne viewed_by_employee_at (provisioning) renvoyee par GET /my-payslips + marquage auto a l'affichage ; badge 'Nouveau' UI (MesBulletins) conditionne par viewed_by_employee_at IS NULL (en-tete + par ligne). Conforme. | I25: ✅ Passé | J25: Agents IA + rendu PDF | K25: 24/06/2026 | O25: Sprint 1 | P25: Production
A26: PAY-024 | B26: P1 — Critique | C26: Historique 24 bulletins — mon-espace | F26: 1. /mon-espace/bulletins | G26: Liste des 24 derniers bulletins, triés du plus récent au plus ancien | H26: Code : GET /payroll/my-payslips filtre sur employeeId du token, ORDER BY month DESC LIMIT 24 (24 derniers, plus recent en tete). Conforme. | I26: ✅ Passé | J26: Agents IA + rendu PDF | K26: 24/06/2026 | O26: Sprint 1 | P26: Production
A27: PAY-025 | B27: P1 — Critique | C27: Cumuls annuels corrects sur bulletin | F27: 1. Ouvrir un bulletin de décembre 2. Vérifier cumuls YTD | G27: Cumuls = somme de tous les bulletins de l'année en cours | H27: CORRIGE+verifie : cumuls annuels (YTD) etaient ABSENTS -> ajoutes. Section 'Cumuls annuels' = SUM(brut/CNPS/ITS/net) des bulletins de l'annee <= mois courant, rendue sur le PDF. Libelles adaptes au pays (IPRES+CSS/IR au Senegal). Verifie sur bulletins d'exemple. | I27: ✅ Passé | J27: Agents IA + correctif | K27: 24/06/2026 | O27: Sprint 1 | P27: Production
A28: PAY-026 | B28: P1 — Critique | C28: FCFA entiers — zéro décimale | F28: 1. Ouvrir n'importe quel bulletin 2. Vérifier tous les montants | G28: Aucun montant avec virgule, tout en FCFA entiers | H28: Verifie : montants ENTIERS partout. Moteur = Math.floor sur chaque ligne/total (13 occurrences) ; colonnes pay_slips en numeric(N,0) ; formatMoney du PDF arrondit (Math.round) + separateur milliers, zero decimale. Aucune virgule sur les bulletins d'exemple. Conforme. | I28: ✅ Passé | J28: Agents IA + code/rendu | K28: 24/06/2026 | O28: Sprint 1 | P28: Production
A29: PAY-027 | B29: P2 — Haute | C29: Vue admin — tous les bulletins | D29: Admin peut accéder aux bulletins de tous les employés | F29: 1. Connecter admin 2. Accéder /payroll/payslips | G29: Grille complète avec filtres par période et employé | H29: Code : GET /payroll/payslips (admin/hr) + page PaySlipsPage (grille) avec filtre par PERIODE (?month=YYYY-MM) ; la grille liste tous les employes du mois (nom, net, statut). Filtre periode confirme ; recherche employe via la grille. Conforme. | I29: ✅ Passé | J29: Agents IA + code/rendu | K29: 24/06/2026 | O29: Sprint 1 | P29: Production
A30: PAY-028 | B30: P2 — Haute | C30: Employeur cost calculé | D30: BRUT + cotisations patronales | F30: 1. Vérifier le coût employeur affiché sur le bulletin | G30: employer_cost = gross + total_cnps_pat, affiché correctement | H30: Verifie : moteur employerCost = grossSalary + totalCnpsPat (+ mutuelle pat) [payroll-engine-ci l.310]. Affiche 'Cout total employeur' sur le bulletin (ex. BNI chef dept 2 719 415, BANGA SN 517 328). Conforme. | I30: ✅ Passé | J30: Agents IA + code/rendu | K30: 24/06/2026 | O30: Sprint 1 | P30: Production
A31: PAY-029 | B31: P1 — Critique | C31: [ITS 2024] Célibataire 0 enfant — brut 450 000 | D31: Réforme ITS 2024 : barème appliqué au brut imposable (16 % / 21 % / 24 %…), sans abattement. | E31: Simulateur ITS ou bulletin ; célibataire, 0 enfant (1 part) | F31: 1. Paie → Simulateur ITS 2. Brut imposable 450 000, célibataire, 0 enfant 3. Calculer | G31: ITS = 70 500 FCFA (26 400 + 210 000 × 21 %) ; RICF = 0 | O31: Recette 10/2026 | P31: Production
A32: PAY-030 | B32: P1 — Critique | C32: [ITS 2024] Célibataire 0 enfant — brut 1 500 000 | D32: Tranche 24 %. | E32: Célibataire, 0 enfant | F32: 1. Simulateur ITS → brut 1 500 000 2. Calculer | G32: ITS = 312 000 FCFA | O32: Recette 10/2026 | P32: Production
A33: PAY-031 | B33: P1 — Critique | C33: [ITS 2024] Brut 75 000 — exonéré | D33: Tranche 0 % jusqu'à 75 000. | E33: Célibataire, 0 enfant | F33: 1. Simulateur ITS → brut 75 000 | G33: ITS = 0 | O33: Recette 10/2026 | P33: Production
A34: PAY-032 | B34: P1 — Critique | C34: [ITS 2024] Brut 240 000 — haut de tranche 16 % | D34: Borne de tranche. | E34: Célibataire, 0 enfant | F34: 1. Simulateur ITS → brut 240 000 | G34: ITS = 26 400 FCFA (165 000 × 16 %) | O34: Recette 10/2026 | P34: Production
A35: PAY-033 | B35: P1 — Critique | C35: [ITS 2024] Marié 2 enfants (3 parts) — brut 500 000 | D35: Réduction d'impôt pour charges de famille (RICF) : 5 500 par demi-part au-delà de 1. | E35: Marié, 2 enfants | F35: 1. Simulateur ITS → brut 500 000, marié, 2 enfants 2. Vérifier le détail | G35: Impôt brut 81 000 − RICF 22 000 = ITS 59 000 FCFA ; 3 parts affichées | O35: Recette 10/2026 | P35: Production
A36: PAY-034 | B36: P1 — Critique | C36: [ITS 2024] Célibataire 1 enfant (2 parts) — RICF | D36: RICF pour 2 parts. | E36: Célibataire, 1 enfant | F36: 1. Simulateur ITS → brut 500 000, célibataire, 1 enfant | G36: RICF = 11 000 FCFA ; ITS = 81 000 − 11 000 = 70 000 | O36: Recette 10/2026 | P36: Production
A37: PAY-035 | B37: P1 — Critique | C37: [ITS 2024] Plafond 5 parts — RICF maximale | D37: Le nombre de parts est plafonné à 5. | E37: Marié, 6 enfants | F37: 1. Simulateur ITS → brut 1 500 000, marié, 6 enfants | G37: Parts = 5 (plafond) ; RICF = 44 000 FCFA ; ITS = 312 000 − 44 000 = 268 000 | O37: Recette 10/2026 | P37: Production
A38: PAY-036 | B38: P1 — Critique | C38: [ITS 2024] Assiette — ni abattement ni déduction CNPS | D38: L'assiette ITS est le brut imposable ; l'ancien abattement 15 % et la déduction CNPS ne s'appliquent plus (remplace PAY-012). | E38: Bulletin d'un salarié brut 450 000, CNPS retraite prélevée | F38: 1. Générer le bulletin 2. Ouvrir « Comprendre mon bulletin » sur la ligne ITS | G38: Base ITS = 450 000 (brut imposable) ; aucune ligne d'abattement ; CNPS non déduite de l'assiette ; ITS 70 500 | O38: Recette 10/2026 | P38: Production
A39: PAY-037 | B39: P1 — Critique | C39: [ITS 2024] Éléments hors assiette — maternité, AT, frais | D39: Indemnités maternité/AT et remboursements de frais ne sont pas imposables. | E39: Salarié avec ligne maternité (1700), indemnité AT et remboursement de note de frais sur le mois | F39: 1. Générer le bulletin 2. Comparer brut imposable et total des gains | G39: Ces lignes figurent au bulletin mais sont exclues de l'assiette ITS (et de la base CNPS selon règle) ; ITS calculé sur le seul brut imposable | O39: Recette 10/2026 | P39: Production
A40: PAY-038 | B40: P1 — Critique | C40: Arrondi maternité — total exact de 140 000 | D40: Départ en congé maternité en cours de mois : salaire prorata + indemnité maternité. | E40: Salariée base 140 000 ; congé maternité débutant le 19/10/2026 (98 j) | F40: 1. Saisir le congé maternité au 19/10 2. Générer la paie 2026-10 3. Additionner ligne 1000 et ligne 1700 | G40: Ligne 1000 (salaire prorata) + ligne 1700 (indemnité maternité) = 140 000 FCFA exactement (aucun écart d'arrondi de ±1) | O40: Recette 10/2026 | P40: Production
A41: PAY-039 | B41: P1 — Critique | C41: Solde de tout compte — indemnité de licenciement au prorata | D41: Indemnité 30 % du salaire par année (1-5 ans), prorata des mois au-delà de l'année complète. | E41: Salarié Yao, embauché le 01/10/2025, sortie 31/10/2026 (licenciement), base 250 000 | F41: 1. Sorties → Nouveau dossier (licenciement, départ 31/10/2026) 2. Calculer le solde 3. Générer la paie 2026-10 (bulletin de solde) | G41: Indemnité de licenciement = 81 250 FCFA (250 000 × 30 % × 13/12) ; reprise sur le bulletin du mois de sortie puis marquée payée | O41: Recette 10/2026 | P41: Production
A42: PAY-040 | B42: P2 — Haute | C42: Bulletin de solde — congés non pris et préavis | D42: Les indemnités du solde sont portées une seule fois sur le bulletin. | E42: Dossier de sortie soldé avec congés restants et préavis non effectué | F42: 1. Générer la paie du mois de sortie 2. Regénérer la paie (réouverture test) 3. Générer la paie du mois suivant | G42: Lignes congés + préavis + licenciement présentes une seule fois ; salarié sorti absent du lot suivant | O42: Recette 10/2026 | P42: Production
... A64: PAY-062 | B64: P2 — Haute | C64: Erreurs de paie — messages personnalisés | D64: Aucune erreur technique brute à l'écran. | E64: Période déjà clôturée, salarié sans salaire de base | F64: 1. Générer une période déjà clôturée 2. Générer avec un salarié sans salaire | G64: Messages métier en français (ex. « Cette période est clôturée ») ; aucun code SQL/stack | O64: Recette 10/2026 | P64: Production

Sheet ABS
A1: GESTION DES ABSENCES · 22 scénarios
A2: ID Test | B2: Priorité | C2: Titre du scénario | D2: Description / Contexte | E2: Prérequis / Données | F2: Étapes détaillées | G2: Résultat attendu | H2: Résultat obtenu | I2: Statut | J2: Testeur | K2: Date test | L2: Durée (min) | M2: Ticket / Requalification | N2: Commentaire / Amélioration | O2: Sprint | P2: Env.
A3: ABS-001 | B3: P1 — Critique | C3: Soldes congés affichés — /mon-espace/absences | D3: 2.5 jours ouvrables/mois CI | E3: employe@sotra.ci connecté | F3: 1. /mon-espace/absences 2. Observer les barres de soldes | G3: CP affiché avec acquired, taken, remaining. Barres de progression colorées | H3: Code : GET /absences/balances (employee, filtre employeeId du token) renvoie acquired/taken/pending/remaining + libelle/couleur du type. UI MesAbsences affiche cartes par type avec pastille couleur + restant/acquis. (Mineur : pastille couleur, pas de barre de progression remplie ; taken present en API.) | I3: ✅ Passé | J3: Agents IA (code) | K3: 24/06/2026 | O3: Sprint 1 | P3: Production
A4: ABS-002 | B4: P1 — Critique | C4: Nouvelle demande absence — formulaire complet | F4: 1. Bouton '+ Demander une absence' 2. Type: CP, dates, motif 3. Soumettre | G4: Demande créée statut 'pending', notification envoyée au manager | H4: CORRIGE : POST /absences cree statut 'pending' (default), Zod strict, ANTI-IDOR (employeeId force depuis le token pour un employee). Le bouton '+ Demander une absence' est cable. AJOUT correctif : notification au MANAGER de l'employe a la creation (table notifications, resolu via manager_id->user_id) — etait absente. | I4: ✅ Passé | J4: Agents IA + correctif | K4: 24/06/2026 | O4: Sprint 1 | P4: Production
A5: ABS-003 | B5: P2 — Haute | C5: Validation dates — début < fin | F5: 1. Saisir date début > date fin 2. Soumettre | G5: Erreur Zod côté client + validation serveur, demande non créée | H5: CORRIGE : la validation date_debut <= date_fin etait ABSENTE (client + serveur) -> une demande aux dates inversees etait creee (201, days=0). Ajout refine Zod SERVEUR (createAbsenceSchema) + CLIENT (MesAbsences) -> 400 avant tout INSERT. Test ajoute (debut>fin -> 400, aucune creation). | I5: ✅ Passé | J5: Agents IA + correctif | K5: 24/06/2026 | O5: Sprint 1 | P5: Production
A6: ABS-004 | B6: P1 — Critique | C6: Workflow approbation — manager approve | E6: Demande pending + manager connecté | F6: 1. Connecter manager 2. Voir demandes à valider 3. Approuver | G6: Statut → 'approved', solde CP décompté, notification employé | H6: CORRIGE : PATCH /absences/:id/approve. RBAC fail-closed : un manager ne valide QUE ses subordonnes directs (manager_id), auto-approbation interdite. A l'approbation : statut 'approved', solde decompte (taken+, pending-), workflow multi-niveaux. AJOUT correctif : notification a l'employe de l'approbation — etait absente. | I6: ✅ Passé | J6: Agents IA + correctif | K6: 24/06/2026 | O6: Sprint 1 | P6: Production
A7: ABS-005 | B7: P2 — Haute | C7: Workflow — manager refuse | F7: 1. Manager refuse une demande 2. Motif de refus saisi | G7: Statut → 'rejected', solde non décompté, notification employé avec motif | H7: CORRIGE : PATCH /absences/:id/reject. Statut 'rejected', motif enregistre (rejection_reason), solde NON decompte (pending restitue, taken intact). RBAC equipe fail-closed. AJOUT correctif : notification a l'employe avec MOTIF — etait absente. | I7: ✅ Passé | J7: Agents IA + correctif | K7: 24/06/2026 | O7: Sprint 1 | P7: Production
A8: ABS-006 | B8: P2 — Haute | C8: Annulation demande pending par l'employé | E8: Demande en statut pending | F8: 1. Employé → liste absences → Annuler | G8: Demande supprimée ou statut cancelled, solde inchangé | H8: Code : PATCH /absences/:id/cancel — l'employe annule SA propre demande pending (statut 'cancelled'), le solde reserve est restitue (pending-, remaining+). UI MesAbsences : bouton Annuler (cancelMut) + statut colore gris. Conforme. | I8: ✅ Passé | J8: Agents IA (code) | K8: 24/06/2026 | O8: Sprint 1 | P8: Production
A9: ABS-007 | B9: P1 — Critique | C9: Calcul en jours ouvrables (lundi→samedi CI) | D9: Pas les jours calendaires | F9: 1. Saisir du lundi au vendredi suivant (5j) 2. Vérifier décompte | G9: 5 jours ouvrables décomptés (samedi inclus si travaillé) | H9: Code : calcul des jours = boucle du debut a la fin, dimanche (getDay()==0) EXCLU, samedi INCLUS (semaine 6 j Code du Travail CI). Lun->ven = 5 j. Conforme. | I9: ✅ Passé | J9: Agents IA (code) | K9: 24/06/2026 | O9: Sprint 1 | P9: Production
A10: ABS-008 | B10: P2 — Haute | C10: Jours fériés CI exclus du calcul | D10: Si absence couvre un jour férié CI | E10: Table jours fériés CI 2024/2025 en base | F10: 1. Absence couvrant le 07 août 2025 (Fête Nationale) 2. Vérifier décompte | G10: Jour férié non compté dans les jours d'absence | H10: CORRIGE : les jours FERIES n'etaient PAS exclus (seuls les dimanches l'etaient) -> un conge couvrant le 07/08 (Fete Nationale) comptait ce jour. Ajout utils/ci-holidays (dates fixes CI + fetes chretiennes mobiles via Paques) ; exclusion dans le calcul. NB : fetes musulmanes (Aid/Tabaski/Maouloud, calendrier lunaire) a parametrer par annee. Test ajoute (07/08 ferie). | I10: ✅ Passé | J10: Agents IA + correctif | K10: 24/06/2026 | O10: Sprint 1 | P10: Production
A11: ABS-009 | B11: P2 — Haute | C11: Demi-journée toggle | D11: Absence de demi-journée = 0.5 jour | F11: 1. Cocher 'demi-journée' 2. Sélectionner date 3. Soumettre | G11: 0.5 jour décompté du solde | H11: Code : toggle 'demi-journee' (halfDay) -> days force a 0.5, decompte 0.5 du solde. Test existant (demi-journee days=0.5 -> 201). Conforme. | I11: ✅ Passé | J11: Agents IA (code) | K11: 24/06/2026 | O11: Sprint 1 | P11: Production
A12: ABS-010 | B12: P1 — Critique | C12: Historique absences employé — statuts colorés | D12: Badge couleur selon statut | F12: 1. /mon-espace/absences → liste historique | G12: pending=orange, approved=vert, rejected=rouge | H12: Code : MesAbsences STATUS_COLORS : pending/submitted=jaune-ambre (orange), approved=vert, rejected=rouge, cancelled=gris. Liste historique avec badge colore par statut. Conforme. | I12: ✅ Passé | J12: Agents IA (code) | K12: 24/06/2026 | O12: Sprint 1 | P12: Production
A13: ABS-011 | B13: P1 — Critique | C13: Admin voit toutes les absences de tous les employés | E13: Admin connecté | F13: 1. /absences (vue admin) | G13: Toutes les absences du tenant, filtrables par employé/type/période | H13: Code : GET /absences (admin/hr_mgr/hr_off) renvoie TOUTES les absences du tenant, filtrables par employeeId, status, year (annee). Conforme. | I13: ✅ Passé | J13: Agents IA (code) | K13: 24/06/2026 | O13: Sprint 1 | P13: Production
A14: ABS-012 | B14: P2 — Haute | C14: Manager voit absences de son équipe seulement | E14: Manager connecté | F14: 1. /absences (vue manager) | G14: Filtrée au département du manager, pas les autres équipes | H14: Code : GET /absences pour role=manager ajoute 'AND e.manager_id = <son employeeId>' (fail-closed OWASP A01 : manager sans dossier lie -> liste vide). Il ne voit que son equipe directe. Conforme. | I14: ✅ Passé | J14: Agents IA (code) | K14: 24/06/2026 | O14: Sprint 1 | P14: Production
A15: ABS-013 | B15: P1 — Critique | C15: Employee voit ses propres absences seulement | E15: employe@sotra.ci | F15: 1. /mon-espace/absences | G15: Uniquement les absences de l'employé connecté | H15: Code : GET /absences/my-absences filtre sur l'employeeId du token -> l'employee ne voit QUE ses propres absences. Conforme. | I15: ✅ Passé | J15: Agents IA (code) | K15: 24/06/2026 | O15: Sprint 1 | P15: Production
A16: ABS-014 | B16: P2 — Haute | C16: Planification calendrier — absences colorées | F16: 1. Onglet Calendrier 2. Observer le mois en cours | G16: Absences apparaissent sur les jours concernés, colorées par type | H16: CORRIGE : ajout d'une VUE CALENDRIER mensuelle (toggle Liste/Calendrier) dans /mon-espace/absences. Grille du mois (Lun-Dim) ou les absences apparaissent sur les jours concernes, colorees par type (type_color) + navigation mois precedent/suivant. La vue liste coloree existait deja. | I16: ✅ Passé | J16: Agents IA + correctif | K16: 24/06/2026 | O16: Sprint 1 | P16: Production
A17: ABS-015 | B17: P2 — Haute | C17: Solde mis à jour après approbation | F17: 1. Solde CP avant = 15j 2. Demande 5j approuvée | G17: Solde = 15 - 5 = 10j après approbation | H17: Code : a l'approbation, absence_balances.taken += days, pending -= days ; remaining a deja ete decremente a la creation. Solde restant 15 -> 10 apres une demande de 5 j approuvee. Conforme. | I17: ✅ Passé | J17: Agents IA (code) | K17: 24/06/2026 | O17: Sprint 1 | P17: Production
A18: ABS-016 | B18: P3 — Moyenne | C18: Notification manager à la soumission | E18: SMTP configuré | F18: 1. Employé soumet une demande 2. Vérifier email manager | G18: Email reçu avec détails de la demande et lien d'approbation | H18: CORRIGE : email au MANAGER a la soumission (sendAbsenceRequestEmail : type, periode, jours, motif + bouton 'Examiner la demande'), en complement de la notif in-app. Best-effort via SMTP tenant/plateforme, non bloquant. | I18: ✅ Passé | J18: Agents IA + correctif | K18: 24/06/2026 | O18: Sprint 1 | P18: Production
A19: ABS-017 | B19: P1 — Critique | C19: Acquisition congés payés — 2,2 j/mois + ancienneté | D19: Solde CP recalculé selon l'ancienneté (CT art. 25.1-25.2). | E19: Salarié avec 6 ans d'ancienneté au 31/10/2026 | F19: 1. Absences → Soldes → salarié 2. Vérifier acquis | G19: Acquis = 2,2 × mois de service de l'année + 1 j d'ancienneté (> 5 ans) ; arrondi selon règle ; affiché dans Mon espace | O19: Recette 10/2026 | P19: Production
A20: ABS-018 | B20: P1 — Critique | C20: Congé maternité 98 jours | D20: Type maternité : 14 semaines, dates calculées. | E20: Salariée SOTRA | F20: 1. Absences → Saisir pour un salarié → Maternité, début 19/10/2026 | G20: Durée 98 jours calendaires, fin calculée automatiquement ; indemnisation maternité reprise en paie (voir PAY) | O20: Recette 10/2026 | P20: Production
A21: ABS-019 | B21: P2 — Haute | C21: Politique de congés du tenant (plus favorable) | D21: Paramètres → Légal / Pays → Politique de congés (leave_policy). | E21: admin@sotra.ci | F21: 1. Définir 2,5 j/mois (convention) 2. Consulter le solde d'un salarié | G21: Acquisition recalculée à 2,5 j/mois ; une valeur moins favorable que la loi est refusée | O21: Recette 10/2026 | P21: Production
A22: ABS-020 | B22: P2 — Haute | C22: Saisie d'une absence par la RH pour un salarié | D22: AbsenceEntryModal — saisie par la RH ou un responsable pour son équipe. | E22: chef.perso@sotra.ci (hr_officer, « Chef Personnel ») | F22: 1. Absences → Saisir une absence → salarié, type, dates 2. Enregistrer | G22: Absence créée ; si saisie par un responsable, vaut visa de son niveau dans le circuit | O22: Recette 10/2026 | P22: Production
A23: ABS-021 | B23: P2 — Haute | C23: Types d'absence paramétrables | D23: Paramètres → Types absences. | E23: admin@sotra.ci | F23: 1. Créer un type « Événement familial » 3 j, payé 2. Le désactiver/supprimer quand utilisé | G23: Type disponible dans le formulaire ; suppression d'un type utilisé refusée ou archivage | O23: Recette 10/2026 | P23: Production
A24: ABS-022 | B24: P2 — Haute | C24: Absence non payée — impact paie | D24: Une absence non rémunérée réduit le salaire au prorata. | E24: Absence sans solde de 2 jours approuvée | F24: 1. Générer la paie du mois | G24: Retenue au prorata des jours ouvrables, libellé clair | O24: Recette 10/2026 | P24: Production

Sheet REC
A1: RECRUTEMENT & ATS · 29 scénarios
A2: ID Test | B2: Priorité | C2: Titre du scénario | D2: Description / Contexte | E2: Prérequis / Données | F2: Étapes détaillées | G2: Résultat attendu | H2: Résultat obtenu | I2: Statut | J2: Testeur | K2: Date test | L2: Durée (min) | M2: Ticket / Requalification | N2: Commentaire / Amélioration | O2: Sprint | P2: Env.
A3: REC-001 | B3: P1 — Critique | C3: Création offre d'emploi | E3: Admin/RH connecté | F3: 1. /recruitment/new 2. Titre, lieu, type contrat, fourchette salariale FCFA, description 3. Publier | G3: Offre créée, statut 'open', visible dans le tableau de bord recrutement | H3: Code : POST /recruitment/jobs (status 'open' par défaut + published_at). Bouton 'Nouvelle offre' câblé. Offre visible dashboard recrutement. RBAC admin/hr_mgr/hr_off. | I3: ✅ Passé | J3: Agents IA (code) | K3: 24/06/2026 | O3: Sprint 1 | P3: Production
A4: REC-002 | B4: P2 — Haute | C4: Clôture offre d'emploi | E4: Offre ouverte | F4: 1. Actions → Clôturer l'offre | G4: Statut = 'closed', n'apparaît plus dans les offres actives | H4: CORRIGE : il n'existait PAS de bouton 'Clôturer' direct (seul un toggle Pause). Ajout d'une action 'Clôturer l'offre' (status=closed) dans le tableau -> disparaît des offres actives. Bascule aussi non-publique côté carrières. | I4: ✅ Passé | J4: Agents IA + correctif | K4: 24/06/2026 | O4: Sprint 1 | P4: Production
A5: REC-003 | B5: P1 — Critique | C5: Pipeline Kanban — 5 colonnes | D5: new → screening → interview → offer → hired | E5: Offre ouverte avec candidatures | F5: 1. Vue Kanban de l'offre | G5: 5 colonnes affichées, candidatures déplaçables par drag & drop | H5: Code : pipeline Kanban à 7 colonnes (new/screening/interview/test/offer/hired/rejected) - supérieur aux 5 attendues. DnD HTML5 opérationnel (fix Chromium setTimeout + setData Firefox). | I5: ✅ Passé | J5: Agents IA (code) | K5: 24/06/2026 | O5: Sprint 1 | P5: Production
A6: REC-004 | B6: P1 — Critique | C6: Ajout candidature | F6: 1. Offre → Ajouter candidature 2. Prénom, nom, email, téléphone CI, CV | G6: Candidature créée en stage 'new' | H6: CORRIGE : aucun bouton 'Ajouter candidature' dans l'espace RH (endpoint POST /applications existait mais jamais appelé) + ZERO validation. Ajout modal RH 'Ajouter une candidature' (stage=new) + validation Zod serveur + téléphone CI (+225 8-10 chiffres) client+serveur. | I6: ✅ Passé | J6: Agents IA + correctif | K6: 24/06/2026 | O6: Sprint 1 | P6: Production
A7: REC-005 | B7: P2 — Haute | C7: Déplacement stage Kanban | F7: 1. Glisser une candidature de 'screening' vers 'interview' | G7: Stage mis à jour, historique conservé | H7: Code : déplacement de stage par DnD -> PATCH /applications/:id/stage (RBAC équipe), historique conservé (recruitment_decisions + audit_log sur hired/rejected). Fix Chromium dragstart présent. | I7: ✅ Passé | J7: Agents IA (code) | K7: 24/06/2026 | O7: Sprint 1 | P7: Production
A8: REC-006 | B8: P3 — Moyenne | C8: Scoring IA candidature | E8: ANTHROPIC_API_KEY configuré | F8: 1. Ouvrir une candidature 2. Cliquer 'Analyser avec IA' | G8: Score de compatibilité retourné avec facteurs explicatifs en français | H8: Code : POST /applications/:id/analyze-cv (IA Claude/Mistral, prompt 100% FR contexte CI/OHADA) -> score + facteurs (forces/gaps/redFlags/questions). Bouton 'Analyser avec IA' câblé. Fallback explicite si pas de clé IA. Anti prompt-injection. | I8: ✅ Passé | J8: Agents IA (code) | K8: 24/06/2026 | O8: Sprint 1 | P8: Production
A9: REC-007 | B9: P3 — Moyenne | C9: Génération contrat OHADA à l'embauche | D9: Stage = hired déclenche la génération du contrat | F9: 1. Déplacer candidature vers 'hired' 2. Compléter informations contrat | G9: PDF CDI/CDD CI généré avec mentions OHADA obligatoires | H9: ECART (P3, différé) : la génération du contrat OHADA à l'embauche n'existe pas (pas de PDF CDI/CDD, generateHRDocument non implémenté ; le passage 'hired' ne propose rien). Le module contracts capture les données OHADA mais ne génère aucun PDF. Décision utilisateur : laisser en écart P3, à planifier avec le module Contrats. | I9: ⚠️ Bloqué | J9: Agents IA (code) | K9: 24/06/2026 | O9: Sprint 1 | P9: Production
A10: REC-008 | B10: P2 — Haute | C10: Fourchette salariale en FCFA | F10: 1. Créer offre avec salary_min 250 000, salary_max 350 000 | G10: Affiché 'De 250 000 à 350 000 FCFA' sans décimales | H10: CORRIGE : la fourchette s'affichait '250 000 F CFA – 350 000 F CFA'. Reformatée en 'De 250 000 à 350 000 FCFA' (entiers, séparateur de milliers, zéro décimale). Exigence numérique (entier/0 décimale) déjà respectée. | I10: ✅ Passé | J10: Agents IA + correctif | K10: 24/06/2026 | O10: Sprint 1 | P10: Production
A11: REC-009 | B11: P2 — Haute | C11: Filtrage offres par statut | F11: 1. Filtre 'Ouvertes' sur la liste | G11: Seules les offres open affichées | H11: Code : filtres de statut côté UI (toutes/externes/internes/fermées) sur le jeu d'offres ; seules les 'open' affichées hors filtre 'fermées'. API supporte ?status= (non utilisé par cette page, filtrage client). | I11: ✅ Passé | J11: Agents IA (code) | K11: 24/06/2026 | O11: Sprint 1 | P11: Production
A12: REC-010 | B12: P1 — Critique | C12: [NEW] Onglet Sourcing IA dans Recrutement | D12: Nouvel onglet entre Pipeline et Carrières | E12: API + Web déployés branche feat/multi-pays-recrutement-owasp | F12: 1. /recruitment 2. Cliquer onglet 'Sourcing IA' (icône Sparkles) 3. Sélectionner une offre 'Chauffeur Bus Senior' | G12: Onglet visible, 3e onglet actif. Affichage automatique des profils sourcés en cache (cards émeraude) | H12: Code : onglet 'Sourcing IA' (3e onglet, icône Sparkles) dans /recruitment. Sélection offre 'Chauffeur Bus Senior' -> profils sourcés en cache (cards émeraude). Conforme. | I12: ✅ Passé | J12: Agents IA (code) | K12: 24/06/2026 | O12: Sprint 1 | P12: Production
A13: REC-011 | B13: P1 — Critique | C13: [NEW] Visualisation profils sourcés du seed | D13: Le seed pré-remplit 8 profils Chauffeur + 6 profils RH SOTRA + 5 profils OpenLab | E13: DB seedée avec données sourced_profiles | F13: 1. Onglet Sourcing IA 2. Sélectionner offre 'Chauffeur Bus Senior' | G13: 8 cards profils visibles avec match_score, ville, disponibilité, plateforme suggérée, salaire FCFA | H13: Code : seed crée EXACTEMENT 8 profils sourcés pour 'Chauffeur Bus Senior' (seedSourced) avec match_score, ville, disponibilité, plateforme suggérée, salaire FCFA. GET /jobs/:id/sourced-profiles (tri match_score DESC). Conforme. | I13: ✅ Passé | J13: Agents IA (code) | K13: 24/06/2026 | O13: Sprint 1 | P13: Production
A14: REC-012 | B14: P1 — Critique | C14: [NEW] Transfert profil unique vers pipeline Kanban | D14: Bouton 'Transférer' sur chaque carte profil | E14: Profils en cache présents | F14: 1. Carte profil → bouton 'Transférer' 2. Observer le badge 'Dans le pipeline' 3. Aller onglet Pipeline Kanban | G14: Profil créé comme candidature (source=sourced_ai, stage=new) visible dans la colonne Nouveau du Kanban | H14: Code : POST /jobs/:id/sourced-profiles/:profileId/transfer -> application (source=sourced_ai, stage=new), idempotent (409), transaction. Badge 'Dans le pipeline'. Visible colonne Nouveau du Kanban. Conforme. | I14: ✅ Passé | J14: Agents IA (code) | K14: 24/06/2026 | O14: Sprint 1 | P14: Production
A15: REC-013 | B15: P1 — Critique | C15: [NEW] Transfert en masse 'Tout transférer' | D15: Bouton 'Tout transférer (N)' transfère tous les profils non transférés | E15: Au moins 3 profils non transférés | F15: 1. Bannière émeraude en haut → 'Tout transférer (N)' 2. Confirmer 3. Aller Pipeline Kanban | G15: N profils créés en transaction, message succès affiché. Tous présents dans colonne 'Nouveau' du Kanban | H15: Code : POST .../transfer-all -> transfert en masse TRANSACTIONNEL (BEGIN/COMMIT unique, FOR UPDATE), message succès, tous en colonne Nouveau. Conforme. | I15: ✅ Passé | J15: Agents IA (code) | K15: 24/06/2026 | O15: Sprint 1 | P15: Production
A16: REC-014 | B16: P1 — Critique | C16: [NEW] Drag-and-drop Kanban sur profil transféré | D16: Vérifier que les profils issus du sourcing peuvent être déplacés normalement | E16: 1+ profil transféré présent | F16: 1. Pipeline Kanban 2. Glisser le profil de 'Nouveau' vers 'Présélection' 3. Vérifier le PATCH /applications/:id/stage | G16: Stage mis à jour, profil dans la nouvelle colonne, aucune erreur 500 | H16: Code : PATCH stage générique (UPDATE par id, aucun filtre source) -> DnD d'un profil transféré (source=sourced_ai) fonctionne sans 500. Conforme. | I16: ✅ Passé | J16: Agents IA (code) | K16: 24/06/2026 | O16: Sprint 1 | P16: Production
A17: REC-015 | B17: P2 — Haute | C17: [NEW] Mode Compare Claude vs Mistral | D17: Comparaison parallèle des deux modèles IA | E17: ANTHROPIC_API_KEY + MISTRAL_API_KEY configurés | F17: 1. Onglet Sourcing IA 2. Mode 'Compare Claude vs Mistral' 3. Lancer la génération | G17: Rapport comparatif affiché : latence, coût, richesse, gagnant, recommandation. Toggle vue Claude/Mistral | H17: Code : POST /jobs/:id/source/compare (Claude vs Mistral en parallèle) -> rapport latence/coût/richesse/winner/ratios/recommendation + toggle vue Claude/Mistral. 422 si Mistral non configuré. Conforme. | I17: ✅ Passé | J17: Agents IA (code) | K17: 24/06/2026 | O17: Sprint 1 | P17: Production
A18: REC-016 | B18: P2 — Haute | C18: [NEW] Multi-pays Sourcing IA (CI + SN + GH) | D18: Cocher plusieurs pays cibles dans le sélecteur | F18: 1. Sélecteur pays : cocher CI, SN, GH 2. Plateformes pré-suggérées s'adaptent 3. Générer | G18: L'IA produit des profils des 3 pays avec noms, localisations et plateformes locales cohérentes | H18: Code : sélecteur multi-pays (visible si tenant multi-pays) + plateformes locales par pays (CI:Emploi.ci/RMO/Novojob ; SN:Emploi.sn/Senjob ; GH:Jobberman/JobWebGhana) ; prompt IA inclut les pays cibles. Conforme. | I18: ✅ Passé | J18: Agents IA (code) | K18: 24/06/2026 | O18: Sprint 1 | P18: Production
A19: REC-017 | B19: P2 — Haute | C19: [NEW] Contact email depuis carte profil | D19: Bouton Message ouvre un dialog avec subject + body pré-remplis | F19: 1. Carte profil → bouton 'Message' 2. Vérifier le contenu pré-rempli 3. Copier le message ou ouvrir LinkedIn search | G19: Dialog affiche objet/corps avec prénom/poste/entreprise. Lien LinkedIn search ouvre Google search préformatée | H19: PARTIEL (mineur) : bouton 'Message' -> dialog objet/corps pré-rempli (prénom/poste/entreprise) + lien LinkedIn People search préformaté. Ecart : pas de lien Google search ni mailto (copie presse-papier). Acceptable, LinkedIn search présent. | I19: ✅ Passé | J19: Agents IA (code) | K19: 24/06/2026 | O19: Sprint 1 | P19: Production
A20: REC-018 | B20: P1 — Critique | C20: [FIX] Modal Nouvelle offre — pas de débordement | D20: Régression UI résolue : modal en flex-column avec body scrollable + footer sticky | F20: 1. Cliquer 'Nouvelle offre' 2. Redimensionner navigateur à 768px de haut 3. Vérifier que les boutons Annuler/Créer restent visibles | G20: Modal centrée, body scroll interne, header + footer toujours visibles, pas de débordement vertical | H20: CORRIGE/Vérifié : modal 'Nouvelle offre' en flex colonne, header + footer (Annuler/Créer) sticky, body overflow-y-auto borné (max-h 90vh) -> aucun débordement à 768px. Idem EditJobModal. | I20: ✅ Passé | J20: Agents IA (code) | K20: 24/06/2026 | O20: Sprint 1 | P20: Production
A21: REC-019 | B21: P1 — Critique | C21: Pré-tri CV — critères éliminatoires (règles dures) | D21: Paramétrage des critères de pré-sélection d'une offre (screening-criteria). | E21: rh@sotra.ci (hr_manager, « Responsable Paie ») ; offre ouverte | F21: 1. Offre → Pré-tri → diplôme minimum, années d'expérience, langue 2. Enregistrer 3. Prévisualiser sur les candidatures | G21: Critères persistés ; aperçu indique candidats retenus/rejetés avec motif | O21: Recette 10/2026 | P21: Production
A22: REC-020 | B22: P1 — Critique | C22: Pré-tri CV — auto-rejet des candidatures publiques | D22: Application du pré-tri (screening/apply) et file de revue. | E22: Critères définis ; 3 candidatures dont 1 non conforme | F22: 1. Appliquer le pré-tri 2. Ouvrir la file de revue 3. Décider manuellement sur un cas limite | G22: Candidature non conforme rejetée avec motif ; cas limites en file ; décision tracée dans l'historique des décisions | O22: Recette 10/2026 | P22: Production
A23: REC-021 | B23: P2 — Haute | C23: Pré-tri — questions de qualification | D23: screening-questions sur l'offre publique. | E23: Offre avec 2 questions éliminatoires | F23: 1. Configurer les questions 2. Postuler en public avec une réponse éliminatoire | G23: Réponse éliminatoire → candidature marquée rejetée par le pré-tri | O23: Recette 10/2026 | P23: Production
A24: REC-022 | B24: P1 — Critique | C24: Page carrières publique — candidature avec CV | D24: /careers/:tenantSlug ; POST public apply + upload CV. | E24: Navigateur non connecté ; offre publique SOTRA | F24: 1. Ouvrir /careers/sotra 2. Postuler en joignant un PDF 3. Joindre un .exe renommé .pdf | G24: Candidature reçue dans le pipeline ; fichier à signature non PDF refusé ; CV analysé antivirus si activé | O24: Recette 10/2026 | P24: Production
A25: REC-023 | B25: P2 — Haute | C25: Offres internes — candidature d'un salarié | D25: Mon espace → Mes offres internes (internal-jobs/apply). | E25: employe@sotra.ci (Kouassi Coulibaly) avec job_level renseigné | F25: 1. Mes offres internes → offre ciblée → Postuler | G25: Candidature interne créée, visible RH, salarié ne voit que les offres ciblant son niveau | O25: Recette 10/2026 | P25: Production
A26: REC-024 | B26: P2 — Haute | C26: Génération de contrat depuis une candidature | D26: POST /applications/:id/contract. | E26: Candidat au stade « Embauché » | F26: 1. Carte candidat → Générer le contrat | G26: Contrat brouillon pré-rempli (OHADA) lié au futur employé ; document PDF généré | O26: Recette 10/2026 | P26: Production
A27: REC-025 | B27: P2 — Haute | C27: Structure d'offre APEC | D27: Référence auto, niveau d'expérience, statut, secteur, formation, avantages, mode de travail, processus. | E27: rh@sotra.ci (hr_manager, « Responsable Paie ») | F27: 1. Nouvelle offre → remplir tous les champs APEC 2. Publier et consulter la page publique | G27: Référence générée, tous les champs affichés côté interne et public | O27: Recette 10/2026 | P27: Production
A28: REC-026 | B28: P1 — Critique | C28: Simulations d'entretien — configuration tenant | D28: Module interview_sim (opt-in) : Paramètres → Simulations d'entretien. | E28: Module activé par le super_admin ; admin@ | F28: 1. Paramètres → Simulations d'entretien → activer interne/externe, durée du jeton, banque de questions 2. Enregistrer | G28: Configuration persistée ; module désactivé → routes /interview-sim en 403 | O28: Recette 10/2026 | P28: Production
A29: REC-027 | B29: P1 — Critique | C29: Simulation externe — lien public à jeton éphémère | D29: /entrainement-entretien/:token, consentement obligatoire, résultats privés. | E29: Offre publique avec simulation activée | F29: 1. Candidat ouvre le lien 2. Refuser puis accepter le consentement 3. Répondre (voix navigateur ou texte) et soumettre 4. Rejouer le lien après expiration | G29: Sans consentement aucun enregistrement ; feedback IA restitué au candidat uniquement ; jeton expiré refusé | O29: Recette 10/2026 | P29: Production
A30: REC-028 | B30: P2 — Haute | C30: Simulation interne — entraînement privé du salarié | D30: internal-jobs/:jobId/start|submit, résultats non visibles par la RH. | E30: employe@sotra.ci (Kouassi Coulibaly) | F30: 1. Mes offres internes → S'entraîner à l'entretien 2. Soumettre 3. rh@ tente de consulter le résultat | G30: Entraînement réalisé, feedback personnel ; aucune donnée exposée à la RH (entraînement privé) | O30: Recette 10/2026 | P30: Production
A31: REC-029 | B31: P2 — Haute | C31: Recrutement — RBAC manager | D31: Le manager voit les offres de son périmètre en lecture. | E31: manager@sotra.ci (manager, « Chef Dépôt ») | F31: 1. Recrutement 2. Tenter de créer/supprimer une offre | G31: Lecture des offres de son équipe ; création/suppression refusées (403) | O31: Recette 10/2026 | P31: Production

Sheet SRC
A1: SOURCING IA MULTI-PAYS AFRIQUE · 11 scénarios
A2: ID Test | B2: Priorité | C2: Titre du scénario | D2: Description / Contexte | E2: Prérequis / Données | F2: Étapes détaillées | G2: Résultat attendu | H2: Résultat obtenu | I2: Statut | J2: Testeur | K2: Date test | L2: Durée (min) | M2: Ticket / Requalification | N2: Commentaire / Amélioration | O2: Sprint | P2: Env.
A3: SRC-001 | B3: P1 — Critique | C3: Endpoint POST /jobs/:id/source — Claude seul | D3: Génération de profils synthétiques via Claude | E3: ANTHROPIC_API_KEY configuré, offre ouverte | F3: 1. POST /api/recruitment/jobs/{id}/source 2. Body: { model:'claude', countries:['CI'], platforms:['LinkedIn','Africawork'], max_profiles:5 } | G3: 200 OK, data.profiles[] de 5 profils + strategy. meta.provider='claude', estimatedCostEur calculé. Audit log inséré | H3: 200 OK, 5 profils + strategy, estimatedCostEur calcule (~0,013E), audit log insere. NB prod: cle Anthropic absente -> repli Mistral (meta.provider='mistral', model mistral-small-latest). | I3: ✅ Passé | J3: Agents IA + live | K3: 24/06/2026 | O3: Sprint 1 | P3: Production
A4: SRC-002 | B4: P1 — Critique | C4: Endpoint POST /jobs/:id/source/compare — Claude vs Mistral | D4: Appels parallèles + métriques | E4: Les 2 clés IA configurées | F4: 1. POST /api/recruitment/jobs/{id}/source/compare 2. Body: { countries:['CI','SN'], max_profiles:3 } | G4: 200 OK, comparison.winner = claude|mistral. ratios.latency/cost/richness retournés. recommendation textuelle | H4: 422 explicite 'ANTHROPIC_API_KEY non configuree - comparaison impossible'. La comparaison exige les 2 cles IA ; Anthropic non configuree en prod. Code corrige (500 -> 422 propre). | I4: ⚠️ Bloqué | J4: Agents IA + live | K4: 24/06/2026 | O4: Sprint 1 | P4: Production
A5: SRC-003 | B5: P1 — Critique | C5: Rate-limit sourcing — 6 requêtes/min | D5: Protection coût IA (OWASP A05) | F5: 1. Boucler 7 fois POST /jobs/:id/source en moins d'1 minute | G5: Les 6 premières passent, la 7e retourne 429 Too Many Requests | H5: Rate-limit actif : 429 Too Many Requests declenche apres le quota/min (observe: 404x3 puis 429x5 sur tirs rapides). | I5: ✅ Passé | J5: Agents IA + live | K5: 24/06/2026 | O5: Sprint 1 | P5: Production
A6: SRC-004 | B6: P1 — Critique | C6: Endpoint GET /jobs/:id/sourced-profiles | D6: Liste cache des profils générés pour une offre | E6: Profils en cache (seed ou générés) | F6: 1. GET /api/recruitment/jobs/{id}/sourced-profiles | G6: 200 OK, tableau ordonné par match_score DESC. Profils transférés et non-transférés inclus, distinguables par transferred_to_application_id | H6: 200 OK, profils ordonnes par match_score DESC, champ transferred_to_application_id present (transferes + non transferes distinguables). | I6: ✅ Passé | J6: Agents IA + live | K6: 24/06/2026 | O6: Sprint 1 | P6: Production
A7: SRC-005 | B7: P1 — Critique | C7: Endpoint transfer-all transactionnel | D7: Tous les profils non transférés transférés en une transaction | E7: ≥1 profil non transféré | F7: 1. POST /api/recruitment/jobs/{id}/sourced-profiles/transfer-all 2. Vérifier en DB | G7: Réponse data.transferred = N. Chaque profil a transferred_to_application_id. N candidatures créées (source=sourced_ai) | H7: 200 OK, data.transferred=3, chaque item porte applicationId ; candidatures creees (source=sourced_ai). Transfert transactionnel. | I7: ✅ Passé | J7: Agents IA + live | K7: 24/06/2026 | O7: Sprint 1 | P7: Production
A8: SRC-006 | B8: P2 — Haute | C8: Idempotence transfert unique (409) | D8: Tenter de transférer 2x le même profil | E8: Profil déjà transféré | F8: 1. POST /api/recruitment/jobs/{id}/sourced-profiles/{profileId}/transfer 2. Re-POST sur le même profileId | G8: 1er appel: 201 Created avec applicationId. 2e appel: 409 Conflict avec applicationId existant | H8: Re-transfert du meme profil deja transfere -> 409 Conflict avec applicationId existant ('Profil deja transfere'). | I8: ✅ Passé | J8: Agents IA + live | K8: 24/06/2026 | O8: Sprint 1 | P8: Production
A9: SRC-007 | B9: P2 — Haute | C9: RBAC sourcing — employee 403 | D9: Un employee ne peut pas lancer un sourcing | E9: Token employe@sotra.ci | F9: 1. POST /jobs/:id/source avec token employee | G9: 403 Forbidden | H9: Token employe@sotra.ci -> 403 Forbidden. | I9: ✅ Passé | J9: Agents IA + live | K9: 24/06/2026 | O9: Sprint 1 | P9: Production
A10: SRC-008 | B10: P1 — Critique | C10: Devise auto par pays cible | D10: Le prompt et les profils utilisent la bonne devise selon le pays | F10: 1. Lancer sourcing avec countries=['NG'] 2. Vérifier les estimatedSalary | G10: Profils retournés avec estimatedSalaryCurrency='NGN' (Nigeria). Pour countries=['CI'] → XOF. Pour CM/TD → XAF | H10: Devise auto par pays cible corrigee : CURRENCY_BY_COUNTRY prioritaire (NG->NGN, CM->XAF, CI->XOF), repli devise offre puis XOF. Unit tests + verif live multi-pays. NB tenant mono-pays force sur SON pays (OWASP A01). | I10: ✅ Passé | J10: Agents IA + live | K10: 24/06/2026 | O10: Sprint 1 | P10: Production
A11: SRC-009 | B11: P1 — Critique | C11: Score de richesse (computeSourcingRichness) | D11: Métrique 0-100 sur la qualité de la réponse IA | F11: 1. Générer un sourcing 2. Vérifier meta.richnessScore | G11: Score >0 si profils + strategy. ≥70 si réponse riche (5+ profils, bestPlatforms 2+, boolean search, salary benchmark) | H11: meta.richnessScore=100 (borne 0-100), coherent (5 profils + strategy riche: booleanSearch, bestPlatforms, salaryBenchmark). | I11: ✅ Passé | J11: Agents IA + live | K11: 24/06/2026 | O11: Sprint 1 | P11: Production
A12: SRC-010 | B12: P2 — Haute | C12: Sourcing — génération de profils synthétiques signalés | D12: Le module génère des profils synthétiques (aucune donnée personnelle réelle). | E12: Offre ouverte | F12: 1. Sourcing IA → Lancer 2. Ouvrir un profil | G12: Profils marqués comme suggestions synthétiques ; aucun email/téléphone réel inventé présenté comme vérifié | O12: Recette 10/2026 | P12: Production
A13: SRC-011 | B13: P3 — Moyenne | C13: Sourcing — module recrutement désactivé | D13: Enforcement module. | E13: Module recrutement désactivé | F13: 1. POST /recruitment/jobs/:id/source | G13: 403 moduleDisabled | O13: Recette 10/2026 | P13: Production

Sheet MPF
A1: MULTI-PAYS & FILIALES · 13 scénarios
A2: ID Test | B2: Priorité | C2: Titre du scénario | D2: Description / Contexte | E2: Prérequis / Données | F2: Étapes détaillées | G2: Résultat attendu | H2: Résultat obtenu | I2: Statut | J2: Testeur | K2: Date test | L2: Durée (min) | M2: Ticket / Requalification | N2: Commentaire / Amélioration | O2: Sprint | P2: Env.
A3: MPF-001 | B3: P1 — Critique | C3: Activation tous packs côté super_admin | D3: Onglet Multi-législatif affiche les 11 pays actifs | E3: Super admin connecté | F3: 1. /platform/settings 2. Onglet 'Multi-législatif' 3. Compter les cards 'Actif' | G3: 11 cartes vert/Actif : CI/SN/BJ/TG/BF/ML/NE (UEMOA), CM/TD (CEMAC), NG/GH (CEDEAO). Drapeaux + badges zone + compteurs | H3: Onglet Multi-legislatif : 15 packs actifs (UEMOA 8 + CEMAC 6 + Nigeria NGN), drapeaux/badges/compteurs. Couverture plus large que les 11 prevus. NB: Ghana (GHS) non couvert (pas de pack OHADA GHA). | I3: ✅ Passé | J3: Agents IA + live | K3: 24/06/2026 | O3: Sprint 1 | P3: Production
A4: MPF-002 | B4: P1 — Critique | C4: Toggle has_subsidiaries sur tenant | D4: Activer l'option filiales sur un tenant existant | E4: Super admin | F4: 1. /platform/tenants/{id} 2. Cocher 'A des filiales' 3. Sauver | G4: platform.tenants.has_subsidiaries = true. Le tenant peut désormais créer plusieurs legal_entities avec pays différents | H4: Toggle has_subsidiaries=true sur SOTRA (via superadmin) -> le tenant peut creer plusieurs legal_entities multi-pays. | I4: ✅ Passé | J4: Agents IA + live | K4: 24/06/2026 | O4: Sprint 1 | P4: Production
A5: MPF-003 | B5: P1 — Critique | C5: Création filiale multi-pays | D5: Admin tenant crée une filiale avec pays + pack législatif | E5: Admin SOTRA connecté | F5: 1. Paramètres → Entités juridiques 2. Nouvelle entité 'SOTRA Dakar' 3. Pays: Sénégal, pack auto sn_2024 4. CNPS, RCCM, AT 2% 5. Créer | G5: Filiale créée, country_code='SEN', legislation_pack_code='sn_2024'. Badge 'Filiale' visible si plusieurs entités | H5: POST /settings/legal-entities 201 : filiale 'SOTRA Dakar', country_code='SEN', legislation_pack_code='sn_2024'. | I5: ✅ Passé | J5: Agents IA + live | K5: 24/06/2026 | O5: Sprint 1 | P5: Production
A6: MPF-004 | B6: P2 — Haute | C6: Édition filiale existante | D6: Modifier les infos d'une filiale (bouton ⚙) | E6: ≥1 filiale créée | F6: 1. Card filiale → bouton ⚙ 2. Changer le pack législatif et l'AT 3. Enregistrer | G6: PATCH /settings/legal-entities/{id} 200 OK. Mise à jour visible dans la card | H6: PATCH /settings/legal-entities/:id 200 : at_rate 0,02 -> 0,03 et pack mis a jour, visible dans la card. | I6: ✅ Passé | J6: Agents IA + live | K6: 24/06/2026 | O6: Sprint 1 | P6: Production
A7: MPF-005 | B7: P1 — Critique | C7: Rattachement employé → filiale | D7: Champ legal_entity_id dans la fiche employé | E7: ≥2 filiales, 1 employé | F7: 1. /employees/{id} 2. Champ 'Filiale' → sélectionner 'SOTRA Bouaké' 3. Sauver | G7: employees.legal_entity_id mis à jour. Compteur employés sur la card filiale incrémenté | H7: PATCH /employees/:id {legalEntityId} 200 : employees.legal_entity_id persiste (confirme par GET, match exact). NB champ API en camelCase legalEntityId. | I7: ✅ Passé | J7: Agents IA + live | K7: 24/06/2026 | O7: Sprint 1 | P7: Production
A8: MPF-006 | B8: P1 — Critique | C8: Suppression filiale avec employés actifs → 409 | D8: Garde-fou : impossible de supprimer une filiale avec employés | E8: Filiale avec ≥1 employé actif | F8: 1. Tenter DELETE /settings/legal-entities/{id} | G8: 409 Conflict avec message 'Cette entite a des employes actifs' | H8: DELETE filiale avec employe actif -> 409 'Cette entite a des employes actifs'. Garde-fou OK. | I8: ✅ Passé | J8: Agents IA + live | K8: 24/06/2026 | O8: Sprint 1 | P8: Production
A9: MPF-007 | B9: P2 — Haute | C9: Bloc d'aide explique le rattachement | D9: Pédagogie sur le mécanisme | E9: Onglet Entités juridiques | F9: 1. /settings → Entités juridiques 2. Lire le bloc bleu en haut | G9: Texte explicite : les employés sont rattachés via legal_entity_id, le moteur de paie applique le pack législatif de la filiale | H9: Bloc d'aide present (SettingsPage.tsx) : explique le rattachement via legal_entity_id et l'application du pack legislatif par le moteur de paie. | I9: ✅ Passé | J9: Agents IA + live | K9: 24/06/2026 | O9: Sprint 1 | P9: Production
A10: MPF-008 | B10: P2 — Haute | C10: Devise locale par filiale | D10: L'UI affiche la devise du pack (XOF / XAF / NGN / GHS) | E10: Filiale créée hors zone XOF | F10: 1. Créer filiale Cameroun → vérifier card affiche XAF 2. Filiale Nigeria → NGN | G10: La carte filiale affiche '(XAF)' ou '(NGN)' à côté du pack législatif | H10: Card filiale affiche la devise du pack ((XOF)/(XAF)/(NGN)) a cote du code pack legislatif (SettingsPage.tsx). | I10: ✅ Passé | J10: Agents IA + live | K10: 24/06/2026 | O10: Sprint 1 | P10: Production
A11: MPF-009 | B11: P2 — Haute | C11: Compteur employés par filiale | D11: Card filiale affiche le nombre d'employés rattachés | F11: 1. Rattacher 5 employés à une filiale 2. Recharger Settings | G11: Icône Users + 5 sur la card | H11: GET /settings/legal-entities : employees_count=1 apres rattachement (icone Users + compteur). | I11: ✅ Passé | J11: Agents IA + live | K11: 24/06/2026 | O11: Sprint 1 | P11: Production
A12: MPF-010 | B12: P3 — Moyenne | C12: Pré-remplissage pack législatif depuis pays | D12: Quand on change le pays dans le formulaire, le pack se met à jour automatiquement | F12: 1. Modal Nouvelle filiale 2. Changer pays de CIV vers SEN | G12: Champ Pack législatif passe de 'ci_2024' à 'sn_2024' automatiquement | H12: Modal Nouvelle filiale : changement de pays met a jour legislation_pack_code automatiquement (onChange -> COUNTRY_OPTIONS.pack). | I12: ✅ Passé | J12: Agents IA + live | K12: 24/06/2026 | O12: Sprint 1 | P12: Production
A13: MPF-011 | B13: P3 — Moyenne | C13: Wizard tenant — sélecteur pays par défaut | D13: Création de tenant propose les pays disponibles | E13: Super admin | F13: 1. /platform/tenants/new 2. Étape 1 → champ Pays 3. Vérifier les options | G13: Liste affiche au moins CIV/SEN/BFA/MLI/TGO/BEN/NER/GNB | H13: Wizard tenant (PlatformTenantNew.tsx) etape 1 : selecteur pays par defaut (CIV/SEN/BFA/MLI/TGO/BEN/NER/GNB). | I13: ✅ Passé | J13: Agents IA + live | K13: 24/06/2026 | O13: Sprint 1 | P13: Production
A14: MPF-012 | B14: P2 — Haute | C14: Règles par pays — préavis/SMIG/devise du pack de l'employé | D14: Le pays de la filiale pilote préavis, SMIG et devise. | E14: Filiale Sénégal avec un salarié | F14: 1. Fiche salarié SN → simulation de paie 2. Dossier de sortie → préavis | G14: SMIG, devise (XOF), préavis du pack SN appliqués ; jamais les règles CI par défaut | O14: Recette 10/2026 | P14: Production
A15: MPF-013 | B15: P2 — Haute | C15: Onglet Paie masqué si filiales + redirection | D15: Avec filiales, la paie passe par Paie multi-filiales. | E15: SOTRA has_subsidiaries=true | F15: 1. Sidebar 2. Ouvrir /payroll directement | G15: Entrée « Paie » masquée au profit de « Paie multi-filiales » ; /payroll redirige ; message « décliner » personnalisé | O15: Recette 10/2026 | P15: Production

Sheet FRM
A1: FORMATION & FDFP · 14 scénarios
A2: ID Test | B2: Priorité | C2: Titre du scénario | D2: Description / Contexte | E2: Prérequis / Données | F2: Étapes détaillées | G2: Résultat attendu | H2: Résultat obtenu | I2: Statut | J2: Testeur | K2: Date test | L2: Durée (min) | M2: Ticket / Requalification | N2: Commentaire / Amélioration | O2: Sprint | P2: Env.
A3: FRM-001 | B3: P1 — Critique | C3: Catalogue formations — affichage | E3: 5+ formations seedées | F3: 1. /training 2. Observer les cards | G3: Cards avec titre, durée (heures), format (présentiel/e-learning), places disponibles | H3: GET /training/catalog 200, 12 formations (titre, duree, format). NB: les places dispo sont au niveau SESSION (/training/sessions = max_places - enrolled_count), pas sur la card catalogue. | I3: ✅ Passé | J3: Agents IA + live | K3: 24/06/2026 | O3: Sprint 1 | P3: Production
A4: FRM-002 | B4: P2 — Haute | C4: Création formation (admin) | E4: Admin connecté | F4: 1. /training/new 2. Remplir titre, description, durée, format, places max 3. Cocher FDFP éligible si applicable | G4: Formation créée, visible dans le catalogue | H4: POST /training/catalog 201 : formation creee (titre, duree, format, places max, is_fdfp_eligible) ; visible au catalogue. | I4: ✅ Passé | J4: Agents IA + live | K4: 24/06/2026 | O4: Sprint 1 | P4: Production
A5: FRM-003 | B5: P1 — Critique | C5: Session planifiée — dates futures | E5: Formation créée | F5: 1. Créer une session avec dates futures 2. Définir lieu et formateur | G5: Session visible avec places disponibles décomptées dynamiquement | H5: POST /training/sessions 201 (dates futures + lieu + formateur) ; enrolled_count decompte dynamiquement (COUNT live). | I5: ✅ Passé | J5: Agents IA + live | K5: 24/06/2026 | O5: Sprint 1 | P5: Production
A6: FRM-004 | B6: P1 — Critique | C6: Inscription self-service — employee | E6: employe@sotra.ci connecté, places disponibles | F6: 1. /mon-espace/formation 2. Catalogue → S'inscrire | G6: Inscription créée, places disponibles -1, confirmation affichée | H6: Auto-inscription employee POST /training/enroll {session_id} 201 ; employee_id derive du token (OWASP A01). | I6: ✅ Passé | J6: Agents IA + live | K6: 24/06/2026 | O6: Sprint 1 | P6: Production
A7: FRM-005 | B7: P2 — Haute | C7: Vérification places avant inscription | E7: Session complète (0 place) | F7: 1. Tenter de s'inscrire à une session pleine | G7: Erreur 'Session complète', bouton désactivé | H7: Session pleine -> 400 'Session complete' (bouton masque cote UI). NB: 400 (et non 409, reserve au doublon d'inscription). | I7: ✅ Passé | J7: Agents IA + live | K7: 24/06/2026 | O7: Sprint 1 | P7: Production
A8: FRM-006 | B8: P2 — Haute | C8: Désinscription | E8: Inscrit à une session future | F8: 1. Mes inscriptions → Annuler | G8: Inscription supprimée, places disponibles +1 | H8: Desinscription DELETE /training/enroll/:id 200 (ajout recette) ; garde A01 (employee = sa propre inscription) + 409 si terminee ; bouton Annuler (MaFormation). | I8: ✅ Passé | J8: Agents IA + live | K8: 24/06/2026 | O8: Sprint 1 | P8: Production
A9: FRM-007 | B9: P3 — Moyenne | C9: Attestation téléchargeable (formation terminée) | E9: Formation passée, statut completed | F9: 1. Mes inscriptions → Télécharger attestation | G9: PDF attestation téléchargé avec nom, date, formation, durée | H9: Attestation GET /training/enrollments/:id/attestation 200 application/pdf (genere pdf-lib, ajout recette) ; 409 si formation non terminee ; bouton Telecharger attestation. | I9: ✅ Passé | J9: Agents IA + live | K9: 24/06/2026 | O9: Sprint 1 | P9: Production
A10: FRM-008 | B10: P3 — Moyenne | C10: Filtre formations agréées FDFP | F10: 1. Catalogue → Filtre 'FDFP éligible' | G10: Seules les formations avec is_fdfp_eligible=true affichées | H10: Filtre ?is_fdfp_eligible=true -> uniquement formations FDFP (8/8 conformes). | I10: ✅ Passé | J10: Agents IA + live | K10: 24/06/2026 | O10: Sprint 1 | P10: Production
A11: FRM-009 | B11: P3 — Moyenne | C11: Demande remboursement FDFP | E11: Formation agréée terminée | F11: 1. POST /training/fdfp/request 2. Dossier complet | G11: Demande créée, statut 'pending FDFP' | H11: POST /training/fdfp/request 201 : remboursement estime 50% (500 000 / 1 000 000 FCFA), statut pending_validation. | I11: ✅ Passé | J11: Agents IA + live | K11: 24/06/2026 | O11: Sprint 1 | P11: Production
A12: FRM-101 | B12: P1 — Critique | C12: Demande de remboursement FDFP | D12: Soumission OK (plus de 400/500) | E12: Admin/RH connecté | F12: 1. /training → Demande FDFP 2. Titre, organisme, date, effectif, coût (sans lier de formation) 3. Soumettre | G12: Demande créée, remboursement estimé 50 %, aucune erreur | H12: Demande FDFP SANS formation liee (training_id vide) 201, estime 50%, aucune erreur. | I12: ✅ Passé | J12: Agents IA + live | K12: 24/06/2026 | O12: Corrections 23/06 | P12: Production
A13: FRM-102 | B13: P2 — Haute | C13: Format formation « e-learning » | D13: Choix du select accepté à la création | E13: Admin connecté | F13: 1. /training/new 2. Format = E-learning 3. Enregistrer | G13: Formation créée, plus de 400 | H13: Formation format e-learning POST /training/catalog 201. | I13: ✅ Passé | J13: Agents IA + live | K13: 24/06/2026 | O13: Corrections 23/06 | P13: Production
A14: FRM-103 | B14: P2 — Haute | C14: Ajout de participants à une session par la RH | D14: POST /training/sessions/:id/participants. | E14: chef.perso@sotra.ci (hr_officer, « Chef Personnel ») | F14: 1. Formations → Session → Ajouter participants (3 salariés) | G14: Participants inscrits, places restantes mises à jour ; dépassement refusé | O14: Recette 10/2026 | P14: Production
A15: FRM-104 | B15: P2 — Haute | C15: Ma formation — espace employé | D15: Mon espace → Formation (my-enrollments). | E15: employe@sotra.ci (Kouassi Coulibaly) | F15: 1. Mon espace → Formation | G15: Ses inscriptions uniquement, statut et attestation si terminée | O15: Recette 10/2026 | P15: Production
A16: FRM-105 | B16: P3 — Moyenne | C16: Salariés éligibles FDFP | D16: GET /training/fdfp/eligible. | E16: rh@sotra.ci (hr_manager, « Responsable Paie ») | F16: 1. Formations → FDFP → Éligibles | G16: Liste cohérente avec les règles d'éligibilité, montants en FCFA entiers | O16: Recette 10/2026 | P16: Production

Sheet FRA
A1: NOTES DE FRAIS · 11 scénarios
A2: ID Test | B2: Priorité | C2: Titre du scénario | D2: Description / Contexte | E2: Prérequis / Données | F2: Étapes détaillées | G2: Résultat attendu | H2: Résultat obtenu | I2: Statut | J2: Testeur | K2: Date test | L2: Durée (min) | M2: Ticket / Requalification | N2: Commentaire / Amélioration | O2: Sprint | P2: Env.
A3: FRA-001 | B3: P1 — Critique | C3: Création note de frais — brouillon | E3: Employé connecté | F3: 1. /mon-espace/notes-de-frais → Nouvelle note 2. Titre, mois 3. Sauvegarder brouillon | G3: Note créée statut 'draft', visible dans la liste | H3: POST /expenses 201 : statut 'draft', visible dans /expenses/my-expenses. | I3: ✅ Passé | J3: Agents IA + live | K3: 24/06/2026 | O3: Sprint 1 | P3: Production
A4: FRA-002 | B4: P1 — Critique | C4: Ajout lignes à la note | D4: Description, catégorie, montant FCFA, justificatif | E4: Note brouillon | F4: 1. Ouvrir la note 2. + Ajouter ligne 3. Repas 8 500 FCFA 4. Upload reçu | G4: Ligne ajoutée, total mis à jour automatiquement en FCFA | H4: POST /expenses/:id/lines (repas 8 500 FCFA) 201 : total_amount recalcule = 8 500 FCFA ; upload recu via /expenses/receipts/upload (data URL). | I4: ✅ Passé | J4: Agents IA + live | K4: 24/06/2026 | O4: Sprint 1 | P4: Production
A5: FRA-003 | B5: P1 — Critique | C5: Soumission note → statut 'submitted' | E5: Note avec au moins 1 ligne | F5: 1. Note brouillon → Soumettre | G5: Statut = submitted, manager notifié, modification impossible | H5: PATCH /expenses/:id/submit -> 'submitted' ; note en lecture seule apres soumission ; notification manager ajoutee (recette). | I5: ✅ Passé | J5: Agents IA + live | K5: 24/06/2026 | O5: Sprint 1 | P5: Production
A6: FRA-004 | B6: P1 — Critique | C6: Validation manager → statut 'approved' | E6: Note submitted + manager connecté | F6: 1. Manager → Notes à valider → Approuver | G6: Statut = approved, RH peut procéder au remboursement | H6: PATCH /expenses/:id/approve (hr_manager) -> 'approved' ; RH peut rembourser ; notification employe ajoutee (recette). | I6: ✅ Passé | J6: Agents IA + live | K6: 24/06/2026 | O6: Sprint 1 | P6: Production
A7: FRA-005 | B7: P2 — Haute | C7: Refus manager → statut 'rejected' | F7: 1. Manager → Refuser avec motif | G7: Statut = rejected, employé notifié avec motif | H7: PATCH /expenses/:id/reject {reason} -> 'rejected', motif stocke et affiche ; notification employe avec motif ajoutee (recette). | I7: ✅ Passé | J7: Agents IA + live | K7: 24/06/2026 | O7: Sprint 1 | P7: Production
A8: FRA-006 | B8: P2 — Haute | C8: Remboursement via Mobile Money | E8: Note approuvée, numéro Mobile Money enregistré | F8: 1. RH → Rembourser → Wave 2. Confirmer montant | G8: Paiement Mobile Money initié, statut = remboursé, référence TXN stockée | H8: PATCH /expenses/:id/pay {provider:wave} : virement Mobile Money initie (initiateTransfer) + reference TXN stockee (payment_reference) + ligne mobile_money_payments ; statut 'paid' (recette). Modal operateur cote UI. | I8: ✅ Passé | J8: Agents IA + live | K8: 24/06/2026 | O8: Sprint 1 | P8: Production
A9: FRA-007 | B9: P2 — Haute | C9: Sauvegarde brouillon autosave | F9: 1. Modifier une note 2. Ne pas cliquer Sauvegarder 3. Quitter et revenir | G9: Modifications conservées (autosave ou confirmation de quitter) | H9: Auto-sauvegarde locale du brouillon (localStorage) + restauration a la reouverture + banniere (recette, MesNotesDesFrais). | I9: ✅ Passé | J9: Agents IA + live | K9: 24/06/2026 | O9: Sprint 1 | P9: Production
A10: FRA-008 | B10: P1 — Critique | C10: Employee voit uniquement ses propres notes | F10: 1. employe@sotra.ci → /mon-espace/notes-de-frais | G10: Seules ses propres notes affichées, jamais celles des collègues | H10: Isolation : /expenses/my-expenses filtre sur employeeId du token ; acces a la note d'un collegue -> 403 (OWASP A01). | I10: ✅ Passé | J10: Agents IA + live | K10: 24/06/2026 | O10: Sprint 1 | P10: Production
A11: FRA-101 | B11: P2 — Haute | C11: Catégorie de frais « Matériel » / « Communication » | D11: Valeurs du select acceptées | E11: Employé connecté | F11: 1. Nouvelle note → ligne 2. Catégorie = Matériel (ou Communication) 3. Enregistrer | G11: Ligne enregistrée, plus de 400 | H11: Categorie de ligne 'materiel' / 'communication' acceptee (enum Zod) 201. | I11: ✅ Passé | J11: Agents IA + live | K11: 24/06/2026 | O11: Corrections 23/06 | P11: Production
A12: FRA-102 | B12: P1 — Critique | C12: Justificatif — upload et contrôle du fichier | D12: POST /expenses/receipts/upload (type, taille, antivirus). | E12: employe@sotra.ci (Kouassi Coulibaly) | F12: 1. Note de frais → ligne → joindre un JPG 2. Joindre un fichier de 20 Mo / un .exe | G12: JPG accepté et consultable ; fichier trop gros ou type interdit refusé avec message clair | O12: Recette 10/2026 | P12: Production
A13: FRA-103 | B13: P2 — Haute | C13: Notes de frais — vue RH (expenses-rh) | D13: Page RH de suivi des notes de frais. | E13: rh@sotra.ci (hr_manager, « Responsable Paie ») | F13: 1. Notes de frais (RH) → filtrer par statut | G13: Toutes les notes du tenant visibles RH, lecture seule tant qu'elles ne sont pas à son niveau (voir WF) | O13: Recette 10/2026 | P13: Production

Sheet CAR
A1: CARRIÈRES & COMPÉTENCES · 9 scénarios
A2: ID Test | B2: Priorité | C2: Titre du scénario | D2: Description / Contexte | E2: Prérequis / Données | F2: Étapes détaillées | G2: Résultat attendu | H2: Résultat obtenu | I2: Statut | J2: Testeur | K2: Date test | L2: Durée (min) | M2: Ticket / Requalification | N2: Commentaire / Amélioration | O2: Sprint | P2: Env.
A3: CAR-001 | B3: P1 — Critique | C3: Référentiel compétences — création | E3: Admin/RH connecté | F3: 1. /careers/skills → Nouvelle compétence 2. Nom, catégorie (technique/comportemental/managérial) | G3: Compétence créée dans le référentiel | H3: POST /careers/skills 201 : competence creee au referentiel (nom + categorie technique/comportemental/manageriale). | I3: ✅ Passé | J3: Agents IA + live | K3: 24/06/2026 | O3: Sprint 1 | P3: Production
A4: CAR-002 | B4: P2 — Haute | C4: Attribution compétences à un employé | F4: 1. Fiche employé → Compétences 2. Sélectionner compétence + niveau (1-5) 3. Sauvegarder | G4: Compétence liée à l'employé avec niveau | H4: PUT /careers/employee-skills 200 : competence rattachee a l'employe avec niveau (1-5) + niveau cible (upsert). | I4: ✅ Passé | J4: Agents IA + live | K4: 24/06/2026 | O4: Sprint 1 | P4: Production
A5: CAR-003 | B5: P1 — Critique | C5: Entretien annuel — création et saisie | F5: 1. /careers/evaluations → Nouvel entretien 2. Sélectionner employé, année 3. Saisir scores performance et compétences | G5: Entretien créé statut 'completed' avec scores et commentaires | H5: POST /careers/evaluations 201 puis PATCH status=completed 200. CORRECTIF : echelle 0-5 (1 decimale) — un score 4,5 est desormais accepte (avant int 0-100 => 400). Coherent DB numeric(3,1)/UI /5. | I5: ✅ Passé | J5: Agents IA + live | K5: 24/06/2026 | O5: Sprint 1 | P5: Production
A6: CAR-004 | B6: P2 — Haute | C6: Historique entretiens par employé | F6: 1. Fiche employé → Entretiens | G6: Liste des entretiens triée par année, scores visibles | H6: GET /careers/evaluations?employee_id= 200 : historique trie par annee DESC (2 entretiens). | I6: ✅ Passé | J6: Agents IA + live | K6: 24/06/2026 | O6: Sprint 1 | P6: Production
A7: CAR-005 | B7: P3 — Moyenne | C7: Vue 9-Box | D7: Performance vs Potentiel | E7: Évaluations avec scores | F7: 1. /careers/9box | G7: Grille 9-box affichée avec positionnement des employés selon scores | H7: GET /careers/nine-box?year=2026 200 : grille 9-box (perf x potentiel) des entretiens annuels completes. | I7: ✅ Passé | J7: Agents IA + live | K7: 24/06/2026 | O7: Sprint 1 | P7: Production
A8: CAR-006 | B8: P3 — Moyenne | C8: Score rétention IA | D8: Calcul du risque de départ | E8: ANTHROPIC_API_KEY configuré | F8: 1. /careers/retention → Analyser | G8: Score + niveau de risque (low/medium/high) + facteurs + recommandations en français | H8: GET /careers/retention/:id 200 (AJOUT recette) : {score, risk low/medium/high, factors[], recommendations[]} en francais. Heuristique CI (anciennete, SMIG, absences maladie, formation, eval). | I8: ✅ Passé | J8: Agents IA + live | K8: 24/06/2026 | O8: Sprint 1 | P8: Production
A9: CAR-101 | B9: P2 — Haute | C9: Entretien — type Fin d'essai / Sortie + année | D9: Types proposés par l'UI acceptés ; année en chaîne coercée | E9: Admin/RH connecté | F9: 1. /careers/evaluations → Nouvel entretien 2. Type = Fin d'essai, année courante 3. Enregistrer | G9: Entretien créé, plus de 400 | H9: POST /careers/evaluations type='trial_end' (Fin d'essai) / 'exit' (Sortie) + annee 201. | I9: ✅ Passé | J9: Agents IA + live | K9: 24/06/2026 | O9: Corrections 23/06 | P9: Production
A10: CAR-102 | B10: P2 — Haute | C10: Ma carrière — espace employé | D10: my-evaluations / my-skills. | E10: employe@sotra.ci (Kouassi Coulibaly) | F10: 1. Mon espace → Carrière | G10: Ses entretiens et compétences uniquement ; GET /careers/evaluations → 403 | O10: Recette 10/2026 | P10: Production
A11: CAR-103 | B11: P2 — Haute | C11: Entretien — périmètre manager | D11: Le manager ne voit/saisit que les entretiens de son périmètre (manager_scope). | E11: manager@sotra.ci (manager, « Chef Dépôt ») | F11: 1. Carrières → Entretiens 2. Tenter un entretien sur un salarié hors équipe | G11: Équipe uniquement ; hors périmètre → 403 | O11: Recette 10/2026 | P11: Production

Sheet CNP
A1: DÉCLARATIONS CNPS & DISA · 15 scénarios
A2: ID Test | B2: Priorité | C2: Titre du scénario | D2: Description / Contexte | E2: Prérequis / Données | F2: Étapes détaillées | G2: Résultat attendu | H2: Résultat obtenu | I2: Statut | J2: Testeur | K2: Date test | L2: Durée (min) | M2: Ticket / Requalification | N2: Commentaire / Amélioration | O2: Sprint | P2: Env.
A3: CNP-001 | B3: P1 — Critique | C3: Génération déclaration mensuelle CNPS | E3: Bulletins clôturés du mois | F3: 1. /cnps/declarations → Générer pour Mai 2025 | G3: Déclaration créée avec total cotisations salariales et patronales en FCFA | H3: CORRIGE : ajout du mode declaration MENSUELLE (e-CNPS legal = depot avant le 15 du mois M+1), en plus du trimestriel. POST /cnps/declarations/generate accepte {year,month} ou {year,quarter} ; table period_type/period_month + unique NULLS NOT DISTINCT ; UI toggle Mensuelle/Trimestrielle + selecteur de mois. Agrege les bulletins, FCFA entiers, persiste. | I3: ✅ Passé | J3: Agents IA + correctif | K3: 24/06/2026 | O3: Sprint 1 | P3: Production
A4: CNP-002 | B4: P1 — Critique | C4: Export e-CNPS CSV format officiel | E4: Déclaration générée | F4: 1. Déclaration → Exporter CSV | G4: CSV téléchargé compatible plateforme e-CNPS CI, format correct | H4: CORRIGE : GET /cnps/declarations/:id/export (CSV) avait BOM/;/CRLF/colonnes corrects MAIS PAS d'anti-injection CSV (un nom =cmd() devenait formule Excel - OWASP A03). Ajout csvCell (encodeField SAGE : neutralise =/+/-/@ + quoting) sur les exports declaration + DISA + RNS. Format e-CNPS a confirmer contre un fichier modele officiel. | I4: ✅ Passé | J4: Agents IA + correctif | K4: 24/06/2026 | O4: Sprint 1 | P4: Production
A5: CNP-003 | B5: P2 — Haute | C5: Alerte date limite déclaration (avant le 15) | E5: En date du 10 du mois | F5: 1. Observer le dashboard admin | G5: Alerte 'Déclaration CNPS à soumettre avant le 15' visible | H5: Code : l'alerte 'Declaration CNPS mensuelle - depot e-CNPS avant le 15 du mois suivant' est VISIBLE sur le dashboard admin/hr (AlertCard, i18n). RESERVE : statique (toujours affichee) ; le backend calcule deja DEADLINE_SOON/PASSED (cnps.routes) mais le dashboard ne l'exploite pas (enhancement = alerte conditionnelle). | I5: ✅ Passé | J5: Agents IA (code) | K5: 24/06/2026 | O5: Sprint 1 | P5: Production
A6: CNP-004 | B6: P1 — Critique | C6: Génération DISA annuelle | D6: Déclaration Individuelle Salaires Annuels | E6: 12 mois de bulletins | F6: 1. /cnps/disa → Générer DISA 2025 | G6: DISA créée pour chaque employé avec cumuls annuels salaire brut + cotisations + ITS | H6: CORRIGE : la generation DISA (backend POST /cnps/disa/generate : agrege 12 mois par employe, cumuls brut+cotisations+ITS, NNI/nom, 1 ligne/an en disa_records) etait OK mais SANS bouton UI -> ajout d'une section 'DISA annuelle' (selecteur annee + bouton Generer) sur la page CNPS. RESERVE : ON CONFLICT(year) peut ecraser entre filiales (a affiner multi-filiales). | I6: ✅ Passé | J6: Agents IA + correctif | K6: 24/06/2026 | O6: Sprint 1 | P6: Production
A7: CNP-005 | B7: P2 — Haute | C7: Export DISA (CSV/XML) | E7: DISA générée | F7: 1. DISA → Exporter | G7: Fichier DISA téléchargé au format requis par CNPS/DGI | H7: CORRIGE : l'export DISA (GET /cnps/disa/:year/export CSV : entete employeur + colonnes NNI/nom/brut annuel/cotis/ITS + total general, BOM, anti-injection) etait OK mais SANS bouton UI -> ajout du bouton 'Exporter (CSV)' DISA. RESERVE : format XML/NEVA pour la DISA non livre (CSV seulement) — enhancement P2. | I7: ✅ Passé | J7: Agents IA + correctif | K7: 24/06/2026 | O7: Sprint 1 | P7: Production
A8: CNP-006 | B8: P1 — Critique | C8: RNS PDF généré — formulaire EN-GDAV-06 v03 | D8: Relevé Nominatif des Salaires | E8: rns-template.pdf copié dans dist/assets (fix Dockerfile) | F8: 1. /cnps/rns → GET /cnps/rns/2026/pdf | G8: PDF téléchargé avec données employeur, liste employés, salaires annuels en FCFA | H8: Code : GET /cnps/rns/:year/pdf genere le Releve Nominatif des Salaires (gabarit officiel CNPS EN-GDAV-06 v03, overlay calibre rns-coords.json en session precedente) : donnees employeur, liste employes, salaires annuels FCFA. Bouton 'RNS PDF' cable. Conforme. | I8: ✅ Passé | J8: Agents IA (code) | K8: 24/06/2026 | O8: Sprint 1 | P8: Production
A9: CNP-007 | B9: P2 — Haute | C9: RNS filtré par employé | F9: 1. GET /cnps/rns/2026/pdf?employeeId=XXX | G9: PDF généré pour un seul employé | H9: Code : GET /cnps/rns/:year/pdf?employeeId=UUID — parametre employeeId valide (UUID strict), genere le RNS pour un seul salarie. Conforme (niveau API). | I9: ✅ Passé | J9: Agents IA (code) | K9: 24/06/2026 | O9: Sprint 1 | P9: Production
A10: CNP-008 | B10: P3 — Moyenne | C10: Attestation conformité CNPS | F10: 1. /cnps/employers/certificate | G10: Attestation PDF téléchargée | H10: PARTIEL : un endpoint /cnps/audit-conformite (audit social 360 CNPS/DGI/SMIG/plafonds) existe en JSON, mais PAS d'ATTESTATION PDF telechargeable a /cnps/employers/certificate ni de bouton UI. NB : l'attestation de regularite officielle est emise par la CNPS elle-meme. Attestation PDF interne = enhancement P3. | I10: ⚠️ Bloqué | J10: Agents IA (code) | K10: 24/06/2026 | O10: Sprint 1 | P10: Production
A11: CNP-101 | B11: P1 — Critique | C11: Export RNS PDF — alignement | D11: Valeurs alignées sur leurs libellés, sans décalage ni superposition | E11: Employés + données CNPS seedés | F11: 1. Générer/Télécharger le RNS 2. Ouvrir le PDF | G11: Chaque donnée dans sa case alignée au libellé ; noms longs auto-réduits ; aucun chevauchement | H11: Code/rendu : alignement du RNS PDF corrige en session precedente (recalibrage rns-coords.json : ancrage a droite des chiffres, police adaptee, noms longs auto-reduits, zero chevauchement) ; verifie par rendu image. Conforme. | I11: ✅ Passé | J11: Agents IA (code) | K11: 24/06/2026 | O11: Corrections 23/06 | P11: Production
A12: CNP-102 | B12: P1 — Critique | C12: Déclaration de cessation (sortie CNPS) | D12: POST /cnps/events/cessation — date de sortie déclarée. | E12: rh@sotra.ci (hr_manager, « Responsable Paie ») ; salarié sorti | F12: 1. CNPS → Événements → Cessation → salarié, date 31/10/2026 | G12: Événement enregistré, exit_date renseignée, salarié exclu des paies suivantes | O12: Recette 10/2026 | P12: Production
A13: CNP-103 | B13: P2 — Haute | C13: Contrôle de cohérence trimestriel | D13: GET /cnps/validate/:year/:quarter. | E13: rh@sotra.ci (hr_manager, « Responsable Paie ») | F13: 1. CNPS → Valider T3 2026 | G13: Anomalies listées (NNI/CNPS manquants, écarts bases) avec lien vers le salarié | O13: Recette 10/2026 | P13: Production
A14: CNP-104 | B14: P2 — Haute | C14: Export NEVA d'une déclaration | D14: GET /cnps/declarations/:id/neva. | E14: Déclaration générée | F14: 1. Déclaration → Export NEVA | G14: Fichier au format attendu, montants entiers | O14: Recette 10/2026 | P14: Production
A15: CNP-105 | B15: P2 — Haute | C15: Export RNS (tableur) et champs RNS | D15: GET /cnps/rns/:year/export et /rns/fields. | E15: rh@sotra.ci (hr_manager, « Responsable Paie ») | F15: 1. CNPS → RNS 2026 → Exporter | G15: Fichier cohérent avec le PDF RNS (mêmes totaux) | O15: Recette 10/2026 | P15: Production
A16: CNP-106 | B16: P2 — Haute | C16: Page Audit de conformité CNPS | D16: /cnps/audit (complète CNP-008). | E16: rh@sotra.ci (hr_manager, « Responsable Paie ») | F16: 1. CNPS & DISA → Audit de conformité | G16: Indicateurs de conformité affichés, aucun écran vide, export possible | O16: Recette 10/2026 | P16: Production
A17: CNP-107 | B17: P2 — Haute | C17: Synthèse CNPS | D17: GET /cnps/summary. | E17: rh@sotra.ci (hr_manager, « Responsable Paie ») | F17: 1. CNPS → Synthèse | G17: Totaux salarié/employeur par branche cohérents avec les bulletins clôturés | O17: Recette 10/2026 | P17: Production

Sheet MM
A1: PAIEMENTS MOBILE MONEY & VIREMENTS · 16 scénarios
A2: ID Test | B2: Priorité | C2: Titre du scénario | D2: Description / Contexte | E2: Prérequis / Données | F2: Étapes détaillées | G2: Résultat attendu | H2: Résultat obtenu | I2: Statut | J2: Testeur | K2: Date test | L2: Durée (min) | M2: Ticket / Requalification | N2: Commentaire / Amélioration | O2: Sprint | P2: Env.
A3: MM-001 | B3: P1 — Critique | C3: Création campagne virement salaires | E3: Bulletins générés + clôturés | F3: 1. /payroll/mobile-money/campaigns → Nouvelle campagne 2. Sélectionner période | G3: Campagne créée avec liste des 80 virements à effectuer | H3: CORRIGE : POST /mobile-money/campaigns agrege les bulletins du mois (1 virement/employe paye, montant net). BUG contrat API/front corrige (slips->paySlips/allPaid/employeesCount) : la page ne crashe plus et liste les virements. | I3: ✅ Passé | J3: Agents IA + correctif | K3: 24/06/2026 | O3: Sprint 1 | P3: Production
A4: MM-002 | B4: P2 — Haute | C4: Exécution campagne — Wave | E4: Campagne créée, API Wave configurée | F4: 1. Campagne → Exécuter 2. Confirmer | G4: Virements Wave initiés, statuts = pending | H4: CORRIGE : exécution Wave -> appel HTTP REEL (transferWave, payout) via identifiants tenant/plateforme ; statut pending (async, confirme par webhook) ou simulation si non configure. Avant : stub Math.random. | I4: ✅ Passé | J4: Agents IA + correctif | K4: 24/06/2026 | O4: Sprint 1 | P4: Production
A5: MM-003 | B5: P2 — Haute | C5: Exécution campagne — MTN MoMo | F5: 1. Filtrer employés MTN 2. Exécuter | G5: Virements MTN initiés | H5: CORRIGE : exécution MTN MoMo reelle (token + transfer disbursement) ; filtre provider corrige (employes stockant 'mtn' OU 'mtn_momo' matches via ANY). Avant : 'mtn' jamais matche + virement 'non configure'. | I5: ✅ Passé | J5: Agents IA + correctif | K5: 24/06/2026 | O5: Sprint 1 | P5: Production
A6: MM-004 | B6: P2 — Haute | C6: Exécution campagne — Orange Money | F6: 1. Filtrer employés Orange 2. Exécuter | G6: Virements Orange initiés | H6: CORRIGE : exécution Orange Money reelle (token + pay) ; filtre 'orange'/'orange_money' harmonise. NOUVEAU : agregateur CinetPay (une integration -> tous operateurs, prioritaire si active). | I6: ✅ Passé | J6: Agents IA + correctif | K6: 24/06/2026 | O6: Sprint 1 | P6: Production
A7: MM-005 | B7: P2 — Haute | C7: Vérification numéro avant virement | D7: POST /payroll/mobile-money/verify-number | F7: 1. Saisir un numéro +225 07 XX XX XX 2. Vérifier | G7: Numéro actif confirmé ou erreur explicite | H7: CORRIGE : POST /mobile-money/verify-number (etait ABSENT) : valide le format CI (+225 07/05 + 8 chiffres) -> 200 valide ou 422 erreur explicite. RBAC admin/hr_mgr. | I7: ✅ Passé | J7: Agents IA + correctif | K7: 24/06/2026 | O7: Sprint 1 | P7: Production
A8: MM-006 | B8: P2 — Haute | C8: Callback webhook → mise à jour statut | E8: Virement initié | F8: 1. Simuler callback success du provider 2. Vérifier statut | G8: Statut mis à jour de 'pending' à 'success' | H8: Code : POST /webhooks/:provider (HMAC SHA-256 timing-safe + anti-rejeu) met le statut pending->completed/failed et marque le bulletin paye si succes. Conforme. | I8: ✅ Passé | J8: Agents IA + correctif | K8: 24/06/2026 | O8: Sprint 1 | P8: Production
A9: MM-007 | B9: P2 — Haute | C9: Virement failed → alerte | F9: 1. Simuler callback failed | G9: Statut = failed, alerte admin, virement visible dans liste des échecs | H9: CORRIGE : sur callback failed, le bulletin repasse en 'failed' ET une ALERTE admin/hr est creee (table notifications) — etait absente (audit log seul). Idem a l'execution si echec(s). | I9: ✅ Passé | J9: Agents IA + correctif | K9: 24/06/2026 | O9: Sprint 1 | P9: Production
A10: MM-008 | B10: P1 — Critique | C10: Bulletin marqué 'payé' après virement success | F10: 1. Virement success 2. Ouvrir le bulletin correspondant | G10: payment_status = 'paid', référence TXN affichée sur le bulletin | H10: Code : a la reussite (execution directe ou webhook), pay_slips.payment_status='paid' + payment_reference=TXN + paid_at ; le bulletin PDF affiche le mode de paiement + ref TXN. Conforme (badge 'PAYE' litteral = amelioration mineure P3). | I10: ✅ Passé | J10: Agents IA + correctif | K10: 24/06/2026 | O10: Sprint 1 | P10: Production
A11: MM-009 | B11: P1 — Critique | C11: Validation format téléphone CI | F11: 1. Saisir +225 07 12 34 56 78 (Wave valide) 2. Saisir +33 6 XX (invalide) | G11: Format +225 07/05 + 8 chiffres accepté, autres rejetés avec erreur claire | H11: CORRIGE : validation format CI coherente. Avant : saisie employe (regex Afrique large) acceptait un numero rejete au virement. Enum provider employe elargi (mtn<->mtn_momo) + validation +225 07/05 dans MonProfil avec message clair. | I11: ✅ Passé | J11: Agents IA + correctif | K11: 24/06/2026 | O11: Sprint 1 | P11: Production
A12: MM-010 | B12: P1 — Critique | C12: Configuration Mobile Money du tenant (secrets chiffrés) | D12: Paramètres → Mobile Money : Wave/MTN/Orange/CinetPay. | E12: admin@sotra.ci | F12: 1. Paramètres → Mobile Money → saisir clés Wave 2. Enregistrer, recharger | G12: Clés masquées après enregistrement (jamais renvoyées en clair) ; simulation si non configuré | O12: Recette 10/2026 | P12: Production
A13: MM-011 | B13: P2 — Haute | C13: Agrégateur CinetPay | D13: Paiement via l'agrégateur. | E13: CinetPay configuré (sandbox) | F13: 1. Créer une campagne via CinetPay 2. Exécuter | G13: Transactions envoyées à CinetPay, statuts mis à jour par callback | O13: Recette 10/2026 | P13: Production
A14: MM-012 | B14: P2 — Haute | C14: Relance d'un paiement échoué | D14: PATCH /mobile-money/payments/:id/retry. | E14: Paiement en échec | F14: 1. Paiements Salaires → Paiements → Relancer | G14: Nouvelle tentative, statut mis à jour ; un paiement réussi ne peut pas être relancé | O14: Recette 10/2026 | P14: Production
A15: MM-013 | B15: P3 — Moyenne | C15: Statistiques des paiements | D15: GET /mobile-money/payments/stats. | E15: rh@sotra.ci (hr_manager, « Responsable Paie ») | F15: 1. Paiements Salaires → Statistiques | G15: Totaux par opérateur et statut cohérents avec la liste | O15: Recette 10/2026 | P15: Production
A16: MM-014 | B16: P1 — Critique | C16: Virement bancaire — aperçu, fichier, envoi | D16: Module bank-transfer : preview / file / send. | E16: Salariés en mode virement (RIB) ; période clôturée | F16: 1. Paiements Salaires → Virement → Aperçu 2. Générer le fichier 3. Envoyer | G16: Aperçu = salariés virement uniquement ; fichier Excel/format banque généré ; RIB manquant signalé | O16: Recette 10/2026 | P16: Production
A17: MM-015 | B17: P2 — Haute | C17: Formats de fichier bancaire — profil versionné | D17: Brouillon → actif → archivé ; import assisté d'un fichier exemple. | E17: admin@sotra.ci | F17: 1. Formats bancaires → Importer un fichier exemple 2. Ajuster le mapping, prévisualiser, fichier de test 3. Activer | G17: Profil actif utilisé pour les virements, l'ancien archivé ; le super_admin n'intervient jamais | O17: Recette 10/2026 | P17: Production
A18: MM-016 | B18: P2 — Haute | C18: Virement — RBAC configuration | D18: CONFIG admin seul, opération admin/hr_manager. | E18: chef.perso@sotra.ci (hr_officer, « Chef Personnel ») | F18: 1. Tenter d'activer un format bancaire et d'envoyer un virement | G18: 403 pour hr_officer ; hr_manager peut opérer mais pas configurer | O18: Recette 10/2026 | P18: Production

Sheet AI
A1: ASSISTANT IA (CLAUDE CI) · 19 scénarios
A2: ID Test | B2: Priorité | C2: Titre du scénario | D2: Description / Contexte | E2: Prérequis / Données | F2: Étapes détaillées | G2: Résultat attendu | H2: Résultat obtenu | I2: Statut | J2: Testeur | K2: Date test | L2: Durée (min) | M2: Ticket / Requalification | N2: Commentaire / Amélioration | O2: Sprint | P2: Env.
A3: AI-001 | B3: P1 — Critique | C3: Chat IA — réponse en streaming SSE | E3: ANTHROPIC_API_KEY configuré | F3: 1. /ai/chat 2. Poser une question RH 3. Observer la réponse | G3: Réponse arrivant en streaming (SSE), affichée progressivement | H3: POST /ai/chat 200 : reponse en streaming SSE (Content-Type text/event-stream, chunks data:{text}) puis {done}. | I3: ✅ Passé | J3: Agents IA + live | K3: 24/06/2026 | O3: Sprint 1 | P3: Production
A4: AI-002 | B4: P1 — Critique | C4: Réponse toujours en français | F4: 1. Poser la question en français 2. (Optionnel) tenter en anglais | G4: Réponse 100% en français, références légales CI citées | H4: Reponse 100% en francais (system prompt 'Tu reponds TOUJOURS en francais' + refs Code du Travail CI/CNPS/OHADA). Confirme live. | I4: ✅ Passé | J4: Agents IA + live | K4: 24/06/2026 | O4: Sprint 1 | P4: Production
A5: AI-003 | B5: P2 — Haute | C5: Question CNPS → calcul correct | F5: 1. 'Quel est le taux CNPS retraite salarié ?' | G5: Réponse: 6.3% avec mention du plafond 1 647 315 FCFA | H5: Question CNPS retraite -> reponse live : '...taux CNPS retraite salarie... 6,3%...' (fait ancre dans le prompt + plafond 1 647 315). | I5: ✅ Passé | J5: Agents IA + live | K5: 24/06/2026 | O5: Sprint 1 | P5: Production
A6: AI-004 | B6: P2 — Haute | C6: Question congés CI | F6: 1. 'Combien de jours de congés pour 8 mois ?' | G6: Réponse: 8 × 2.5 = 20 jours ouvrables (Code du Travail CI) | H6: Conges 8 mois -> 20 jours ouvrables (regle 2,5 j/mois ancree dans le prompt, exemple ajoute). | I6: ✅ Passé | J6: Agents IA + live | K6: 24/06/2026 | O6: Sprint 1 | P6: Production
A7: AI-005 | B7: P2 — Haute | C7: Question taux AT par secteur | F7: 1. 'Quel est le taux AT pour une entreprise BTP ?' | G7: Réponse: 3% (BTP/Transport) avec source réglementaire | H7: Taux AT BTP -> 3% : table AT par secteur AJOUTEE au prompt (Commerce 2% / BTP-Transport 3% / Industrie 4% / Mines 5%). | I7: ✅ Passé | J7: Agents IA + live | K7: 24/06/2026 | O7: Sprint 1 | P7: Production
A8: AI-006 | B8: P3 — Moyenne | C8: Génération CDI CI — OHADA | F8: 1. IA → Générer contrat → CDI CI 2. Saisir infos employé | G8: PDF CDI CI avec clauses OHADA obligatoires, NNI, CNPS, période d'essai légale CI | H8: POST /ai/generate-document type=cdi_ci 200 (AJOUT recette) : Markdown CDI avec clauses OHADA, NNI, CNPS, periode d'essai legale CI. | I8: ✅ Passé | J8: Agents IA + live | K8: 24/06/2026 | O8: Sprint 1 | P8: Production
A9: AI-007 | B9: P3 — Moyenne | C9: Génération certificat de travail | F9: 1. IA → Générer document → Certificat de travail | G9: Document complet avec données employé, poste, dates, mentions légales CI | H9: POST /ai/generate-document type=certificat_travail 200 : certificat complet (employe, poste, dates, mentions legales CI). | I9: ✅ Passé | J9: Agents IA + live | K9: 24/06/2026 | O9: Sprint 1 | P9: Production
A10: AI-008 | B10: P3 — Moyenne | C10: Analyse rétention — score et facteurs | F10: 1. /ai/retention → Analyser pour un employé | G10: { score, risk: low|medium|high, factors[], recommendations[] } en français | H10: GET /ai/retention/:id 200 (AJOUT recette) : {score, risk, factors[], recommendations[]} en francais (service partage avec CAR-006). | I10: ✅ Passé | J10: Agents IA + live | K10: 24/06/2026 | O10: Sprint 1 | P10: Production
A11: AI-009 | B11: P2 — Haute | C11: Employee — accès limité à l'IA | E11: employe@sotra.ci connecté | F11: 1. Accéder au chat IA 2. Poser des questions avancées | G11: Questions simples autorisées, génération de documents refusée (rôle limité) | H11: RBAC : employe@ -> POST /ai/generate-document 403 ET POST /ai/chat 403 (generation de documents refusee au salarie). | I11: ✅ Passé | J11: Agents IA + live | K11: 24/06/2026 | O11: Sprint 1 | P11: Production
A12: AI-010 | B12: P2 — Haute | C12: Contexte tenant injecté dans le prompt | F12: 1. Demander 'Quel est mon secteur d'activité ?' | G12: IA répond avec le secteur du tenant connecté (ex: 'Transport pour SOTRA') | H12: Contexte tenant injecte : le prompt inclut 'Entreprise: SOTRA (Abidjan, secteur Transport...)' (sanitization anti-injection). | I12: ✅ Passé | J12: Agents IA + live | K12: 24/06/2026 | O12: Sprint 1 | P12: Production
A13: AI-101 | B13: P1 — Critique | C13: Chat IA répond (fournisseur actif) | D13: L'assistant RH génère une réponse (plus d'« Erreur IA ») | E13: Clé IA configurée (Mistral en secret), admin/RH connecté | F13: 1. Ouvrir la bulle de chat IA 2. Poser « Comment calculer la prime d'ancienneté ? » 3. Envoyer | G13: Réponse en français générée, aucune erreur 503/500 | H13: GET /ai/status 200 available=true provider=mistral ; chat repond sans 500/503 (fournisseur actif). | I13: ✅ Passé | J13: Agents IA + live | K13: 24/06/2026 | O13: Corrections 23/06 | P13: Production
A14: AI-102 | B14: P2 — Haute | C14: Label « Propulsé par … » dynamique | D14: L'en-tête du chat affiche le fournisseur réel | E14: Chat disponible | F14: 1. Ouvrir le chat 2. Lire l'en-tête sous le titre | G14: « Propulsé par Mistral AI » (ou Claude selon config), pas « Claude » en dur | H14: Label dynamique : /ai/status renvoie provider ; UI mappe 'Propulse par Mistral AI' (pas Claude en dur). | I14: ✅ Passé | J14: Agents IA + live | K14: 24/06/2026 | O14: Corrections 23/06 | P14: Production
A15: AI-103 | B15: P1 — Critique | C15: Rendu markdown des réponses IA | D15: Titres, listes, tableaux, gras correctement rendus | E15: Chat disponible | F15: 1. Poser une question dont la réponse contient une liste/un tableau | G15: Mise en forme propre, plus de **, #, - bruts à l'écran | H15: Rendu markdown (react-markdown + remark-gfm) : listes/tableaux mis en forme, plus de **,#,- bruts (verifie code MarkdownMessage). | I15: ✅ Passé | J15: Agents IA + live | K15: 24/06/2026 | O15: Corrections 23/06 | P15: Production
A16: AI-104 | B16: P1 — Critique | C16: Conso tokens IA par tenant (super_admin) | D16: Vue /platform/ai-usage (clé plateforme uniquement) | E16: Super_admin connecté, ≥1 tenant ayant utilisé la clé plateforme | F16: 1. /platform → Consommation IA | G16: Tableau par tenant : tokens entrée/sortie, appels, coût estimé | H16: GET /platform/ai-usage 200 (super_admin) : tableau par tenant (tokens E/S, appels, cout estime) + totaux. | I16: ✅ Passé | J16: Agents IA + live | K16: 24/06/2026 | O16: Corrections 23/06 | P16: Production
A17: AI-105 | B17: P1 — Critique | C17: Toggle clé IA plateforme par tenant | D17: Autoriser/refuser la clé générale pour un tenant ; clé tenant prioritaire | E17: Super_admin, page détail tenant | F17: 1. /platform/tenants/{id} 2. Basculer « Autoriser la clé IA plateforme » 3. Désactiver puis tester le chat du tenant | G17: Si désactivé + pas de clé tenant → IA indisponible pour ce tenant | H17: Toggle ai_platform_key_enabled : a false + sans cle tenant -> /ai/status available=false (IA indisponible) ; re-activation OK. | I17: ✅ Passé | J17: Agents IA + live | K17: 24/06/2026 | O17: Corrections 23/06 | P17: Production
A18: AI-106 | B18: P2 — Haute | C18: IA hybride — outils (tool use) sur données tenant | D18: Le chat interroge les données réelles via outils, dans le périmètre du rôle. | E18: manager@sotra.ci (manager, « Chef Dépôt ») | F18: 1. Chat IA : « Combien d'absences dans mon équipe ce mois ? » 2. « Quel est le salaire de l'admin ? » | G18: Réponse 1 limitée à son équipe ; réponse 2 refusée (hors périmètre) ; aucune donnée d'un autre tenant | O18: Recette 10/2026 | P18: Production
A19: AI-107 | B19: P2 — Haute | C19: Clé et modèle IA par tenant | D19: Paramètres → IA (clé & modèle) ; clé chiffrée, repli plateforme. | E19: admin@sotra.ci | F19: 1. Saisir une clé API + modèle du catalogue 2. Enregistrer, poser une question 3. Supprimer la clé | G19: Chat utilise la clé tenant ; clé masquée ; sans clé → repli plateforme si autorisé (AI-105) | O19: Recette 10/2026 | P19: Production
A20: AI-108 | B20: P2 — Haute | C20: Simulation ITS via l'IA | D20: POST /ai/simulate-its. | E20: employe@sotra.ci (Kouassi Coulibaly) | F20: 1. Chat : « Combien d'ITS pour 450 000 brut, célibataire sans enfant ? » | G20: Réponse 70 500 FCFA cohérente avec le moteur (réforme 2024) | O20: Recette 10/2026 | P20: Production
A21: AI-109 | B21: P3 — Moyenne | C21: Référentiel droit — recherche d'articles | D21: /referentiels (search, tree, articles). | E21: employe@sotra.ci (Kouassi Coulibaly) | F21: 1. Référentiel Droit → rechercher « préavis » 2. Ouvrir un article | G21: Articles du pays de l'utilisateur, arborescence navigable | O21: Recette 10/2026 | P21: Production

Sheet REP
A1: REPORTING, ANALYTICS & VUE DG · 14 scénarios
A2: ID Test | B2: Priorité | C2: Titre du scénario | D2: Description / Contexte | E2: Prérequis / Données | F2: Étapes détaillées | G2: Résultat attendu | H2: Résultat obtenu | I2: Statut | J2: Testeur | K2: Date test | L2: Durée (min) | M2: Ticket / Requalification | N2: Commentaire / Amélioration | O2: Sprint | P2: Env.
A3: REP-001 | B3: P1 — Critique | C3: KPIs dashboard RH — valeurs correctes | D3: Effectifs, masse salariale FCFA, cotisations CNPS, postes ouverts | E3: Données seedées | F3: 1. Connecter admin 2. Observer /dashboard | G3: Valeurs cohérentes avec la base de données (ex: 80 employés SOTRA) | H3: GET /reporting/overview?year=2026 200 : activeEmployees=81 (~80 SOTRA), coherent BD. KPIs effectifs/masse salariale/CNPS. | I3: ✅ Passé | J3: Agents IA + live | K3: 24/06/2026 | O3: Sprint 1 | P3: Production
A4: REP-002 | B4: P1 — Critique | C4: Graphique évolution effectifs 12 mois | D4: LineChart | F4: 1. Observer graphique dashboard | G4: Courbe affichée, points par mois, valeurs cohérentes | H4: Evolution mensuelle : payrollEvolution avec employees_count par mois AJOUTE (15 mois) — serie effectifs disponible. | I4: ✅ Passé | J4: Agents IA + live | K4: 24/06/2026 | O4: Sprint 1 | P4: Production
A5: REP-003 | B5: P2 — Haute | C5: Répartition départements — BarChart | F5: 1. Observer BarChart dashboard | G5: Barres par département avec nombre d'employés, ordonné | H5: departments[] : 8 departements avec compteurs (BarChart), ordonne. | I5: ✅ Passé | J5: Agents IA + live | K5: 24/06/2026 | O5: Sprint 1 | P5: Production
A6: REP-004 | B6: P2 — Haute | C6: Cotisations CNPS mensuelles | D6: Total patronal + salarial du mois | F6: 1. KPI card CNPS 2. Vérifier la valeur du mois en cours | G6: Valeur = somme des cotisations des bulletins du mois sélectionné | H6: Cotisations CNPS : annualTotals.totalCnps=25 569 220 FCFA + total_cnps mensuel (somme bulletins du mois). | I6: ✅ Passé | J6: Agents IA + live | K6: 24/06/2026 | O6: Sprint 1 | P6: Production
A7: REP-005 | B7: P2 — Haute | C7: Taux absentéisme calculé | D7: % jours d'absence / jours ouvrables | F7: 1. KPI card absentéisme | G7: Taux affiché en %, calculé sur les absences approuvées | H7: absencesByType[] (3 types) -> taux absenteisme calcule sur absences approuvees (page Reporting). | I7: ✅ Passé | J7: Agents IA + live | K7: 24/06/2026 | O7: Sprint 1 | P7: Production
A8: REP-006 | B8: P2 — Haute | C8: Export rapport masse salariale | F8: 1. Reporting → Masse salariale → Exporter 2. Choisir période | G8: Excel/CSV téléchargé avec employé, brut, net, cotisations FCFA | H8: Export masse salariale : GET /payroll/livre-de-paie/2026/export 200 CSV (par employe : brut/net/cotisations FCFA, BOM UTF-8). | I8: ✅ Passé | J8: Agents IA + live | K8: 24/06/2026 | O8: Sprint 1 | P8: Production
A9: REP-007 | B9: P2 — Haute | C9: Insight IA — alerte rétention | D9: 3 alertes max sur le dashboard | E9: IA configurée | F9: 1. Observer la section 'Insights IA' du dashboard | G9: Maximum 3 alertes avec risque de départ, absentéisme, essais expirants | H9: GET /reporting/insights 200 (AJOUT recette) : max 3 alertes calculees sur donnees reelles (absenteisme/essais/echeance CNPS) -> panneau Insights IA dashboard. | I9: ✅ Passé | J9: Agents IA + live | K9: 24/06/2026 | O9: Sprint 1 | P9: Production
A10: REP-008 | B10: P3 — Moyenne | C10: Alerte CNPS à déclarer sur dashboard | E10: Après le 10 du mois | F10: 1. Observer le panneau alertes | G10: Alerte 'Déclaration CNPS à soumettre avant le 15' visible | H10: Alerte 'Declaration CNPS avant le 15' : carte dashboard + insight dynamique cnps_deadline (genere si jour <= 15). | I10: ✅ Passé | J10: Agents IA + live | K10: 24/06/2026 | O10: Sprint 1 | P10: Production
A11: REP-009 | B11: P1 — Critique | C11: Vue DG 360° — tableau de bord | D11: Module dg_view opt-in, rôle dg. | E11: dg_view activé ; dg@sotra.ci (rôle dg) | F11: 1. Se connecter dg@ 2. Vue 360° | G11: Indicateurs consolidés (effectif, masse salariale, absentéisme, recrutement) en lecture seule | O11: Recette 10/2026 | P11: Production
A12: REP-010 | B12: P2 — Haute | C12: Vue DG — activité des responsables | D12: GET /dg/activity et /dg/actors. | E12: dg@sotra.ci (rôle dg) | F12: 1. Activité des responsables 2. Filtrer par acteur | G12: Actions des responsables listées, aucune donnée sensible individuelle (salaire) exposée | O12: Recette 10/2026 | P12: Production
A13: REP-011 | B13: P1 — Critique | C13: Vue DG — RBAC et module désactivé | D13: dg_view désactivé ou rôle autre que dg. | E13: rh@sotra.ci (hr_manager, « Responsable Paie ») ; puis dg@ avec module désactivé | F13: 1. rh@ → GET /dg/overview 2. Désactiver dg_view, dg@ → Vue 360° | G13: rh@ → 403 ; module désactivé → 403 et entrée de menu absente | O13: Recette 10/2026 | P13: Production
A14: REP-012 | B14: P2 — Haute | C14: Rapport synthèse paie / absences / CNPS | D14: GET /reporting/payroll-summary, /absences, /cnps-analytics. | E14: rh@sotra.ci (hr_manager, « Responsable Paie ») | F14: 1. Reporting → onglets Paie, Absences, CNPS | G14: Chiffres cohérents avec les bulletins clôturés et les absences approuvées | O14: Recette 10/2026 | P14: Production
A15: REP-013 | B15: P2 — Haute | C15: Tableau de bord manager | D15: ManagerDashboard (équipe). | E15: manager@sotra.ci (manager, « Chef Dépôt ») | F15: 1. Tableau de bord | G15: KPIs de son équipe uniquement (effectif, absents du jour, demandes à valider) | O15: Recette 10/2026 | P15: Production
A16: REP-014 | B16: P2 — Haute | C16: Reporting — readonly | D16: Le rôle readonly consulte le reporting sans action. | E16: Compte readonly | F16: 1. Reporting 2. Tenter un export de paie | G16: Lecture OK ; aucune action d'écriture disponible | O16: Recette 10/2026 | P16: Production

Sheet SET
A1: PARAMÈTRES TENANT · 18 scénarios
A2: ID Test | B2: Priorité | C2: Titre du scénario | D2: Description / Contexte | E2: Prérequis / Données | F2: Étapes détaillées | G2: Résultat attendu | H2: Résultat obtenu | I2: Statut | J2: Testeur | K2: Date test | L2: Durée (min) | M2: Ticket / Requalification | N2: Commentaire / Amélioration | O2: Sprint | P2: Env.
A3: SET-001 | B3: P2 — Haute | C3: Modifier logo tenant | D3: Upload logo pour personnalisation | E3: Admin connecté | F3: 1. Paramètres → Apparence → Upload logo 2. Choisir image PNG 3. Sauvegarder | G3: Logo affiché dans la sidebar et sur la page login | H3: PATCH /settings/tenant {logo_url:data:image} 200 ; sélecteur de fichier logo (PNG/JPG -> data URL) ajouté à Apparence (aperçu, cap 1 Mo). Logo appliqué sidebar + login (/public/brand/by-slug). | I3: ✅ Passé | J3: Agents IA + live | K3: 24/06/2026 | O3: Sprint 1 | P3: Production
A4: SET-002 | B4: P2 — Haute | C4: Modifier couleur primaire/secondaire | F4: 1. Paramètres → Couleur primaire → Changer 2. Sauvegarder 3. Rafraîchir | G4: Nouvelle couleur appliquée à toute l'interface | H4: PATCH /settings/tenant {primary_color,secondary_color} 200, appliqué en direct (updateTenantConfig). | I4: ✅ Passé | J4: Agents IA + live | K4: 24/06/2026 | O4: Sprint 1 | P4: Production
A5: SET-003 | B5: P1 — Critique | C5: Gestion utilisateurs tenant — liste | D5: Admin peut voir tous les users du tenant | F5: 1. Paramètres → Utilisateurs | G5: Liste avec email, rôle, statut, date création | H5: GET /settings/users 200 : 8 utilisateurs (email, rôle, statut, date). | I5: ✅ Passé | J5: Agents IA + live | K5: 24/06/2026 | O5: Sprint 1 | P5: Production
A6: SET-004 | B6: P2 — Haute | C6: Invitation nouvel utilisateur | F6: 1. + Inviter 2. Email, rôle (dropdown) 3. Envoyer | G6: Email d'invitation envoyé, token d'invitation créé | H6: POST /settings/users 201 + email d'invitation (emailSent) + tempPassword filet. SÉCURITÉ : injection role='super_admin' à la création bloquée (400) — allowlist rôles tenant + Zod (OWASP A01). | I6: ✅ Passé | J6: Agents IA + live | K6: 24/06/2026 | O6: Sprint 1 | P6: Production
A7: SET-005 | B7: P2 — Haute | C7: Modification rôle utilisateur | F7: 1. Utilisateur → Modifier rôle → hr_officer | G7: Rôle mis à jour, permissions ajustées immédiatement | H7: PATCH /settings/users/:id {role} 200 (allowlist tenant ; super_admin refusé). | I7: ✅ Passé | J7: Agents IA + live | K7: 24/06/2026 | O7: Sprint 1 | P7: Production
A8: SET-006 | B8: P2 — Haute | C8: Désactivation utilisateur tenant | F8: 1. Utilisateur → Désactiver | G8: is_active = false, cet user ne peut plus se connecter | H8: PATCH /settings/users/:id {is_active:false} 200 — compte désactivé. | I8: ✅ Passé | J8: Agents IA + live | K8: 24/06/2026 | O8: Sprint 1 | P8: Production
A9: SET-101 | B9: P1 — Critique | C9: Rubrique de paie — type cotisation | D9: Cotisation salariale/patronale acceptée (valeur canonique) | E9: Admin connecté | F9: 1. /settings → Rubriques de paie → Ajouter 2. Type = Cotisation salariale 3. Enregistrer | G9: Rubrique créée, plus de 400 « type invalide » | H9: POST /settings/payroll-rules {type:employee_contribution,rate:0.063} 201. CORRECTIF : colonnes réelles label/formula (avant name/rate inexistantes -> 500 systématique) ; rate seul -> formule 'BRUT * 0.063'. | I9: ✅ Passé | J9: Agents IA + live | K9: 24/06/2026 | O9: Corrections 23/06 | P9: Production
A10: SET-102 | B10: P2 — Haute | C10: Taux AT saisi en décimal | D10: Le taux AT « 0.03 » (chaîne) est accepté | E10: Admin connecté | F10: 1. /settings → Général 2. Taux AT = 0.03 3. Enregistrer | G10: Enregistré, plus de 400 | H10: AT en décimal 0.03 accepté (POST /settings/legal-entities at_rate=0.0300, borne 0.02-0.05). | I10: ✅ Passé | J10: Agents IA + live | K10: 24/06/2026 | O10: Corrections 23/06 | P10: Production
A11: SET-103 | B11: P2 — Haute | C11: Entité juridique — forme SASU/SNC/ONG | D11: Formes juridiques CI proposées acceptées | E11: Admin connecté | F11: 1. Entités juridiques → Nouvelle 2. Forme = SASU 3. Enregistrer | G11: Entité créée, plus de 400 | H11: Forme juridique ONG/SASU/SNC acceptée (enum legal_form étendu) 201. | I11: ✅ Passé | J11: Agents IA + live | K11: 24/06/2026 | O11: Corrections 23/06 | P11: Production
A12: SET-104 | B12: P1 — Critique | C12: SMTP du tenant — configuration et email de test | D12: Paramètres → Général → Email : expéditeur + SMTP chiffré ; POST /settings/email/test. | E12: admin@sotra.ci | F12: 1. Saisir expéditeur, hôte, port, TLS, identifiants 2. Envoyer un email de test à son adresse 3. Mot de passe SMTP faux | G12: Email reçu avec l'expéditeur du tenant ; erreur claire si identifiants faux (attente bornée ≤ 8 s) ; mot de passe jamais renvoyé | O12: Recette 10/2026 | P12: Production
A13: SET-105 | B13: P2 — Haute | C13: Emails métier via SMTP du tenant | D13: Notifications (absence, invitation) envoyées par le SMTP tenant. | E13: SMTP tenant configuré | F13: 1. Soumettre une absence (employe@) 2. Inviter un utilisateur | G13: Emails envoyés depuis l'expéditeur tenant ; repli plateforme si SMTP tenant absent | O13: Recette 10/2026 | P13: Production
A14: SET-106 | B14: P2 — Haute | C14: Création utilisateur — retour immédiat sans F5 | D14: Fix : la création renvoie l'utilisateur même si l'email tarde. | E14: admin@sotra.ci | F14: 1. Utilisateurs → Nouveau → enregistrer | G14: Utilisateur visible immédiatement dans la liste ; mot de passe temporaire affiché si email non envoyé | O14: Recette 10/2026 | P14: Production
A15: SET-107 | B15: P2 — Haute | C15: Réinitialisation du mot de passe d'un utilisateur | D15: POST /settings/users/:id/reset-password. | E15: admin@sotra.ci | F15: 1. Utilisateur → Réinitialiser le mot de passe | G15: Mot de passe temporaire / email envoyé, changement forcé au prochain login, audit | O15: Recette 10/2026 | P15: Production
A16: SET-108 | B16: P2 — Haute | C16: Suppression d'un utilisateur | D16: DELETE /settings/users/:id. | E16: admin@sotra.ci | F16: 1. Supprimer un utilisateur de test 2. Tenter de se supprimer soi-même | G16: Utilisateur supprimé ; auto-suppression refusée | O16: Recette 10/2026 | P16: Production
A17: SET-109 | B17: P2 — Haute | C17: Départements — CRUD | D17: Paramètres → Départements. | E17: admin@sotra.ci | F17: 1. Créer « Maintenance » 2. Renommer 3. Supprimer un département avec employés | G17: CRUD OK ; suppression d'un département non vide refusée avec message | O17: Recette 10/2026 | P17: Production
A18: SET-110 | B18: P2 — Haute | C18: Éléments variables — saisie et suppression | D18: Paramètres / Paie → éléments variables du mois. | E18: rh@sotra.ci (hr_manager, « Responsable Paie ») | F18: 1. Ajouter une prime de 15 000 à un salarié pour 2026-10 2. Supprimer 3. Tenter sur une période clôturée | G18: Ajout/suppression OK ; période clôturée → refus | O18: Recette 10/2026 | P18: Production
A19: SET-111 | B19: P1 — Critique | C19: Reprise de données — import et génération des comptes | D19: Paramètres → Reprise de données (import/:type, generate-users). | E19: admin@sotra.ci | F19: 1. Importer un fichier employés modèle 2. Générer les comptes utilisateurs 3. Consulter le statut | G19: Lignes valides importées, erreurs ligne par ligne ; comptes créés sans doublon ; statut de génération affiché | O19: Recette 10/2026 | P19: Production
A20: SET-112 | B20: P2 — Haute | C20: Paramètres Workflow — niveaux absences et notes de frais | D20: PATCH /settings/workflow (levels_count, SLA, valideur RH désigné). | E20: admin@sotra.ci | F20: 1. Workflow → Absences : 2 niveaux, SLA 1 j/niveau, RH 2 j 2. Notes de frais : 1 niveau 3. Valeurs invalides (0 niveau) | G20: Configuration persistée et appliquée aux nouvelles demandes ; valeurs invalides → 400 | O20: Recette 10/2026 | P20: Production

Sheet RBA
A1: CONTRÔLE D'ACCÈS (RBAC) · 15 scénarios
A2: ID Test | B2: Priorité | C2: Titre du scénario | D2: Description / Contexte | E2: Prérequis / Données | F2: Étapes détaillées | G2: Résultat attendu | H2: Résultat obtenu | I2: Statut | J2: Testeur | K2: Date test | L2: Durée (min) | M2: Ticket / Requalification | N2: Commentaire / Amélioration | O2: Sprint | P2: Env.
A3: RBA-001 | B3: P1 — Critique | C3: super_admin ne peut pas accéder /dashboard | D3: Redirection /platform/dashboard | E3: superadmin connecté | F3: 1. Naviguer vers /dashboard | G3: Redirection automatique vers /platform/dashboard, pas d'erreur | H3: super_admin : redirectTo='/platform/dashboard' au login + 403 sur les données tenant (GET /employees) — jamais l'interface RH. | I3: ✅ Passé | J3: Agents IA + live | K3: 24/06/2026 | O3: Sprint 1 | P3: Production
A4: RBA-002 | B4: P1 — Critique | C4: admin d'un tenant ne peut pas accéder /platform/* | D4: 403 ou redirection | E4: admin@sotra.ci connecté | F4: 1. Tenter /platform/tenants | G4: 403 Forbidden ou redirection /dashboard, jamais l'interface super admin | H4: admin tenant : GET /platform/tenants -> 403 (jamais l'interface super_admin). | I4: ✅ Passé | J4: Agents IA + live | K4: 24/06/2026 | O4: Sprint 1 | P4: Production
A5: RBA-003 | B5: P1 — Critique | C5: employee tente /employees → redirigé /mon-espace | D5: Guard RoleGuard actif | E5: employe@sotra.ci | F5: 1. URL directe /employees | G5: Redirection automatique /mon-espace | H5: employee : GET /employees -> 403 (UI redirige /mon-espace via guard). | I5: ✅ Passé | J5: Agents IA + live | K5: 24/06/2026 | O5: Sprint 1 | P5: Production
A6: RBA-004 | B6: P1 — Critique | C6: hr_officer ne peut pas clôturer la paie | D6: Action non disponible dans l'UI | E6: hr_officer connecté | F6: 1. Accéder /payroll 2. Chercher le bouton Clôturer | G6: Bouton absent ou désactivé, API retourne 403 si tenté directement | H6: hr_officer : POST /payroll/periods/:m/close -> 403 (clôture réservée admin/hr_manager). | I6: ✅ Passé | J6: Agents IA + live | K6: 24/06/2026 | O6: Sprint 1 | P6: Production
A7: RBA-005 | B7: P1 — Critique | C7: manager ne voit que son équipe | D7: Filtrage automatique | E7: manager@sotra.ci lié à Exploitation | F7: 1. Accéder /employees depuis manager | G7: Seuls les 30 employés Exploitation listés (pas les 80 SOTRA) | H7: manager : GET /employees ne renvoie QUE l'équipe directe (30 Exploitation, pas les 81). CORRECTIF : filtre via employeeId du token (email non unique faussait l'équipe). | I7: ✅ Passé | J7: Agents IA + live | K7: 24/06/2026 | O7: Sprint 1 | P7: Production
A8: RBA-006 | B8: P2 — Haute | C8: readonly — aucune modification possible | D8: Tous les boutons d'édition absents | E8: Utilisateur rôle readonly | F8: 1. Connecter 2. Tenter toute modification | G8: 403 sur toutes les routes PUT/POST/DELETE, UI en lecture seule | H8: readonly : aucune route d'écriture ne liste 'readonly' dans authorize -> lecture seule par construction (OWASP A01). | I8: ✅ Passé | J8: Agents IA + live | K8: 24/06/2026 | O8: Sprint 1 | P8: Production
A9: RBA-007 | B9: P1 — Critique | C9: Isolation multi-tenant — token cross-tenant | D9: Token SOTRA ne donne pas accès aux données Cabinet | E9: Token SOTRA JWT | F9: 1. Utiliser le token SOTRA pour appeler /api/employees avec schéma cabinet | G9: 403 ou données du bon schéma uniquement, jamais de fuite cross-tenant | H9: Isolation multi-tenant : le schéma vient du JWT SIGNÉ (non forgeable) ; un token SOTRA ne voit que SOTRA, aucune fuite cross-tenant. | I9: ✅ Passé | J9: Agents IA + live | K9: 24/06/2026 | O9: Sprint 1 | P9: Production
A10: RBA-008 | B10: P1 — Critique | C10: manager_scope = direct — équipe directe seulement | D10: Périmètre manager direct (N-1). | E10: Tenant en manager_scope=direct ; manager@ a des N-1 qui ont eux-mêmes des N-1 | F10: 1. manager@ → Employés, Absences, Notes de frais | G10: Seuls les collaborateurs directs apparaissent | O10: Recette 10/2026 | P10: Production
A11: RBA-009 | B11: P1 — Critique | C11: manager_scope = hierarchy — toute la ligne hiérarchique | D11: Périmètre hiérarchique complet (lu côté SQL). | E11: Tenant en manager_scope=hierarchy | F11: 1. manager@ → Employés 2. Appeler GET /employees/:id d'un N-2 puis d'un salarié hors ligne | G11: N-1 et N-2 visibles ; hors ligne → 403/404 | O11: Recette 10/2026 | P11: Production
A12: RBA-010 | B12: P1 — Critique | C12: Rôle dg — lecture seule 360° | D12: Le DG ne peut rien modifier. | E12: dg@sotra.ci (rôle dg) | F12: 1. Tenter PATCH /employees/:id, POST /payroll/periods/2026-10 | G12: 403 sur toutes les écritures | O12: Recette 10/2026 | P12: Production
A13: RBA-011 | B13: P1 — Critique | C13: Rôle raf_site — limité à sa filiale | D13: Le RAF de site ne voit que sa filiale. | E13: Compte raf_site d'une filiale | F13: 1. Paie de ma filiale 2. Appeler une période d'une autre filiale | G13: Accès limité à sa filiale ; autre filiale → 403 | O13: Recette 10/2026 | P13: Production
A14: RBA-012 | B14: P1 — Critique | C14: Nouveaux modules — matrice des rôles | D14: Discipline (admin/hr_mgr/hr_off), Succession, Calibrage, Climat (lecture readonly), Mobilités (décision admin/hr_mgr), Sécurité (admin). | E14: Comptes admin, rh, chef.perso, manager, employe, readonly | F14: 1. Pour chaque module, appeler les routes de lecture/écriture/suppression avec chaque rôle | G14: Conforme aux constantes READ/WRITE/DELETE de chaque module ; employé → 403 sur toutes les routes RH ; suppressions réservées admin/hr_manager | O14: Recette 10/2026 | P14: Production
A15: RBA-013 | B15: P1 — Critique | C15: Isolation tenant — nouveaux modules | D15: Un id d'un autre tenant ne doit jamais être accessible. | E15: Ids de discipline/succession/offboarding/signature du tenant Cabinet Expertise | F15: 1. Avec admin@sotra.ci, appeler GET /discipline/:id, /offboarding/:id, /signature/requests/:id avec ces ids | G15: 404 systématique (schéma du tenant issu du jeton), aucune fuite | O15: Recette 10/2026 | P15: Production
A16: RBA-014 | B16: P1 — Critique | C16: Module désactivé — 403 côté API | D16: Defense in depth : l'UI masque, l'API refuse. | E16: Module discipline désactivé pour SOTRA | F16: 1. Appeler GET /discipline avec admin@ (jeton valide) | G16: 403 { moduleDisabled: true } | O16: Recette 10/2026 | P16: Production
A17: RBA-015 | B17: P2 — Haute | C17: Promotion de rôle — effet immédiat | D17: Changement de rôle pris en compte au prochain jeton. | E17: employé promu manager | F17: 1. Admin change le rôle 2. L'utilisateur rafraîchit sa session | G17: Nouveaux droits actifs, anciens retirés | O17: Recette 10/2026 | P17: Production

Sheet ESP
A1: ESPACE EMPLOYEE (SELF-SERVICE) · 16 scénarios
A2: ID Test | B2: Priorité | C2: Titre du scénario | D2: Description / Contexte | E2: Prérequis / Données | F2: Étapes détaillées | G2: Résultat attendu | H2: Résultat obtenu | I2: Statut | J2: Testeur | K2: Date test | L2: Durée (min) | M2: Ticket / Requalification | N2: Commentaire / Amélioration | O2: Sprint | P2: Env.
A3: ESP-001 | B3: P1 — Critique | C3: Dashboard /mon-espace — soldes congés affichés | D3: Barres de progression colorées | E3: employe@sotra.ci connecté, soldes seedés | F3: 1. Connecter employe 2. Observer /mon-espace | G3: CP, Maladie affichés avec jours acquis/pris/restants, barres colorées | H3: GET /absences/balances 200 : soldes CP/Maladie (acquis/pris/restant) + barres colorées (MonEspace). | I3: ✅ Passé | J3: Agents IA + live | K3: 24/06/2026 | O3: Sprint 1 | P3: Production
A4: ESP-002 | B4: P1 — Critique | C4: Badge 'Nouveau' bulletin — /mon-espace | E4: Bulletin non consulté | F4: 1. Observer /mon-espace après génération d'un nouveau bulletin | G4: Badge 'Nouveau' visible sur le bulletin le plus récent | H4: GET /payroll/my-payslips 200 : badge 'Nouveau' sur bulletin non consulté (viewed_by_employee_at null). | I4: ✅ Passé | J4: Agents IA + live | K4: 24/06/2026 | O4: Sprint 1 | P4: Production
A5: ESP-003 | B5: P1 — Critique | C5: Sidebar réduite — 5 items seulement | D5: Mon espace, Absences, Bulletins, Frais, Formation, Profil | E5: employe connecté | F5: 1. Observer la sidebar | G5: Exactement 6 items, aucun lien vers /employees, /payroll global, /recruitment | H5: Sidebar employé (EmployeeLayout) : 100% /mon-espace/* — AUCUN lien /employees, /payroll, /recruitment (sécurité OK). NB : 10 items self-service (intégration/carrière/offres/climat ajoutés) au lieu des 6 d'origine. | I5: ✅ Passé | J5: Agents IA + live | K5: 24/06/2026 | O5: Sprint 1 | P5: Production
A6: ESP-004 | B6: P2 — Haute | C6: Mon profil — modification téléphone | F6: 1. /mon-espace/profil → Modifier téléphone 2. Sauvegarder | G6: Téléphone mis à jour, Mobile Money provider visible | H6: PATCH /employees/:id (son propre dossier) 200 : téléphone + Mobile Money modifiables ; édition d'un AUTRE dossier -> 403 (IDOR/A01). | I6: ✅ Passé | J6: Agents IA + live | K6: 24/06/2026 | O6: Sprint 1 | P6: Production
A7: ESP-005 | B7: P2 — Haute | C7: Mon profil — changement de mot de passe | F7: 1. Saisir ancien mot de passe 2. Nouveau + confirmation 3. Sauvegarder | G7: Mot de passe changé, session maintenue | H7: POST /auth/change-password : ancien mot de passe vérifié (400 si incorrect), session conservée (JWT non rotaté). | I7: ✅ Passé | J7: Agents IA + live | K7: 24/06/2026 | O7: Sprint 1 | P7: Production
A8: ESP-006 | B8: P2 — Haute | C8: Mes 3 dernières absences affichées | D8: Sur le dashboard /mon-espace | F8: 1. Observer la section absences du dashboard | G8: 3 dernières absences avec badge statut coloré | H8: GET /absences/my-absences 200 : 3 dernières absences + badge statut coloré. | I8: ✅ Passé | J8: Agents IA + live | K8: 24/06/2026 | O8: Sprint 1 | P8: Production
A9: ESP-007 | B9: P2 — Haute | C9: Formations recommandées — 2 cards | F9: 1. Observer la section formation du dashboard | G9: 2 cards de formations affichées | H9: Section 'Formations recommandées' (2 cards) AJOUTÉE au dashboard /mon-espace (GET /training/catalog). | I9: ✅ Passé | J9: Agents IA + live | K9: 24/06/2026 | O9: Sprint 1 | P9: Production
A10: ESP-008 | B10: P1 — Critique | C10: Accès /mon-espace/bulletins | D10: Liste des 24 derniers bulletins | F10: 1. /mon-espace/bulletins | G10: Liste avec mois, net payable FCFA, statut, bouton télécharger PDF | H10: GET /payroll/my-payslips 200 : mois, net payable FCFA, statut, bouton Télécharger PDF (GET /my-payslips/:id/pdf). | I10: ✅ Passé | J10: Agents IA + live | K10: 24/06/2026 | O10: Sprint 1 | P10: Production
A11: ESP-009 | B11: P1 — Critique | C11: Mes validations — vue valideur | D11: /validations : demandes à traiter avec échéance. | E11: manager@sotra.ci (manager, « Chef Dépôt ») avec une absence d'équipe en attente | F11: 1. Menu Mes validations 2. Approuver depuis la liste | G11: Demande listée avec échéance et étape ; décision appliquée ; ses propres demandes n'y figurent pas | O11: Recette 10/2026 | P11: Production
A12: ESP-010 | B12: P2 — Haute | C12: Mes pointages | D12: Mon espace → Pointages (attendance/me). | E12: employe@sotra.ci (Kouassi Coulibaly) ; module Pointage actif | F12: 1. Mon espace → Pointages | G12: Ses journées pointées (arrivée, départ, retards) uniquement | O12: Recette 10/2026 | P12: Production
A13: ESP-011 | B13: P2 — Haute | C13: Mes avertissements — répondre | D13: Mon espace → Avertissements (warnings respond). | E13: employe@sotra.ci (Kouassi Coulibaly) avec un avertissement de retard | F13: 1. Ouvrir l'avertissement → Répondre (justification) | G13: Réponse enregistrée, visible RH ; impossible de répondre à l'avertissement d'un autre | O13: Recette 10/2026 | P13: Production
A14: ESP-012 | B14: P2 — Haute | C14: Mon intégration (onboarding) | D14: Mon espace → Intégration (my-journey). | E14: employe@sotra.ci (Kouassi Coulibaly) (parcours avec étape en retard) | F14: 1. Ouvrir le parcours 2. Cocher une étape qui lui est assignée | G14: Étapes affichées avec échéances, retard signalé ; seules ses étapes sont modifiables | O14: Recette 10/2026 | P14: Production
A15: ESP-013 | B15: P2 — Haute | C15: Mon climat — répondre à une enquête | D15: Mon espace → Climat (my-surveys). | E15: employe@sotra.ci (Kouassi Coulibaly) ; enquête ouverte | F15: 1. Répondre à l'enquête 2. Tenter de répondre une 2e fois | G15: Réponse anonyme enregistrée ; 2e réponse refusée | O15: Recette 10/2026 | P15: Production
A16: ESP-014 | B16: P2 — Haute | C16: Mes notes de frais | D16: Mon espace → Frais. | E16: employe@sotra.ci (Kouassi Coulibaly) | F16: 1. Créer, soumettre, suivre le circuit de validation | G16: Étape courante du circuit affichée (N+1, RH…) ; ses notes uniquement | O16: Recette 10/2026 | P16: Production
A17: ESP-015 | B17: P2 — Haute | C17: Mes signatures | D17: Demandes de signature où l'employé est signataire. | E17: employe@sotra.ci (Kouassi Coulibaly) | F17: 1. Signature → Mes demandes → Signer | G17: Document signé, horodatage/IP audités ; refus possible avec motif | O17: Recette 10/2026 | P17: Production
A18: ESP-016 | B18: P2 — Haute | C18: Langue de l'interface FR/EN | D18: Sélecteur de langue partout. | E18: employe@sotra.ci (Kouassi Coulibaly) | F18: 1. Basculer EN dans l'en-tête 2. Parcourir Mon espace 3. Recharger | G18: Tous les libellés traduits (pas de clé brute), choix mémorisé | O18: Recette 10/2026 | P18: Production

Sheet WF
A1: WORKFLOWS & VALIDATIONS · 13 scénarios
A2: ID Test | B2: Priorité | C2: Titre du scénario | D2: Description / Contexte | E2: Prérequis / Données | F2: Étapes détaillées | G2: Résultat attendu | H2: Résultat obtenu | I2: Statut | J2: Testeur | K2: Date test | L2: Durée (min) | M2: Ticket / Requalification | N2: Commentaire / Amélioration | O2: Sprint | P2: Env.
A3: WF-001 | B3: P1 — Critique | C3: Absence — circuit 1 niveau (N+1 → RH) | D3: workflow_configs.levels_count = 1. | E3: Paramètres → Workflow → Absences = 1 niveau | F3: 1. employe@ demande 2 j de CP 2. manager@ (N+1) vise 3. rh@ approuve | G3: Statut passe « Visa N+1 » puis « Approuvée » ; solde décompté à l'approbation RH uniquement | O3: Recette 10/2026 | P3: Production
A4: WF-002 | B4: P1 — Critique | C4: Absence — circuit 2 niveaux (N+1 → N+2 → RH) | D4: Visas hiérarchiques successifs. | E4: Workflow absences = 2 niveaux ; N+2 existant | F4: 1. Demande employe@ 2. N+1 vise 3. rh@ tente d'approuver avant N+2 4. N+2 vise, rh@ approuve | G4: rh@ ne voit pas la demande (ou ne peut pas agir) tant que N+2 n'a pas visé ; ensuite approbation OK | O4: Recette 10/2026 | P4: Production
A5: WF-003 | B5: P2 — Haute | C5: Absence — niveau hiérarchique inexistant sauté | D5: Pas de N+2 → étape sautée. | E5: Workflow 2 niveaux ; salarié dont le N+1 n'a pas de manager | F5: 1. Demande 2. N+1 vise | G5: Demande passe directement à la RH | O5: Recette 10/2026 | P5: Production
A6: WF-004 | B6: P2 — Haute | C6: Absence saisie par le responsable — vaut visa | D6: Un responsable qui saisit pour son équipe vaut visa de son niveau. | E6: manager@sotra.ci (manager, « Chef Dépôt ») | F6: 1. manager@ saisit une absence pour un N-1 | G6: Étape N+1 marquée visée automatiquement, demande chez le niveau suivant | O6: Recette 10/2026 | P6: Production
A7: WF-005 | B7: P1 — Critique | C7: Personne ne valide sa propre demande | D7: RH et managers sont aussi des salariés. | E7: rh@ dépose une absence pour lui-même | F7: 1. rh@ ouvre Mes validations 2. Tente PATCH /absences/:id/approve sur sa demande | G7: Sa demande n'apparaît pas ; API 403 | O7: Recette 10/2026 | P7: Production
A8: WF-006 | B8: P1 — Critique | C8: Refus à une étape hiérarchique | D8: Le refus d'un N+1 clôt la demande. | E8: Demande au niveau N+1 | F8: 1. manager@ refuse avec motif | G8: Statut « Refusée », motif visible par le salarié, notification, solde non décompté | O8: Recette 10/2026 | P8: Production
A9: WF-007 | B9: P1 — Critique | C9: Note de frais — circuit N+1 → RH | D9: Visibilité RH dès la soumission en lecture seule. | E9: Workflow frais = 1 niveau | F9: 1. employe@ soumet une note 2. rh@ consulte Mes validations 3. manager@ vise 4. rh@ approuve | G9: rh@ voit la note en lecture seule avant le visa, actionnable après ; statut final « approuvée » | O9: Recette 10/2026 | P9: Production
